Workbook
Name _Hlk99048333: '17025 SAL'!$B$179

Sheet INICIO
A1: Directorio OEC | J1: Código No. : | K1: Páginas:
J2: ECA-MP-P09-F03 | K2: Página: 1 de 10
J3: Fecha de entrada en vigencia | K3: Versión:
J4: 45503 | K4: 4

Sheet 17025 SAL
B1: Norma de Referencia: INTE ISO/IEC 17025:2017 Requisitos generales para la competencia de laboratorios de ensayo y calibración | AN1: =4*365 -> 1460
A2: Nombre del OEC | B2: Nombre Razón social | C2: Tipo OEC | D2: Estatus | E2: Sector | F2: # Expediente | G2: # Acreditación | H2: Fecha firma de contrato | I2: Renovación de contrato | J2: Fecha de Otorgamiento | K2: Resumen fecha ampliaciones | L2: Nombre Representante ECA | M2: Email para notificaciones (oficial) | N2: Email alternativos (copias de comunicación) | O2: Teléfono | P2: Fax | Q2: País | R2: Dirección | S2: Provincia | T2: Cédula Jurídica | U2: Sitio Web | V2: Representante Legal | W2: # Identificación | X2: Estado Civil | Y2: Nacionalidad | Z2: Profesión | AA2: Dirección para recibir notificaciones | AB2: Correo electrónico | AC2: Cargo dentro del OEC: | AD2: Contacto Dpto. de Facturación/ Cobro | AE2: Nombre | AF2: Teléfono2 | AG2: Dirección3 | AH2: Fax4 | AI2: Email | AJ2: Horario | AK2: Empresa | AL2: Observaciones
A3: AGQ Costa Rica S.A. | B3: AGQ Costa Rica S.A. | C3: LE | D3: A | E3: Privado | F3: LE-002 | G3: LE-002 | H3: 45128 | I3: ='17025 SAL'!$H3+$AN$1 -> 46588 | J3: 35536 | L3: Jeisson Cárdenas | M3: jeisson.cardenas@agqlabs.com | N3: noelia.lopez@agqlabs.com, andres.villalobos@agqlabs.com, David.solorzano@agqlabs.com | O3: 2286-1168 | P3: 2286-1168 | Q3: Costa Rica | R3: San José, de la Iglesia 100 m oeste, 75 m norte y 75 m oeste, Barrio Los Álamos, San Francisco de Dos Ríos | S3: San José | T3: 3-101-74595 | U3: https://agqlabs.cr/ | V3: Andrés Villalobos Herrera | W3: 1-0984-0656 | X3: Casado | Y3: Costarricense | Z3: Ingeniero agronomo | AA3: San José, San Francisco de Dos Ríos, de la escuela República Dominicana 50 m norte y 75 m oeste | AB3: andres.villalobos@agqlabs.com | AC3: Gerente General | AD3: Romario Masis Valle | AE3: AGQ Costa Rica S.A. | AF3: 2286-1168 | AG3: San José, de la Iglesia 100 oeste, 75 norte y 75 oeste, Barrio Los Álamos, San Francisco de Dos Ríos | AH3: 2286-1168 | AI3: facturae-cr@agqlabs.com | AJ3: 8 am A 6 pm | AK3: AGQ Costa Rica S.A. | AL3: Cambio en razón social, ahora es AGQ Costa Rica
A4: Laboratorio Químico AQYLA S.A. | B4: Asesorías Químicas AQYLA Sociedad Anónima | C4: LE | D4: A | E4: Privado | F4: LE-003 | G4: LE-003 | H4: 45859 | I4: No aplica | J4: 35879 | L4: Elizabeth Mojica Araya | M4: aqylasa@ice.co.cr | N4: emojica.aqylasa@hotmail.com | O4: 22723159 | P4: 22723159 | Q4: Costa Rica | R4: San José, 25 m Sur de Esquina Sur Oeste del Parque, Curridabat. | S4: San José | T4: 3-101-093975-35 | U4: =HYPERLINK("http://www.labaqylasa.com/","www.labaqylasa.com ") -> www.labaqylasa.com | V4: Lic Leonor Rodriguez Montero | W4: 1-418-303 | X4: Soltera | Y4: Costarricense | Z4: Lic Quimica | AA4: San José, 25 Sur de Esquina Sur Oeste del Parque, Curridabat. | AC4: Directora Técnica | AD4: Lic Elizabeth Mojica | AE4: Asesorias Quimicas Aqylasa | AF4: 22723159 | AG4: San José, 25 Sur de Esquina Sur Oeste del Parque, Curridabat. | AH4: 22723159 | AI4: =HYPERLINK("mailto:aqylasa@ice.co.cr","aqylasa@ice.co.cr ") -> aqylasa@ice.co.cr | AJ4: 8Am a 5 pm | AK4: AQYLA S.A | AL4: Suspensión parcial voluntario del 08/03/2024 al 08/03/2025
A5: Laboratorio del Centro de Investigación y de Servicios Químicos y Microbiológicos- CEQIATEC | B5: Instituto Tecnológico de Costa Rica | C5: LE | D5: A | E5: Académico | F5: LE-004 | G5: LE-004 | H5: 45414 | I5: ='17025 SAL'!$H5+$AN$1 -> 46874 | J5: 36707 | L5: Federico Masís Meléndez / Adrián Flores | M5: fmasis@itcr.ac.cr | N5: aflores@tec.ac.cr; aflores@itcr.ac.cr | O5: 2550-2368 | P5: 2591-5147 | Q5: Costa Rica | R5: Cartago, 400 este, Estadio Fello Meza, Edificio Núcleo integrado de escuela de Química e Ingeniería Ambiental" (Sede Central I.T.C.R.) | S5: Cartago | T5: 4000-042145-07 | U5: =HYPERLINK("http://www.tec.ac.cr/","www.tec.ac.cr") -> www.tec.ac.cr | V5: María Estrada Sánchez | AA5: Cartago, 400 este, Estadio Fello Meza, (Sede Central I.T.C.R.) | AC5: Rector | AD5: Noemy Quirós Bustos | AE5: Fundatec | AF5: 2550-2368 | AG5: Cartago, 400 este, Estadio Fello Meza, Edificio Núcleo integrado de escuela de Química e Ingeniería Ambiental" (Sede Central I.T.C.R.) | AH5: 25915147 | AI5: =HYPERLINK("mailto:ceqiatec@itcr.ac.cr","ceqiatec@itcr.ac.cr") -> ceqiatec@itcr.ac.cr | AJ5: 7:30 a.m. a 12:00 md y de 1:00 a 4:30 p.m. | AK5: ITCR | AL5: 18.02.2019 Reducción voluntaria para los ensayos PT-QU-3, cloruros, PT-QU-5, fluoruros y PT-QU-6, nitratos. / 07.06.2017 reducción del ensayo recuento heterotrofo en placa para agua /23.01.2017 reducción de alcance para el ensayo físico químico en agua residual: demanda química de oxígeno / 12.04.2016 reducción de alcance para los metodos PT-QUI-02-08 para determinación de sulfato en agua, PT-QUI-02-09 para determinación de cromo en agua, Método desarrollado en laboratorio (PT-QUI-03). Cromatografía de gases. Extracción en fase sólida para determinación de residuos de plaguicidas organofosforados en Leche, Método no normalizado, modificado (Application, Note 64, Sigma-Aldrich Co. 1997) (PT-QUI-03) Cromatografía de gases Extracción en fase sólida para determinación de Residuo de plaguicidas organofosforados y organoclorados en agua potable y residual, Método desarrollado en laboratorio (PT-QUI-03). Cromatografía de gases. Extracción en fase sólida para la determinación de Residuo de plaguicidas organofosforados en Frutas y vegetales (banano, piña, mango, camote, chile dulce, chayote) / 01.07.2014 para pruebas de esterilidad para controles biológicos en dispositivos de control de procesos de esterilización
A6: Laboratorio de Ensayos Conducen | B6: CONDUCEN SOCIEDAD DE RESPONSABILIDAD LIMITADA | C6: LE | D6: A | E6: Privado | F6: LE-006 | G6: LE-006 | H6: 43909 | I6: ='17025 SAL'!$H6+$AN$1 -> 45369 | J6: 37882 | L6: Juan Arias Araya | M6: juan.arias@prysmiangroup.com | N6: nikol.castillo@prysmiangroup.com edwin.hernandez@prysmiangroup.com | O6: 22984800 | P6: No aplica | Q6: Costa Rica | R6: Carretera Interamericana Norte, frente a Real Cariari. PROVINCIA 04 HEREDIA, CANTON 07 BELEN, SAN ANTONIO, KILOMETRO 11.5 AUTOPISTA GENERAL CAÑAS, INTERSECCION SAN ANTONIO. | S6: Heredia | T6: 3102011928 | U6: https://central-america.prysmian.com/es | V6: Adriana de lo Ángeles Delgado Castillo | W6: 1-1268-0188 | X6: Casado | Y6: Costarricense | Z6: Administradora de Empresas | AA6: Carretera Interamericana Norte, frente a Real Cariari. PROVINCIA 04 HEREDIA, CANTON 07 BELEN, SAN ANTONIO, KILOMETRO 11.5 AUTOPISTA GENERAL CAÑAS, INTERSECCION SAN ANTONIO. | AB6: adriana.delgado@prysmian.com | AC6: Directora Financiera | AD6: Depto. Crédito y Cobro. | AE6: Depto. Crédito y Cobro. | AF6: No aplica | AG6: Carretera Interamericana Norte, frente a Real Cariari. PROVINCIA 04 HEREDIA, CANTON 07 BELEN, SAN ANTONIO, KILOMETRO 11.5 AUTOPISTA GENERAL CAÑAS, INTERSECCION SAN ANTONIO. | AI6: luisfernando.roman@prysmian.com | AJ6: 8 am a 5:30 pm | AK6: CONDUCEN | AL6: 4/8/25: Se actualizan datos de contacto para facturación y datos del representante legal 15.07.2016 reducción de alcance para el ensayo visual en alambres, cables cordones desnudos con aislamiento area transversal 0,205mm2 para la determinación del marcado del producto / 27.05.2016 DETERMINACIÓN DE LA CANTIDAD DE HUMOS y DETERMINACIÓN DE LA CANTIDAD DE GAS ÁCIDO HALOGENADO en Alambres, Cable, Cordones desnudos o con aislamiento y/o cubiertas con Área de sección transversal de 0,205 mm² a 507,0 mm² (Alcance Original) / Antes de enviar una factura deben enviar una cotizacion del servicio brindado.
A7: Laboratorio del Centro de Investigación en Contaminación Ambiental-CICA | B7: Universidad de Costa Rica | C7: LE | D7: A | E7: Académico | F7: LE-007 | G7: LE-007-R01 | H7: 45147 | I7: ='17025 SAL'!$H7+$AN$1 -> 46607 | J7: 36707 | L7: Johan Molina Delgado | M7: calidad.cica@ucr.ac.cr | O7: 2511-8208 | P7: N/A | Q7: Costa Rica | R7: San José, Cuidad Universitaria Rodrigo Facio, atrás de la biblioteca de salud, San Pedro de Montes de Oca. | S7: San José | T7: 3-006101757 | U7: https://cica.ucr.ac.cr/ | V7: Carlos Araya Leandro | W7: 3-0305-0948 | X7: Casado | Y7: Costarricense | Z7: Doctor en Economía, Gestión y Control de Entidades y Políticas Públicas. | AA7: San José, Sede Univesitaria Rodrigo Facio, Edificio Administrativo B, Segundo Piso, Oficina de Rectoría, San Pedro de Montes de Oca. | AC7: Rector Universidad de Costa Rica | AD7: María Soledad Vanegas Avilés | AE7: FUNDEVI | AF7: 25118205 | AG7: San José, Cuidad Universitaria Rodrigo Facio, atrás de la biblioteca de salud, San Pedro de Montes de Oca. | AH7: 2253-1363 | AI7: =HYPERLINK("mailto:maria.vanegas.aviles@gmail.com","maria.vanegas.aviles@gmail.com ") -> maria.vanegas.aviles@gmail.com | AJ7: 8:00-12:00 y 13:00-17:00 | AK7: UCR | AL7: 12.04.2016 Reducción de alcance para el metodo de referencia MAR-14 para la determinación del ensayo Mancozeb en rroz, apio, banano, brócoli, cebolla, chile, coliflor, culantro, chayote, camote, espinaca, frijoles, fresa, granadilla, lechuga, limón, melón, mora, minivegetales, mango, manzana, naranja, ñame, pepino, pera, papa, piña, papaya, repollo, sandía, tomate, tiquisque, vainica, yuca y zanahoria / Reducción de alcance 12.05.2015 analitos del ensayo “MAR-05: Determinación de residuos de plaguicidas en alimentos por cromatografía de gases”de los analitos: Diazinón, Forato, Terbufós, Acefato, Clorotalonil y Foxim. Reducción de alcance 28.04.2015 para el ensayo: “MAQA-19: Determinación de metales por absorción atómica utilizando horno de grafito (GFAAS) para los elementos antimonio, selenio y estaño” 24.02.2015 Reducción de alcance para los ensayos MAR 5: Determinación de residuos de plaguicidas por cromatografía de gases: Causafos, Fenamifos, Metamidofos, Triadimefon, Triazofós, Deltametrina. 16.12.2014 Reducción de alcance para los ensayos MACA-17 Determinación de la concentración de gases O2, CO2, CO, SO2, NO, NO2 y NOx, en los gases de escape de una fuente fija EPA CTM-034. MACA-07 Partículas suspendidas en aire PM-10. Determinación de la concentración de partículas respirables (PM-10). 10.06.2014. Suspensión voluntaria parcial del alcance del 10.06.2014 al 10.12.2014 para los ensayos: determinación de gases O2, CO2, CO, SO2, NO, NO2 y NOx, en los gases de escape de una fuente fija EPA CTM-034. 27.05.2014 1. MAR-1 Determinación de residuos de plaguicidas en muestra de agua por cromatografía de gases utilizando extracción líquido analito: Acefato, Captán, Clorotalonil, Forcim, Metalaxil, Metamidofos, Monocrotofós. 2. MAR-7 Determinación de plaguicidas ácidos y neutros en agua por extracción en fase sólida y cromatografía líquida de alta resolución analito: Dicamba, Disulfotón, Fentión. 3. MAR- 9 Determinación de residuos carbonatados en aguas utilizando extracción líquido y CLAR analito: 3- cetocarbofuran. 4. MAR-24 Determinación de residuos de fenamidona por cromatografía de gases en muestras de piña: corazón, pulpa, cáscara y fruto completo 12.11.2013 Reducción de alcance en los ensayos determinación de Caudal en aguas, aguas residuales y aguas de mar, Determinación de Sólidos Volátiles y fijos en aguas, aguas residuales y aguas de mar 14.01.2014 Suspensión voluntaria parcial del alcance del 14.01.2014 al 14.07.2014 para los ensayos: MAR-5:Determinaciòn de residuos de Plaguicidas, por cromatografía de gases en matrices de origen vegetal: con elevado contenido de agua y contenido escaso o ausencia de clorofila, elevado contenido de ácido, elevado contenido de agua y clorofila, elevado contenido de aceite o grasa, y materiales secos. MAQA-19: Metales pesados MAQA-39: Mercurio.
A8: Laboratorios de Control de Calidad RECOPE | B8: Refinadora Costarricense de Petroleo Sociedad Anónima | C8: LE | D8: A | E8: Público | F8: LE-009/LE-010 | G8: LE-009/LE-010 | H8: 43900 | I8: ='17025 SAL'!$H8+$AN$1 -> 45360 | J8: 36944 | K8: A10: 09/07/2025 | L8: Erick Solano , Francisco Padilla | M8: gestión.calidad@recope.go.cr gestioncalidad.comunicacioneseca@recope.go.cr | N8: francisco.padilla@recope.go.cr erick.solano@recope.go.cr | O8: (506) 2550-3667 Móvil: (506) 8819-9383 2550-3553 / 2550-3750 / 8310-0137 Erick Solano, 2550-3667 3500 367 Francisco Padilla: 2436-6049 | P8: No aplica | Q8: Costa Rica | R8: Cartago, Plantel de Distibución El Alto Recope, Ochomogo de Cartago | S8: Cartago | T8: 3-101-007749 | U8: =HYPERLINK("http://www.recope.go.cr/","www.recope.go.cr ") -> www.recope.go.cr | V8: Luis Manuel Sánchez Esquierdo | W8: 700860334 | X8: Casado | Y8: Costarricense | Z8: Ingeniero Químico | AA8: Terminal el Alto de Ochomogo, kilómetro 12 km, Ruta 2, Ochomogo, San Nicolás, Cartago. | AC8: Gerente de Operaciones | AD8: Tesorería | AE8: Hubert López Chacón | AF8: 2284-4740 | AG8: Calle 108, Ruta 32. Km 0, Edificio Hernán Garrón Salazar San Francisco de Goicoechea San José, Costa Rica | AH8: No aplica | AI8: factura@recope.go.cr | AJ8: 7:00 am a 3:00 pm | AK8: RECOPE | AL8: El cliente de la factura debe ser: Laboratorio Control de Calidad RECOPE, LE-009
A9: Laboratorio San Martín | C9: LE | D9: A | E9: Privado | F9: LE-012 | G9: LE-012 | H9: 43963 | I9: ='17025 SAL'!$H9+$AN$1 -> 45423 | J9: 37194 | L9: Dr. Juan Carlos Rojas Carrión | M9: jcrojas@labsanmartin.com | N9: carolina@labsanmartin.com | O9: 2222-3635 | P9: 2222-2486 | Q9: Costa Rica | R9: San José, Calles 1 y 3, Ave. 10, del Banco Popular 300 m sur y 25 m este. | S9: San José | T9: 3-101-74483 | U9: =HYPERLINK("http://www.labsanmatin.com/","www.labsanmatin.com ") -> www.labsanmatin.com | V9: Dr. Juan Carlos Rojas Carrión | W9: 1-0576-0622 | X9: Casado | Y9: Costarricense | Z9: Microbiólogo | AA9: San José, Calles 1 y 3, Ave. 10, del Banco Popular 300 sur y 25 este. | AC9: Gerente General | AD9: Carolina Rojas Sánchez | AE9: Centro Médico San Martín | AF9: 2222-3635 | AG9: San José, Calles 1 y 3, Ave. 10, del Banco Popular 300 sur y 25 este. | AH9: 2222-2486 | AI9: =HYPERLINK("mailto:carolina@labsanmartin.com","carolina@labsanmartin.com ") -> carolina@labsanmartin.com | AJ9: L-V 7am - 5 pm S 8am - 12 md | AK9: San Martin | AL9: Fecha de actualización de listado de alcance flexible: 22.01.2014
A10: Laboratorio Echandi | B10: Microbiologos Asociados Sociedad Anonima | C10: LE | D10: A | E10: Privado | F10: LE-014 | G10: LE-014 | H10: 45190 | I10: ='17025 SAL'!$H10+$AN$1 -> 46650 | J10: 37571 | L10: Federico Echandi | M10: fechandi@labechandi.com | N10: nvargas@labechandi.com aviquez@labechandi.com | O10: 7106-2648 /2258-4334/8666-0423 | Q10: Costa Rica | R10: San José, 25 metros norte de el restaurante Mac Donalds, contiguo a Auto Pitz, San Rafael de Escazú | S10: San José | T10: 3-101-014359-26 | U10: www.labechandi.com | V10: Federico Echandi | W10: 1-1111-0536 | Y10: Costarricense | AA10: San José, 25 metros norte de el restaurante Mac Donalds, contiguo a Auto Pitz, San Rafael de Escazú | AB10: fechandi@labechandi.com | AC10: Gerente General | AD10: Federico Echandi | AE10: Microbiólogos Asociados S.A. | AF10: 7106-2648 /2258-4334 | AG10: San José, 25 metros norte de el restaurante Mac Donalds, contiguo a Auto Pitz, San Rafael de Escazú | AH10: 2221-7159 | AI10: =HYPERLINK("mailto:labechandi@ice.co.cr","labechandi@ice.co.cr") -> labechandi@ice.co.cr | AJ10: L a V de 8 am a 5 pm | AK10: Echandi - Sta Rita | AL10: 2022.01.18 Reducción voluntaria del alcance de acreditación de los siguientes ensayos: LE-AA-I09, LE-AA-I10 y LE-DE-100// 22.10.2013 Reducción de alcances en los inmunoensayos: Canabinoides (THC) en orina. Metabolito de Cocaína en orina. // 17.09.2018 en el área de química clínica para los ensayos de Hierro y Capacidad de Fijación de Hierro. //
A11: Laboratorio Nacional de Materiales y Modelos Estructurales LANAMME-UCR. | B11: Universidad de Costa Rica | C11: LE | D11: R | E11: Académico | F11: LE-018 | L11: Ing. Humberto Tioli Mora | M11: emmanuel.badilla@ucr.ac.crjose.tioli@ucr.ac.cr | N11: direccion.lanamme@ucr.ac.crmaria.castrosoto@ucr.ac.cr | O11: 2511-2500/ 2511-2531 | P11: 2511-4440 | Q11: Costa Rica | R11: San José, 500 m Norte de Supermercado Muñoz & Nanne, Ciudad de la Investigación, Universidad de Costa Rica, San Pedro de Montes de Oca. | S11: San José | T11: 4-000-042149 | U11: http://www.lanamme.ucr.ac.cr/ | V11: Carlos Araya Leandro | W11: 3-0305-0948 | X11: Casado | Y11: Costarricense | Z11: Doctor en Economía, Gestión y Control de Entidades y Políticas Públicas. | AD11: Ing. Humberto Tioli | AE11: Universidad de Costa Rica | AF11: 2511-2514 | AG11: San José, 500 Norte de Supermercado Muñoz & Nanne, Ciudad de la Investigación, Universidad de Costa Rica, San Pedro de Montes de Oca. | AH11: 2511-4440 | AI11: jose.tioli@ucr.ac.cr; maria.castrosoto@ucr.ac.cr; randall.valle@ucr.ac.cr; facturacionelectronica.lanamme@ucr.ac.cr; emmanuel.badilla@ucr.ac.cr | AJ11: 08:00 - 17:00 | AK11: UCR | AL11: Facturar a nombre de: Universidad de Costa Rica
A12: Laboratorio de Calibración SCM Metrología y Laboratorios S.A. | B12: SCM Metrología y Laboratorios Sociedad Anónima | C12: LC | D12: A | E12: Privado | F12: LC-020 | G12: LC-020 | H12: 45869 | I12: No aplica | J12: 37718 | L12: Carlos Alvarado / Jose Marvin Rodríguez Vásquez | M12: carlos.alvarado@scmmetrologia.com | N12: jose.rodriguez@scmmetrologia.com | O12: (+506) 4020-1201 / (+506) 7206-1540 / (+506) 7206-1566 | P12: 4020-1203 | Q12: Costa Rica | R12: Zona Franca Bes, L1, Coyol, Alajuela | T12: =HYPERLINK("http://www.scmmetrologia.com/Newsite/","3-101-271623 ") -> 3-101-271623 | U12: =HYPERLINK("http://www.scmmetrologia.com/Newsite/","http://www.scmmetrologia.com/Newsite/") -> http://www.scmmetrologia.com/Newsite/ | V12: Edgar Sánchez Molina | W12: 2-0459-0214 | X12: Casado | Y12: Costarricense | Z12: Químico | AA12: vecino de San Pablo de Heredia, Residencial Doña Nina, casa 19. | AC12: Director | AD12: Laura Molina Salazar | AE12: SCM Metrología y Laboratorio S.A. | AF12: 2431-5252 ext. 102 | AG12: Alajuela, 2 km Este del Aeropuerto Internacional Juan Santamaría, Río Segundo de Alajuela | AH12: 2432-4180 | AI12: =HYPERLINK("mailto:laura.molina@scmmetrologia.com","laura.molina@scmmetrologia.com") -> laura.molina@scmmetrologia.com | AJ12: 7:00 am a 4:30 pm | AK12: SCM | AL12: 11.06.2019. Mantenimiento de acreditación otorgada en CA-008-2019
A13: Laboratorio Pruebas de Paternidad | B13: Caja Costarricense de Seguro Social | C13: LE | D13: A | E13: Público | F13: LE-021 | G13: LE-021 | H13: 45552 | I13: No aplica | J13: 37718 | L13: Lucía Obando Madrigal | M13: lobandom@ccss.sa.cr | N13: jpmontes@ccss.sa.cr | O13: 2257-5342 | P13: 22575342 | Q13: Costa Rica | R13: San José, Avenida central, calles 16 y 20, edificio Joissar, 3° piso. | S13: San José | T13: 4-000-042147 | U13: http://portal.ccss.sa.cr/portal/page/portal/Gerencia_Medica/Laboratorio_de_Pruebas_de_Paternidad | V13: RANDAL ALAN ÁLVAREZ JUÁREZ | W13: 5-0290-0193 | Y13: costarricense | Z13: Medico | AA13: San José, Avenida central, calles 16 y 20, edificio Joissar, 3° piso. | AC13: Gerente Médico CCSS | AD13: Diana Jane Conejo Rodríguez; José Joaquín Solano Solís | AE13: CCSS, Laboratorio de Pruebas de Paternidad | AF13: 2257-5342 | AG13: San José, Avenida central, calles 16 y 20, edificio Joissar, 3° piso. | AH13: 2257-5342 | AI13: =HYPERLINK("mailto:jjsolano@ccss.sa.crjpzunigg@ccss.sa.cr","dconejohm@ccss.sa.cr; jjsolano@ccss.sa.cr") -> dconejohm@ccss.sa.cr; jjsolano@ccss.sa.cr | AJ13: Lunes a jueves de 7:00 a 16:00; viernes 7:00 a 15:00 | AK13: CCSS - Pruebas de Paternidad
A14: La casa de la Balanza de Cartago S.A. | B14: La casa de la Balanza de Cartago Sociedad Anónima | C14: LC | D14: A | E14: Privado | F14: LC-025 | G14: LC-025 | H14: 43843 | I14: ='17025 SAL'!$H14+$AN$1 -> 45303 | J14: 38334 | L14: Roberto Granados Solis | M14: calidad@casabalanza.com | N14: servicioalcliente@casabalanza.com | O14: 2552-6311 | P14: 2551-4751 | Q14: Costa Rica | R14: Cartago, del Banco de Costa Rica, 200 m Sur, 50 m este y 25 m al Sur, San Rafael de Oreamuno. | S14: Cartago | T14: 3-101-136275 | U14: =HYPERLINK("http://www.casabalanza.com/","www.casabalanza.com") -> www.casabalanza.com | V14: Roberto Granados Solís | W14: 3-280-863 | X14: Casado | Y14: Costarricense | Z14: Mecánico Industrial | AA14: Cartago, del Banco de Costa Rica, 200 Sur y 50 este, San Rafael de Oreamuno. | AC14: Presidente | AD14: Gabriela Vargas Araya | AE14: La Casa de la Balanza de Cartago, S.A. | AF14: 2552-7293 | AG14: Cartago, del Banco de Costa Rica, 200 Sur y 50 este, San Rafael de Oreamuno. | AH14: 2551-4751 | AI14: =HYPERLINK("mailto:gvargas@casabalanza.com","gvargas@casabalanza.com") -> gvargas@casabalanza.com | AJ14: Lunes a Viernes de 10 a.m a 12.a.m y 2:00 pm a 4:00 p.m. | AK14: La casa de la Balanza de Cartago S.A. | AL14: Los pagos se hacen por transferencia los días viernes.
A15: Vieto & Asociados S.A. | B15: Vieto & Asociados Sociedad Anónima | C15: LE | D15: A | E15: Privado | F15: LE-026 | G15: LE-023 | H15: 45378 | I15: ='17025 SAL'!$H15+$AN$1 -> 46838 | J15: 38590 | K15: A07: 15/10/2024 | L15: Susy Vieto de la Fuente | M15: susy.vieto@vieto.com | N15: calidad@vieto.com | O15: 2268-8297 ext: 225 | P15: 2268-9457 | Q15: Costa Rica | R15: Heredia, del rancho de Doña Lela 3.5km sobre la autopista Braulio Carrillo, después del segundo puente peatonal 400 norte primer entrada de lastre a mano derecha, San Luis de Santo Domingo. | S15: Heredia | T15: 3-101-029579-15 | U15: =HYPERLINK("http://www.vieto.com/","www.vieto.com") -> www.vieto.com | V15: Susy Vieto de la Fuente | W15: 1-0753-0214 | X15: Casada | Y15: Costarricense | Z15: Administradora de empresas | AA15: =HYPERLINK("mailto:susy.vieto@vieto.com","susy.vieto@vieto.com calidad@vieto.com") -> susy.vieto@vieto.com calidad@vieto.com | AC15: Gerente de Calidad | AD15: Vanessa Loaiza | AE15: Vieto & Asociados S.A. | AF15: 2268-8297 | AG15: Heredia, del rancho de Doña Lela 3.5km sobre la autopista Braulio Carrillo, después del segundo puente peatonal 400 norte primer entrada de lastre a mano derecha, San Luis de Santo Domingo. | AH15: 2268-9457 | AI15: =HYPERLINK("mailto:contabilidad@vieto.com","contabilidad@vieto.com") -> contabilidad@vieto.com | AJ15: Lunes a viernes de 7:00am a 5:00pm Sábados 7:00am a 12:00md | AK15: Vieto y Asociados | AL15: De lunes a viernes cerrado de 12:00md a 1:00pm
A16: Agrotec Laboratorios Analíticos S.A. | B16: Agrotec Laboratorios Analíticos Sociedad Anónima | C16: LE | D16: A-S | E16: Privado | F16: LE-027 | G16: LE-029 | H16: 45411 | I16: ='17025 SAL'!$H16+$AN$1 -> 46871 | J16: 38635 | K16: A01: 12/07/2024 | L16: Frank Rivas, Priscilla Meléndez Vargas | M16: frank.rivas@agrotec.net | N16: priscila.melendez@agrotec.net eric.arauz@agrotec.net ana.angulo@agrotec.net | O16: 4040-0390 | Q16: Costa Rica | R16: Alajuela, Alajuela, San Rafael. Ofibodegas del Oeste, local 13. | S16: San José | T16: 3-101-161663 | U16: NA | V16: Steven Mullins Cordero | W16: 900930880 | X16: Divorciado | Y16: Costarricense | Z16: Administrador de Empresas | AA16: San José, Calles 36 y 38, Avenida 4, Paseo Colón, Mata Redonda. O al correo eric.arauz@agrotec.net; | AC16: Gerente General | AD16: Ana Cecilia Angulo Segura | AE16: Agrotec Laboratorios Analíticos S.A. | AF16: 4081-1010 | AG16: San José, Calles 36 y 38, Avenida 4, Paseo Colón, Mata Redonda. | AH16: 4081-1010 | AI16: =HYPERLINK("mailto:ana.angulo@agrotec.net","ana.angulo@agrotec.net") -> ana.angulo@agrotec.net | AJ16: Lunes a Viernes de 7:15 am-12:00 md | AK16: Agrotec | AL16: 20-12-22: Por favor cambiar al representante de Agrotec ante ECA, eliminar a Alejandra Montenegro, en su lugar queda Priscila Meléndez Vargas, este es su correo priscila.melendez@agrotec.net
A17: Laboratorio Clínico Médico Dr. Carlos Páez Sotela | C17: LE | D17: R | E17: Privado | F17: LE-028 | G17: LE-022 | I17: ='17025 SAL'!$H17+$AN$1 -> 1460 | J17: 38516 | L17: Dr. Marco Molina | M17: mamolina10@hotmail.com | O17: 2255-0561 | P17: 2258-5026 | Q17: Costa Rica | R17: San José, detrás de Pollo Campero en la Sabana. | S17: San José | T17: Servicios Clinicos la Sabana 3-101-570114 | U17: =HYPERLINK("http://www.laboratoriospaez.com/","www.laboratoriospaez.com") -> www.laboratoriospaez.com | V17: Carlos R Paez Sotela | W17: 9-011-206 | X17: casado | Y17: Costarricense | Z17: Microbiólogo | AA17: San José, detrás de Pollo Campero en la Sabana. | AC17: Alta Dirección | AD17: Sr. Jorge Sánchez | AE17: Servicios Clínicos La Sabana razón social | AF17: 2233-8318 | AG17: San José, detrás de Pollo Campero en la Sabana. | AH17: 2258-5026 | AI17: =HYPERLINK("mailto:Jsan@laboratoriospaez.com;","Jsan@laboratoriospaez.com;") -> Jsan@laboratoriospaez.com; | AJ17: 8 am a 5 pm | AK17: Laboratorio Clínico Médico Dr. Carlos R Páez Sotela | AL17: 15.05.2018 retiro voluntario de acreditación / 07.06.2017 reducción del alcance dejando solo los ensayos de Suero, Orina y Líquido cefalorraquídeo: Glucosa AU 480 BECKMAN COULTER OSR 6521, Suero: Colesterol Total AU 480 BECKMAN COULTER OSR 6116, Suero: hTSH II ultrasensible Hormona tiroestimulant humana 7K 62-25 Arquitect de Abbott, y Suero: Antígeno Prostático Específico PSA Total 7K 70-25 Arquitect de Abbott/24.05.2016 Reducción de alcance para los ensayos de: Prolactina humana en suero, Fenitoína 7ª en suero, Carbamazepina en suero / 08.09.2015 Reducción parcial del alcance para los siguientes ensayos: Canabinoides 3B28-20 Arquitect de Abbott y Cocaína metabolitos 3B24-20 Arquitect Abbott. Reducción de alcance 25.08.2015 de los siguientes ensayos: Ferritina, Reducción de alcance 14.01.2014 para los siguientes ensayos Digoxina, DL Colesterol Por fórmula Y Globulinas séricas Por fórmula
A18: Laboratorio de Hidrocarburos, Laboratorio Costarricense de Metrología | B18: Instituto Costarricense de Electricidad | C18: LE | D18: R | E18: Público | F18: LE-029 | G18: LE-026 | I18: ='17025 SAL'!$H18+$AN$1 -> 1460 | J18: 38635 | L18: Licda. Ileana Hidalgo | M18: ihidalgo@lacomet.go.cr | O18: 2224-3502 | P18: 2283-5133 | Q18: Costa Rica | R18: Ciudad de la investigación, San Pedro de Montes de Oca, Costa Rica. | AK18: Laboratorio Costarricense de Metrología
A19: Centro para Investigaciones en Granos y Semillas CIGRAS-UCR | B19: Universidad de Costa Rica | C19: LE | D19: A | E19: Académico | F19: LE-030 | G19: LE-028 | H19: 45147 | I19: ='17025 SAL'!$H19+$AN$1 -> 46607 | J19: 38635 | L19: Lic. Erika Villalobos Chaves | M19: erika.villalobos@ucr.ac.cr | N19: mariaveronica.campos@ucr.ac.cr | O19: 2511-8823 2511-3517 | P19: 2511-4346 | Q19: Costa Rica | R19: San José, Universidad de Costa Rica, Sede Rodrigo Facio, Contiguo a la Fac. de Ciencias Agroalimentarias, San Pedro de Montes de Oca. | S19: San José | T19: 4-000-042149 | U19: =HYPERLINK("http://www.cigras.ucr.ac.cr/;","http://www.cigras.ucr.ac.cr/;") -> http://www.cigras.ucr.ac.cr/; | V19: Carlos Araya Leandro | W19: 3-0305-0948 | X19: Casado | Y19: Costarricense | Z19: Doctor en Economía, Control y Gestión de Entidades y Políticas Públicas | AA19: San José, Universidad de Costa Rica, Sede Rodrigo Facio, Contiguo a la Fac. de Ciencias Agroalimentarias, San Pedro de Montes de Oca. | AB19: carlos.arayaleandro@ucr.ac.cr tel: 2511-1212 | AC19: Rector Universidad de Costa Rica | AD19: Jefatura Administrativa | AE19: M.B.A Armando Alvarado Luna | AF19: 2511 8822 | AG19: San José, Universidad de Costa Rica, Sede Rodrigo Facio, Contiguo a la Fac. de Ciencias Agroalimentarias, San Pedro de Montes de Oca. | AH19: NA | AI19: =HYPERLINK("mailto:armando.alvarado@ucr.ac.cr","armando.alvarado@ucr.ac.cr") -> armando.alvarado@ucr.ac.cr | AJ19: De lunes a viernes, de 8:00 a.m- 4:00 p.m. | AK19: UCR
A20: Laboratorio de Análisis Ambiental, Universidad Nacional | B20: Universidad Nacional | C20: LE | D20: A | E20: Académico | F20: LE-031 | G20: LE-024 | H20: 45681 | I20: No aplica | J20: 38635 | L20: José Felix Rojas Marin | M20: jose.rojas.marin@una.cr | N20: alejandra.gamboa@una.cr laa@una.ac.cr | O20: 2277-3292 EXT: 3508 | P20: 2277-3696 | Q20: Costa Rica | R20: Heredia, Edificio Rectoría de la UNA, Calle 9 Avenida central y primera.Laboratorio de Análisis Ambiental Tercer Piso, Escuela de Ciencias Ambientales, Campus Omar Dengo, UNA | S20: Heredia | T20: 4-000-042150-140 | U20: oe | V20: Jorge Herrera Murillo | W20: 205330454 | X20: Divorciado | Y20: Costarricense | Z20: Doctor en Ciencias de la Tierra con énfasis en Física de la Atmósfera | AA20: Heredia, Edificio Rectoría de la UNA, Calle 9 Avenida central y primera | AB20: rectoria@una.cr | AC20: Rector de la Universidad Nacional | AD20: Kerlyn Sánchez Campos | AE20: FUNDAUNA | AF20: 2263-7444 | AG20: Heredia, Edificio Rectoría de la UNA, Calle 9 Avenida central y primera | AH20: 2263-7444 | AI20: kerlin.sanchez.campos@una.cr; kersc_15@hotmail.com; | AJ20: De 8:00 a.m. hasta las 5:00 p.m | AK20: UNA | AL20: Suspensión parcial voluntario del 22/1/24 al 22/1/25
A21: Laboratorio de Ensayo Compañía Asesora de Construcción e Ingeniería S.A. CACISA | B21: Compañía Asesora de Construcción e Ingeniería CACISA Sociedad Anónima | C21: LE | D21: A | E21: Privado | F21: LE-032 | G21: LE-030 | H21: 45099 | I21: ='17025 SAL'!$H21+$AN$1 -> 46559 | J21: 38853 | L21: Ing. Elda Patricia Daniels Chang | M21: pdaniels@cacisa.cr | N21: rzuniga@cacisa.cr | O21: 2244-0548 | P21: 2244-1385 | Q21: Costa Rica | R21: Heredia, de la iglesia de Santa Rosa, 200 m oeste y 750 m norte, Sto. Domingo. | S21: Heredia | T21: 3-101-036290 | U21: =HYPERLINK("mailto:info@cacisa.cr","info@cacisa.cr") -> info@cacisa.cr | V21: Rodolfo De León rdeleon@cacisa.cr | W21: 900460935 | X21: Casado | Y21: Costarricense | Z21: Ingeniero Civil | AA21: Heredia, de la iglesia de Santa Rosa, 200 oeste y 750 norte, Sto. Domingo. | AC21: Director General | AD21: psalas@cacisa.cr | AE21: Paula Salas cuentas por pagar | AF21: 2244-0548 | AG21: Heredia, de la iglesia de Santa Rosa, 200 oeste y 750 norte, Sto. Domingo. | AH21: 2244-1385 | AI21: =HYPERLINK("mailto:cmontero@cacisa.cr","cmontero@cacisa.cr") -> cmontero@cacisa.cr | AJ21: L-V de 7:30 a.m. a 5:30 p.m. | AK21: CACISA
A22: Centro de Investigaciones en Nutrición Animal CINA-UCR | B22: Universidad de Costa Rica | C22: LE | D22: A | E22: Académico | F22: LE-033 | G22: LE-038 | H22: 45147 | I22: ='17025 SAL'!$H22+$AN$1 -> 46607 | J22: 39125 | K22: A03: 16/06/2025 | L22: Gerardo Soto Rodríguez | M22: calidad.cina@ucr.ac.cr | N22: calidad.cina@gmail.com | O22: 2511-2028 / 2511-2049 | P22: 2234-2415 | Q22: Costa Rica | R22: San José, 150 m oeste y 25 m sur de la UNED carretera a Sabanilla de Montes de Oca. | S22: San José | T22: 4-000-042149 | U22: =HYPERLINK("http://www.cina.ucr.ac.cr/","www.cina.ucr.ac.cr ") -> www.cina.ucr.ac.cr | V22: Carlos Araya Leandro | W22: 3-0305-0948 | X22: Casado | Y22: Costarricense | Z22: Doctor en Biología con especialidad en Genética | AA22: San José, Sede Univesitaria Rodrigo Facio, Edificio Administrativo B, Segundo Piso, Oficina de Rectoría, San Pedro de Montes de Oca | AC22: Rector Universidad de Costa Rica | AD22: Jenny Ascencio Ayala | AE22: Universidad de Costa Rica | AF22: 25113002 | AG22: San José, 150 oeste y 25 sur de la UNED carretera a Sabanilla de Montes de Oca. | AH22: 22342415 | AI22: =HYPERLINK("mailto:jenny.ascencio@ucr.ac.cr","jenny.ascencio@ucr.ac.cr ") -> jenny.ascencio@ucr.ac.cr | AJ22: L-V 8:00am a 4:30pm | AK22: UCR | AL22: La Gerencia de Calidad será asumida por el Bach. Fabio Granados Chinchilla, la Dra. Guadalupe Molina Chavarría será a su vez sustito de éste.
A23: Centro de Investigaciones Agronómicas CIA UCR | B23: Universidad de Costa Rica | C23: LE | D23: A | E23: Académico | F23: LE-036 | G23: LE-033 | H23: 45147 | I23: ='17025 SAL'!$H23+$AN$1 -> 46607 | J23: 38880 | L23: Marianela Blanco Morice | M23: sistemacalidad.cia@ucr.ac.cr marianela.blancomorice@ucr.ac.cr | N23: freddy.blanco@ucr.ac.cr gestoriatecnica.lsf@ucr.ac.cr | O23: 2511-2072 2511-3112 2511-2079 | P23: 2234-1627 | Q23: Costa Rica | R23: San José, Ciudad de la Investigación, Finca 2 UCR, de la UNED carretera a Sabanilla, 175 m este y 100 m sur, edificio de 3 pisos a mano izquierda, Montes de Oca. | S23: San José | T23: 3006101757 | U23: =HYPERLINK("http://www.cia.ucr.ac.cr/","www.cia.ucr.ac.cr ") -> www.cia.ucr.ac.cr | V23: Carlos Araya Leandro | W23: 3-0305-0948 | X23: Casado | Y23: Costarricense | Z23: Doctor en Biología con especialidad en Genética | AA23: San José, Sede Univesitaria Rodrigo Facio, Edificio Administrativo B, Segundo Piso, Oficina de Rectoría, San Pedro de Montes de Oca. | AC23: Rector Universidad de Costa Rica | AD23: María Gabirela Villegas Jefatura Administrativa CIA | AE23: FUNDEVI | AF23: 2511-2053 | AG23: San José, Ciudad de la Investigación, Finca 2 UCR, de la UNED carretera a Sabanilla, 175 este y 75 sur, Montes de Oca. | AH23: 2234-1627 | AI23: =HYPERLINK("mailto:maria.villegas@ucr.ac.cr","maria.villegas@ucr.ac.cr ") -> maria.villegas@ucr.ac.cr | AJ23: Lunes a Viernes de 8 a.m. a 5 p.m. | AK23: UCR | AL23: La factura debe venir a nombre de FUNDEVI pero debe entregarse en el CIA
A24: Consultora Costarricense para Programas de Desarrollo S.A COPRODESA | B24: Consultora Costarricense para Programas de Desarrollo S.A COPRODESA | C24: LC | D24: A | E24: Privado | F24: LC-038 | G24: LC-031 | H24: 45859 | I24: No aplica | J24: 38810 | L24: Jean Carlo Sandí Jiménez Sara Granados | M24: jsandi@coprodesa.com | N24: sgranados@coprodesa.com | O24: 2528-5880 | P24: 2283-1838 | Q24: Costa Rica | R24: San José, 75 m Sur de la Mitsubishi, Curridabat. | S24: San José | T24: 3-101-026507 | U24: =HYPERLINK("http://www.coprodesa.com/","www.coprodesa.com ") -> www.coprodesa.com | V24: Mario Longan Espinoza | W24: 1-0369-0348 | X24: Casado | Y24: Costarricense | Z24: Empresario | AA24: San José, 75 Sur de la Mitsubishi, Curridabat. | AC24: No tiene cargo en el Laboratorio sin embargo es parte de la Junta Directiva de la Empresa | AD24: Jennifer Mejía Castro | AE24: COPRODESA | AF24: 2528-5880 | AG24: San José, 75 Sur de la Mitsubishi, Curridabat. | AH24: 2283-1838 | AI24: =HYPERLINK("mailto:jmejia@coprodesa.com","jmejia@coprodesa.com") -> jmejia@coprodesa.com | AJ24: Todos los jueves de 9 a.m. a 5 p.m. (jornada continua) | AK24: Consultora Costarricense para Programas de Desarrollo S.A COPRODESA | AL24: 25/5/23: Con respecto a los representantes ante el ECA, se procede de la siguiente manera: Eliminar a Alonso Porras Cabezas como representante. Mantener a Jean Carlo Sandí Jiménez como representante. Agregar a Sara Granados Valverde como representante. De ahora en adelante por favor dirigirse a los siguientes correos para las notificaciones y avisos que nos deban dar: jsandi@coprodesa.com - Jean Carlo Sandí sgranados@coprodesa.com - Sara Granados
A25: Laboratorio de Ensayo del Centro de Electroquímica y Energía Química CELEQ | B25: Universidad de Costa Rica | C25: LE | D25: A | E25: Académico | F25: LE-040 | G25: LE-037 | H25: 45147 | I25: ='17025 SAL'!$H25+$AN$1 -> 46607 | J25: 39069 | K25: A07: 28/04/2025 | L25: Mariann Guillén Osorno | M25: calidad.celeq@ucr.ac.cr direccion.celeq@ucr.ac.cr | N25: jean.sanabria@ucr.ac.cr | O25: 2511-2487 | P25: 2511-2484 | Q25: Costa Rica | R25: San José, U.C.R Ciudad de la Investigación, San Pedro de Montes de Oca. | S25: San José | T25: 4-000-042149 | U25: =HYPERLINK("http://celeq.ucr.ac.cr/","http://celeq.ucr.ac.cr/ ") -> http://celeq.ucr.ac.cr/ | V25: Carlos Araya Leandro | W25: 3-0305-0948 | X25: Casado | Y25: Costarricense | Z25: Doctor en Biología con especialidad en Genética | AA25: San José, Sede Univesitaria Rodrigo Facio, Edificio Administrativo B, Segundo Piso, Oficina de Rectoría, San Pedro de Montes de Oca. | AC25: Rector Universidad de Costa Rica | AD25: Licda. Marjorie Badilla | AE25: Fundevi | AF25: 2511-3217 | AG25: San José, U.C.R Ciudad de la Investigación, San Pedro de Montes de Oca. | AH25: 2511-3211 | AI25: =HYPERLINK("mailto:mbadillad@hotmail.com","mbadillad@hotmail.com") -> mbadillad@hotmail.com | AJ25: 8 a.m. a 4 p.m. | AK25: UCR | AL25: La Factura debe venir a nombre de Fundevi, pero se debe recibir en el Celeq primero para enviar el trámite a Fundevi
A26: Laboratorio de Aseguramiento de la Calidad, Ingenio Taboga | B26: Laboratorio de Aseguramiento de la Calidad, Ingenio Taboga | C26: LE | D26: R | E26: Privado | F26: LE-041 | G26: LE-074 | H26: 44738 | I26: ='17025 SAL'!$H26+$AN$1 -> 46198 | J26: 40295 | L26: Martha Nuñez Torres | M26: mnunez@taboga.cr | N26: gdiaz@taboga.cr; jrodriguez@chemlabsonline.com | O26: 2674 0935 ext 1323 | P26: N/A | Q26: Costa Rica | R26: Guanacaste, Bebedero, Cañas. Para notificaciones: San José, Almacén Carazo en la Uruca | S26: Guanacaste | T26: 3-101-024153-03 | U26: NA | V26: Daniel Carvajal Carvajal | W26: 111120255 | X26: casado | Y26: costarricense | Z26: administrador de empresas. | AA26: San José, Almacén Carazo en La Uruca | AG26: San José, Almacén Carazo en La Uruca | AI26: NA | AK26: Taboga | AL26: Se le solicito en varias ocasiones la información faltante para completarla en el Directorio, sin obtener respuesta.
A27: Laboratorio Metrológico de Variables Eléctricas, LMVE-ICE | B27: Instituto Costarricense de Electricidad | C27: LC | D27: R | E27: Público | F27: LC-042 | G27: LC-036/125 | H27: 44348 | I27: ='17025 SAL'!$H27+$AN$1 -> 45808 | J27: 39034 | L27: Javier Robles Cordero, Blanca Castro Blanco,Lucrecia Montero Aguilar | M27: JRoblesCo@ice.go.cr | N27: BCastro@ice.go.cr; | O27: 2001-2374/75 | P27: NA | Q27: Costa Rica | R27: San José, Edificio ICE, Quinto Piso, Puerta # 11, San Pedro de Montes de Oca. | S27: San José | T27: =HYPERLINK("http://www.grupoice.com/","4-000-421-39 ") -> 4-000-421-39 | U27: =HYPERLINK("http://www.grupoice.com/","www.grupoice.com") -> www.grupoice.com | V27: Luis Pacheco Morgan | W27: 104620902 | X27: Casado | Y27: Costarricense | Z27: Ingeniero Químico | AA27: San José, 400 norte del edificio central del ICE, puesto de guarda a mano izquierda, edificio UEN PySA, piso 1, Sabana norte. | AC27: Gerente Sector Energía | AD27: Carmen Elena Rojas Zumbado | AE27: Laboratorio Metrológico de Variables Eléctricas, LMVE-ICE | AF27: 2000-5485 | AG27: San José, Edificio UEN PySA, 3° Piso, Centro de Servicio Investigación y Desarrollo, Sabana Norte. | AH27: 2220-8684 | AI27: JRoblesCo@ice.go.cr; BCastro@ice.go.cr; | AJ27: 7 am a 4:36 pm de L a V | AK27: ICE | AL27: 12.01.2016 reducción de alcance para las calibraciones de resistencia CD, medidores de resistencia CD, valores intermedios, Teraohmetros de 10 - 100 MW y de 1 - 100 GW
A28: Unidad de Laboratorio Metrológicos del Negocio Generación | B28: Instituto Costarricense de Electricidad | C28: LC | D28: A | E28: Público | F28: LC-042/138 | G28: LC-036/125 | H28: 44022 | I28: ='17025 SAL'!$H28+$AN$1 -> 45482 | J28: 39034 | K28: A01: 7-6-21 A02: 26-4-23 | L28: Javier Robles Cordero, Blanca Castro Blanco | M28: JRoblesCo@ice.go.cr | N28: BCastro@ice.go.cr | O28: 2000-4517 o 2001-2374 | P28: NA | Q28: Costa Rica | R28: Plantel ICE Colima, Tibás, San José. | S28: San José | T28: 4000042139 | U28: https://www.grupoice.com/wps/portal/ICE/electricidad/laboratorioss/lab | V28: José Joaquín Granados Ramírez | W28: 302970039 | X28: Soltero | Y28: Costarricense | Z28: Ingeniero Electromecánico | AA28: San José, Mata Redonda, Sabana Sur, Edificio ICE, Torre de Telecomunicaciones, Piso # 14 División Generación San José, Costa Rica | AB28: jogranados@ice.go.cr | AC28: Jefe División Generación | AD28: Cadena de Abastecimiento - División Generación | AE28: Sandra Hidalgo Cabrera | AF28: 2000-3087 | AG28: San José, Mata Redonda, Sabana Sur, Edificio ICE, Torre de Telecomunicaciones, Piso # 14 División Generación San José, Costa Rica | AH28: No aplica | AI28: shidalgo@ice.go.cr | AJ28: L a V de 7 am a 4:36 pm | AK28: ICE | AL28: 2020.08.19: Se acuerda unificar los laboratorio LACALI y LMVE y crear este OEC. // 12.01.2016 reducción de alcance para las calibraciones de resistencia CD, medidores de resistencia CD, valores intermedios, Teraohmetros de 10 - 100 MW y de 1 - 100 GW
A29: Laboratorio Punta Morales LAICA | B29: Liga Agricola Industrial de la caña de azucar | C29: LE | D29: A | E29: Público | F29: LE-043 | G29: LE-044 | H29: 45869 | I29: No aplica | J29: 39307 | L29: Reyner Alpízar Medina | M29: ralpizar@laica.co.cr | O29: 2661-0884 ext:129 | P29: 2661-0566 | Q29: Costa Rica | R29: Puntarenas, Punta Morales de Chomes. | S29: Puntarenas | T29: 3-007-42036 | U29: =HYPERLINK("http://www.laica.co.cr/","www.laica.co.cr") -> www.laica.co.cr | V29: Edgar Herrera Echadi | W29: 1-522-0490 | X29: Casado | Y29: costarricese | Z29: Administrador de negocios | AA29: San José, detrás del Ministerio de Trabajo, Barrio Tournon. | AC29: No tiene | AD29: Gabriela Sánchez | AE29: LAICA | AF29: 22846043 | AG29: San José, detrás del Ministerio de Trabajo, Barrio Tournon. | AH29: 26610566 | AI29: msanchez@laica.co.cr | AJ29: 09:00 a 10:30 | AK29: LAICA | AL29: No
A30: Laboratorio de Pruebas Físicas de Producto Terminado de Bridgestone de Costa Rica S.A. | B30: Bridgestone de Costa Rica Sociedad Anónima | C30: LE | D30: A | E30: Privado | F30: LE-044 | G30: LE-041 | H30: 45272 | I30: ='17025 SAL'!$H30+$AN$1 -> 46732 | J30: 39209 | L30: Carlos Alberto Martínez Sanchez/ Rixi Leiva | M30: martinezsanchezcarlos@la-bridgestone.com | N30: LeivaRixi@la-bridgestone.com | O30: 2209-7381/2209-7385 2209-7300 extensión 7083. | P30: 2209-7301 | Q30: Costa Rica | R30: Heredia, La Ribera, Kilometro 11, Autopista General Cañas, Belén. | S30: Heredia | T30: 3-101-008915 | U30: https://www.bridgestone.co.cr | V30: José Fernando Lopez Lopez. | W30: 122201367821 | Y30: Salvadoreño | AA30: Heredia, La Ribera, Kilometro 11, Autopista General Cañas, Belén. | AC30: Country Manager -Costa Rica Plant | AD30: Allan Soto Castrillo | AE30: Bridgestone de Costa Rica S.A | AF30: 22097300 | AG30: Heredia, La Ribera, Kilometro 11, Autopista General Cañas, Belén. | AH30: 22097301 | AI30: =HYPERLINK("mailto:alvarezronald@bfcr.co.cr","alvarezronald@bfcr.co.cr") -> alvarezronald@bfcr.co.cr | AJ30: de L a V de 8:00 am a 5 pm. | AK30: Laboratorio de Pruebas Físicas de Producto Terminado de Bridgestone de Costa Rica S.A.|
A31: Laboratorio del Centro Nacional de Ciencia y Tecnología de Alimentos CITA - UCR | B31: Universidad de Costa Rica | C31: LE | D31: A | E31: Académico | F31: LE-045 | G31: LE-035 | H31: 45147 | I31: ='17025 SAL'!$H31+$AN$1 -> 46607 | J31: 38971 | L31: Vanny Mora Villalobos | M31: vanny.mora@ucr.ac.cr | N31: marcy.gonzalez@ucr.ac.cr | O31: 25113270 | P31: N/A | Q31: Costa Rica | R31: San José, UCR, Detrás de la Facultad de Agronomía, San Pedro Montes de Oca | S31: San José | T31: 4-000-042149 | U31: =HYPERLINK("http://www.cita.ucr.ac.cr/","www.cita.ucr.ac.cr") -> www.cita.ucr.ac.cr | V31: Carlos Araya Leandro | W31: 3-0305-0948 | X31: Casado | Y31: Costarricense | Z31: Doctor en Biología con especialidad en Genética | AA31: San José, Sede Univesitaria Rodrigo Facio, Edificio Administrativo B, Segundo Piso, Oficina de Rectoría, San Pedro de Montes de Oca. | AC31: Rector Universidad de Costa Rica | AD31: FUNDEVI | AE31: Fundación de la Universidad de Costa Rica para la Investigación | AF31: 2511-1777 | AG31: San José, UCR, Detrás de la Facultad de Agronomía, San Pedro Montes de Oca | AH31: 2225-3876 | AI31: =HYPERLINK("mailto:fundevi@ucr.ac.cr","fundevi@ucr.ac.cr") -> fundevi@ucr.ac.cr | AJ31: 8am a 4pm | AK31: UCR | AL31: 26.07.2017 reducción ensayode química para productos lacteos - Grasa método SA-MQ-008 / Reducción de alcance 25.08.2015 para los ensayos de: Prueba triangular, prueba de comparación por pares, prueba de duo trío y prueba de tres alternativas de selección forzada.
A32: Laboratorio Costarricense de Metrología | B32: Instituto Costarricense de Electricidad | C32: LC | D32: R | E32: Público | F32: LC-047 | G32: LC-039 | I32: ='17025 SAL'!$H32+$AN$1 -> 1460 | J32: 39125 | M32: mnunez@taboga.co.cr | O32: 2283-6580 | P32: 2283-5133 | Q32: Costa Rica | R32: Ciudad de la Investigación, San Pedro de Montes de Oca, Costa Rica | AK32: LACOMET
A33: Laboratorio Nacional de Servicios Veterinarios LANASEVE | B33: Servicio Nacional de Salud Animal (SENASA) | C33: LE | D33: A-S | E33: Público | F33: LE-048 | G33: LE-040 | H33: 44096 | I33: ='17025 SAL'!$H33+$AN$1 -> 45556 | J33: 39209 | L33: Jeremy Barrantes Zamora | M33: jjbarrantesz@senasa.go.cr fchaverri@senasa.go.cr | N33: Para temas legales: german.rojas.h@senasa.go.cr, bernardita.rojas.c@senasa.go.cr | O33: 2587-1785 | P33: 2260-8300 ext 2345 | Q33: Costa Rica | R33: Lagunilla Heredia, 2 Km. Oeste y 500 metros Norte de Jardines del Recuerdo, en el Campus Universitario Benjamín Núñez, | S33: Heredia | T33: 3-007-475206 | U33: =HYPERLINK("http://www.senasa.go.cr/senasa/sitio/;","http://www.senasa.go.cr/senasa/sitio/;") -> http://www.senasa.go.cr/senasa/sitio/; | V33: Luis Alberto Matamoros Cortés | W33: 6-0289-0018 | X33: Casado | Y33: Costarricense | Z33: Médico Veterinario | AA33: Heredia, Cantón Central, Distrito Ulloa, Lagunilla, Campus Benjamín Núñez.2 km Oeste y 500 m Norte de Jardines del Recuerdo | AB33: luis.matamoros.c@senasa.go.cr | AC33: Director General del Servicio Nacional de Salud Animal (SENASA) | AD33: Dirección Administrativa Financiera del SENASA, Departamento de Recursos Materiales | AE33: Jose Luis Meneses Guevara | AF33: 22571600 o 22571613 | AG33: Heredia, 2 Km. Oeste y 500 Norte de Jardines del Recuerdo, en el Campus Universitario Benjamín Núñez, Lagunilla. | AH33: 22386169 o 22620226 | AI33: =HYPERLINK("mailto:eddy.obando.a@senasa.go.cr","eddy.obando.a@senasa.go.cr; bryan.moreira.r@senasa.go.cr") -> eddy.obando.a@senasa.go.cr; bryan.moreira.r@senasa.go.cr | AJ33: 7:30 a 15:30 | AK33: MAG - Senasa | AL33: Acuerdo Ministerial número N° 001-2023-MAG de fecha 11 de septiembre de 2023, publicado en el Diario Oficial La Gaceta número 178 del 28 de septiembre de 2023; se nombró al señor Luis Alberto Matamoros Cortés,
A34: Ingeniería Técnica de Proyectos ITP | B34: Ingeniería Técnica de Proyectos ITP Sociedad Anónima | C34: LE | D34: A | E34: Privado | F34: LE-050 | G34: LE-050 | H34: 45533 | I34: No aplica | J34: 39517 | K34: A16: 6/12/2024 | L34: Shirleny Salas Picado | M34: shirleny.salas@itp.cr | N34: oscar.martinez@itp.cr | O34: 2220-1400 ext: 2005/2009/2010 | P34: 2290-9295 | Q34: Costa Rica | R34: San José, Contiguo a Repretel, diagonal al AMPM, La Uruca. | S34: San José | T34: 3-101-362220 | U34: =HYPERLINK("http://www.itp.co.cr/","www.itp.co.cr") -> www.itp.co.cr | V34: Marcela Bonilla Verdesia | W34: 110740098 | X34: Casada | Y34: Costarricense | Z34: Administradora de Empresas | AA34: San José, Contiguo a Repretel, diagonal al AMPM, La Uruca. | AC34: Gerente General | AD34: Alejandra Acuña | AE34: Ingeniería Técnica de Proyectos ITP | AF34: 2220-1400 | AG34: San José, Contiguo a Repretel, diagonal al AMPM, La Uruca. | AH34: 2296-2382 | AI34: =HYPERLINK("mailto:aacuna@itp.co.cr","aacuna@itp.co.cr") -> aacuna@itp.co.cr | AJ34: Lunes a Viernes 8 am a 5 pm | AK34: ITP | AL34: * Ampliación 22709/2016 /11.08.2017 Reducción de alcance para el ensayo suelo - cemento para la determinación de suelo - cemento para el metodo ITP-IT-064 método de ensayo para la elaboración y curado de especímenes de laboratorio para los ensayos de comprensión y Flexión de muestras de suelo cemento / 15.12.2016 Reducción de alcance para los ensayos de la sede Panamá ver acta CA-2016-040 / 12.04.2016 reducción de alcance para el metodos de ensayo ITP-IT-52 Método Superpave para mezclado y compactación de mezcla asfáltica en caliente 12.08.2014 Reducción del método ITP-IT-11 densidad de parafina a 25°C en mezclas asfálaticas
A35: CHEMLABS | B35: CHEMLABS SOCIEDAD ANÓNIMA | C35: LE | D35: A | E35: Privado | F35: LE-051 | G35: LE-043 | H35: 45482 | I35: No aplica | J35: 39244 | L35: José Armando Rodríguez Solano | M35: jrodriguez@chemlabsonline.com | O35: 2234-6339 | P35: 2283-9869 | Q35: Costa Rica | R35: Cartago, #42 Residencial Monzerrat Concepción de la Unión. | S35: Cartago | T35: 3-101-492724 | U35: =HYPERLINK("http://www.chemlabsonline.com/","www.chemlabsonline.com") -> www.chemlabsonline.com | V35: Jose Armando Rodriguez Solano | W35: 1-06710412 | X35: Casado | Y35: Costarricense | Z35: Lic. Químico | AA35: San José, #192 Residencial Altamonte, Granadilla de Curridabat. | AC35: Jefe del Laboratorio | AD35: Blanca Ramirez | AE35: Blanca Ramirez | AF35: 22346339 | AG35: San José, #192 Residencial Altamonte, Granadilla de Curridabat. | AH35: 2283-9869 | AI35: =HYPERLINK("mailto:bramirez@chemlabsonline.com","bramirez@chemlabsonline.com") -> bramirez@chemlabsonline.com | AJ35: 8 am-5pm | AK35: Chem labs
A36: Laboratorio de Control de Calidad de Industria Farmacéutica S.A. de C.V. (calibración) | C36: LC | D36: R | E36: Privado | F36: LC-052 | G36: LC-047 | I36: ='17025 SAL'!$H36+$AN$1 -> 1460 | J36: 39426 | L36: Brenda Xiomara Miranda Bueso | M36: =HYPERLINK("mailto:brenda.miranda@infarma.hn","brenda.miranda@infarma.hn; administracion.calidad@infarma.hn") -> brenda.miranda@infarma.hn; administracion.calidad@infarma.hn | O36: (504) 2225-1272 | P36: (504) 2225-0271 | Q36: Honduras | R36: Col El Prado, atrás de Corporacion Flores TOYOTA | T36: 0401-1977-01951 | U36: =HYPERLINK("http://www.infarma.hn/","www.infarma.hn") -> www.infarma.hn | V36: Liliana Andonie | W36: 0801-1958-04265 | X36: Soltera | Y36: Hondureña | Z36: Lic. En Administración de empresas | AA36: Col El Prado, atrás de Corporacion Flores TOYOTA | AC36: Junta Directiva | AD36: Cinthia Vasquez | AE36: Iris Martínez | AF36: (504) 22251272 | AG36: Col El Prado, atrás de Corporacion Flores TOYOTA | AH36: (504) 22250271 | AI36: =HYPERLINK("mailto:iris.martinez@infarma.hn","iris.martinez@infarma.hn") -> iris.martinez@infarma.hn | AJ36: 08 h 00 a 15 h00 de Lunes a Viernes | AK36: Industria Farmacéutica S.A. de C.V. | AL36: Retiro de acreditación 09.12.2014
A37: Laboratorio de Control de Calidad de Industria Farmacéutica S.A. de C.V. (ensayos) | C37: LE | D37: R | E37: Privado | F37: LE-053 | G37: LE-051 | I37: ='17025 SAL'!$H37+$AN$1 -> 1460 | J37: 39574 | L37: Brenda Xiomara Miranda Bueso | M37: =HYPERLINK("mailto:brenda.miranda@infarma.hn","brenda.miranda@infarma.hn; administracion.calidad@infarma.hn") -> brenda.miranda@infarma.hn; administracion.calidad@infarma.hn | O37: (504) 2225-1272 | P37: (504)2225-0271 | Q37: Honduras | R37: Col El Prado, atrás de Corporacion Flores TOYOTA | T37: 0401-1977-01951 | U37: =HYPERLINK("http://www.infarma.hn/","www.infarma.hn") -> www.infarma.hn | V37: Liliana Andonie | W37: 0801-1958-04265 | X37: Soltera | Y37: Hondureña | Z37: Lic. En Administración de empresas | AA37: Col El Prado, atrás de Corporacion Flores TOYOTA | AC37: Junta Directiva | AD37: Cinthia Vasquez | AE37: Iris Martínez | AF37: (504) 22251272 | AG37: Col El Prado, atrás de Corporacion Flores TOYOTA | AH37: (504) 22250271 | AI37: =HYPERLINK("mailto:iris.martinez@infarma.hn","iris.martinez@infarma.hn") -> iris.martinez@infarma.hn | AJ37: 08 h 00 a 15 h00 de Lunes a Viernes | AK37: Industria Farmacéutica S.A. de C.V. | AL37: Retiro de acreditación 09.12.2014
A38: Metrología Consultores S.A. | B38: Metrología Consultores Sociedad Anónima | C38: LC | D38: A | E38: Privado | F38: LC-054 | G38: LC-046 | H38: 45128 | I38: ='17025 SAL'!$H38+$AN$1 -> 46588 | J38: 39344 | L38: Luis Miranda | M38: lmiranda@metrocal.co.cr | N38: gerentecalidad@metrocalcr.com administracion@metrocalcr.com | O38: 2280-1347 | P38: 2253-4687 | Q38: Costa Rica | R38: San José, de la Municipalidad 75 este, 175 m sur, frente al Minisuper Victoria, Guadalupe. | S38: San José | T38: 3-101-194426 | U38: =HYPERLINK("http://www.metrocal.co.cr/","www.metrocal.co.cr") -> www.metrocal.co.cr | V38: Marco V. Martínez Quesada | W38: 1-0629-0585 | X38: Casado | Y38: Costarricense | Z38: Físico y Meteorólogo | AA38: =HYPERLINK("mailto:mmartinez@metrocal.co.cr","Alajuela, 2 km este del Aeropuerto Internacional Juan Santamaría, Río Segundo de Alajuela .") -> Alajuela, 2 km este del Aeropuerto Internacional Juan Santamaría, Río Segundo de Alajuela . | AC38: Responsable Técnico | AD38: Sharon Chavarría Pérez | AE38: Sharon Chavarría Pérez | AF38: 2280-1347 | AG38: San José, de la Municipalidad 75 este, 175 sur, frente al Minisuper Victoria, Guadalupe. | AH38: 2253-4687 | AI38: =HYPERLINK("mailto:schavarria@metrocal.co.cr","schavarria@metrocal.co.cr") -> schavarria@metrocal.co.cr | AJ38: L-V 7:30 am a 5:00 pm | AK38: Metrología Consultores S.A. | AL38: N/A
A39: Laboratorio Nacional de Aguas AyA | B39: Instituto Costarricense de Acueductos y Alcantarillados | C39: LE | D39: A | E39: Público | F39: LE-055 | G39: LE-049 | H39: 44159 | I39: ='17025 SAL'!$H39+$AN$1 -> 45619 | J39: 39489 | K39: LE-049-A01 13 de julio del 2007. LE-049-A02 06 de diciembre del 2011. LE-049-A03 01 de julio del 2014. LE-049-A04 09 de febrero del 2016. LE-049-A05 10 de mayo del 2016. LE-049-A06 01 de diciembre del 2017. LE-049-A07 30 de octubre del 2018. LE-049-A08 22 de febrero del 2022. LE-049-A09 08 de abril del 2022. | L39: Ilena Vega Guzmán | M39: ivega@aya.go.cr | N39: nalfaro@aya.go.cr | O39: 2242-5000, ext. 6538 | P39: 2279-5973 | Q39: Costa Rica | R39: Cartago, 400 m norte del edificio municipal, La Unión de Tres Ríos. | S39: Cartago | T39: 4-000-042138 | U39: =HYPERLINK("http://www.aya.go.cr/","www.aya.go.cr") -> www.aya.go.cr | V39: José Alberto Moya Segura | W39: 1-0538-0956 | X39: Casado | Y39: Costarricense | Z39: Ingeniero Industrial | AA39: Cartago, 400 Norte de la Municipalidad de Tres Ríos, La Unión | AC39: Gerente General. | AD39: Lic. Marco Antonio Sequeira Barquero | AE39: Lic. Marco Antonio Sequeira Barquero | AF39: 22795118 | AG39: Cartago, 400 norte del edificio municipal, La Unión de Tres Ríos. | AH39: 22795973 | AI39: =HYPERLINK("mailto:msequeira@aya.go.cr","msequeira@aya.go.cr") -> msequeira@aya.go.cr | AJ39: 07:45 - 16:00 | AK39: A Y A
A40: OJM Consultores de Calidad y Laboratorios S.A. | B40: OJM Consultores de Calidad y Laboratorios Sociedad Anónima | C40: LE | D40: A | E40: Privado | F40: LE-056 | G40: LE-066 | H40: 44009 | I40: ='17025 SAL'!$H40+$AN$1 -> 45469 | J40: 40099 | K40: LE-066-A01: 26 de abril del 2011. LE-066-A02: 28 de octubre del 2014. LE-066-A03: 26 de enero del 2016. LE-066-A04: 26 de enero del 2016. LE-066-A05: 08 de diciembre del 2016. LE-066-A06: 29 de diciembre del 2016. LE-066-A07: 11 de mayo del 2017. LE-066-A08:27de Octubredel2017. LE-066-A09: 17 de junio 2021. LE-066-A10: 24 de agosto del 2021. | L40: José Luis Loría Álvarez Alfredo Salas Murillo | M40: calidad@ojmconsultores.com | N40: a.salas@ojmconsultores.com | O40: 2226-4078 / 83273421 | P40: No aplica | Q40: Costa Rica | R40: San Jose, Curridabat, Curridabat. Del Archivo Nacional, 50 metros este, junto a CRECEX de Costa Rica. | S40: San José | T40: 3-101-449145 | U40: N.A | V40: Alfredo Salas Murillo | W40: 1-1125-0222 | X40: Casado | Y40: Costarricense | Z40: sociólogo | AA40: San Jose, Curridabat, Curridabat. Del Archivo Nacional, 50 metros este, junto a CRECEX de Costa Rica. | AC40: Gerente General | AD40: No indica | AE40: Alfredo Salas Murillo | AF40: 2226-4078 / 8327-3421 | AG40: 50 metros al este y 25 metros al sur del Archivo Nacional, Curridabat, San José. | AH40: No aplica | AI40: facturacion@ojmconsultores.com | AJ40: 8:00 am a 5:00pm de Lunes a Viernes | AK40: OJM Consultores de Calidad y Laboratorios S.A. | AL40: 14/6/2019. Transición a la Norma INTE-ISO/IEC 17025:2017 y mantenimiento de acreditación
A41: LGC Ingeniería de Pavimentos S.A. | B41: LGC Ingeniería en Pavimentos, Sociedad Anónima | C41: LE | D41: A | E41: Privado | F41: LE-057 | G41: LE-054 | H41: 45142 | I41: ='17025 SAL'!$H41+$AN$1 -> 46602 | J41: 39735 | K41: Acreditación Número: 14 de junio del 2011 Acreditación Número: 10 de julio del 2012 Acreditación Número: 23 de julio del 2013 Acreditación Número: 01 de julio del 2014 Acreditación Número: 11 de agosto del 2015 Acreditación Número: 21 de diciembre del 2016 Acreditación Número: 10 de octubre del 2017 Acreditación Número: 28 de febrero del 2018 Acreditación Número: 21 de enero del 2019 Acreditación Número: 06 de agosto del 2020 Acreditación Número: 22 de marzo del 2021 Acreditación Número: 16 de septiembre del 2021 Acreditación Número: 19 de junio del 2023 | L41: José Luis Loría Álvarez | M41: jloria@lgcingenieria.net | N41: amedaldi@lgcingenieria.net | O41: 2270-55-54 / 2270-55-55 | P41: 2219-8035 | Q41: Costa Rica | R41: Dirección: Desamparados, San Miguel, San José, Costa Rica, de la entrada de Casa Cuba 400 metros este edificio a mano derecha color terracota. | S41: San José | T41: 3-101-303726 | U41: N/A | V41: LUIS GUILLERMO CHAVARRIA BRAVO | W41: 1-680-947 | X41: Casado | Y41: Costarricense | Z41: Lic.Ing. Civil | AA41: Dirección: Desamparados, San Miguel, San José, Costa Rica, de la entrada de Casa Cuba 400 metros este edificio a mano derecha color terracota. | AC41: Gerente General | AD41: Carlos Montero Godinez | AE41: LGC INGENIERIA DE PAVIMENTOS .A. | AF41: 2270-0555/2270-0331/ 2270-0538 | AG41: Dirección: Desamparados, San Miguel, San José, Costa Rica, de la entrada de Casa Cuba 400 metros este edificio a mano derecha color terracota. | AH41: 2219-8035 | AI41: lgcingenieriadepavimentos@gmail.com;"calidadlgc@gmail.com; lgcingenieriadepavimentos@gmail.com") | AJ41: De L a V de 730 a.m. a 5:00 p.m./sabados de 7:30 a.m. a 11:00 a.m. | AK41: LGC Ingeniería de Pavimentos S.A.
A42: Laboratorio de Aseguramiento de Calidad de Coca-Cola Industrias Ltda | C42: LE | D42: R | E42: Privado | F42: LE-058 | G42: LE-042 | I42: ='17025 SAL'!$H42+$AN$1 -> 1460 | J42: 39244 | L42: Rebeca Rodríguez / Erick Rojas Fajardo | M42: rebecrodriguez@coca-cola.com ; erirojas@coca-cola.com, helizondo@coca-cola.com; nayub@coca-cola.com | N42: N/A | O42: 2299-3487 | P42: 2223-7362 | Q42: Costa Rica | R42: San José, de la plaza de deportes 125 m Este, La Uruca | S42: San José | T42: 3-102-279501 | U42: N/A | V42: Erick Rojas Fajardo | W42: 1- 0763-0315 | X42: CasadO | Y42: Costarricense | Z42: Químico | AA42: San José, Coca Cola Industrias LTDA, de la plaza de deportes 125 Este, contiguo a Lachner y Sáenz, La Uruca. | AC42: Gerente General de la Planta de Concentrados de CPS Costa Rica | AD42: Jeffrey Salas | AE42: Jose Isaías Cubillo Herrera | AF42: 2299 3319 | AG42: San José, Coca Cola Industrias LTDA, de la plaza de deportes 125 Este, contiguo a Lachner y Sáenz, La Uruca. | AH42: 2223-7362 | AI42: =HYPERLINK("mailto:jcubillo@coca-cola.com","jcubillo@coca-cola.com") -> jcubillo@coca-cola.com | AJ42: De Lunes a Viernes 8:30 - 5:00 | AK42: de Coca-Cola Industrias Ltda | AL42: Se retira la acreditación el día 2021.09.08
A43: Laboratorio Castro & de la Torre | B43: Castro & de la Torre | C43: LE | D43: A | E43: Privado | F43: LE-059 | G43: LE-045 | H43: 45203 | I43: ='17025 SAL'!$H43+$AN$1 -> 46663 | J43: 39344 | K43: 19 de Setiembre del 2007 14 de Julio del 2009 23 de Febrero del 2010 11 de Enero del 2011 07 de Noviembre del 2012 26 de Noviembre del 2013 10 de Febrero del 2015 08 de Diciembre del 2016 23 de Marzo del 2018 12 de Diciembre del 2022 21 de agosto del 2023 | L43: Ing. Oscar Picado Acuña | M43: info@cyt.cr | N43: opicado@cyt.cr | O43: 4010-2273 | P43: 2296-0076 | Q43: Costa Rica | R43: San José, 500 m oeste de la Fabrica Jack’s, frente al Ministerio de Salud, Pavas. | S43: San José | T43: 3-101-007885 | U43: =HYPERLINK("http://www.cyt.cr/","www.cyt.cr") -> www.cyt.cr | V43: Orlando De la Torre Castro | W43: 107400155 | X43: Casado | Y43: Costarricense | Z43: Ingeniero Industrial | AA43: San José, 500 m oeste de la Fabrica Jack’s, frente al Ministerio de Salud, Pavas. | AC43: Sub-Gerente | AD43: Alexis Mata | AE43: Castro & De la Torre S.A. | AF43: 2232-2273 | AG43: San José, 500 m oeste de la Fabrica Jack’s, frente al Ministerio de Salud, Pavas. | AH43: 2296-0076 | AI43: =HYPERLINK("mailto:amata@cyt.cr","amata@cyt.cr") -> amata@cyt.cr | AJ43: Lunes a Viernes de 8:00 am a 5:00 pm | AK43: Castro & de la Torre | AL43: 29.08.2016 Reducción de alcance para los ensayos IE04, IE05, IE06, IE08, IE012, IE013, IE015, IE018 para el laboratorio sede la Guaria Guanacaste / 10.03.2015 para el ensayo: IT-02 "Práctica Normal para el Capeo de Especímenes de Concreto"
A44: Laboratorios de Metrología RECOPE | C44: LC | D44: A | E44: Público | F44: LC-060 | G44: LC-053 | H44: 45378 | I44: ='17025 SAL'!$H44+$AN$1 -> 46838 | J44: 39700 | L44: Roberto Coto Rojas Lorena Acosta Solís | M44: sg.metrologia@recope.go.cr | N44: labmetrologia@recope.go.cr | O44: 2550-3553/ 2550-3750/ 8310-0137/ 8824-1443 | P44: 2537-1272 | Q44: Costa Rica | R44: Cartago, Plantel de Distibución El Alto Recope, Ochomogo Cartago | S44: Cartago | T44: 3-101-007749 | U44: =HYPERLINK("http://www.recope.go.cr/","www.recope.go.cr ") -> www.recope.go.cr | V44: Alejandro Muñoz Villalobos | W44: 1 0497 0373 | X44: Union libre | Y44: Costarricense | Z44: Economista | AA44: Cartago. San Nicolas, Ochomogo. Ruta 2, km 12. Puesto 6. | AC44: Presidente | AD44: Patricia Soto Muñoz/ Maricela Rodriguez Cespedes | AE44: El cliente de la factura debe ser: Laboratorios de Metrologia RECOPE, LC-060 | AF44: 2550-3750 | AG44: Cartago, Plantel de Distibución El Alto Recope, Ochomogo Cartago | AH44: 2537-1272 | AI44: =HYPERLINK("mailto:patricia.soto@recope.go.cr;","patricia.soto@recope.go.cr; maricela.rodriguez@recope.go.cr") -> patricia.soto@recope.go.cr; maricela.rodriguez@recope.go.cr | AJ44: 07:00 a 15:00 | AK44: RECOPE | AL44: 2019.07.01 Transición a la norma INTE-ISO/IEC 17025.2017 // Calibración de densidad, materiales de referencia certificados, AS-15-03-025 (temperatura y húmedad)
A45: IMNSA Ingenieros Consultores S.A. Laboratorio de Geotecnia y Materiales | B45: IMNSA Ingenieros Consultores Sociedad Anónima | C45: LE | D45: S | E45: Privado | F45: LE-061 | G45: LE-048 | H45: 45470 | I45: No aplica | J45: 39426 | L45: Brenda Mondragón Lagos | M45: calidadimnsa@gmail.com | N45: asistentecalidadimnsa@gmail.com | O45: (+506) 62805172/2234-1587 | P45: 2225-9551 | Q45: Costa Rica | R45: San José, Carretera a Sabanilla del Supermercado "La Cosecha" 100 m Sur, 100 m Este y 25 m Norte, Edificio # 505, Barrio Carmiol, Montes de Oca. //Alajuela, 150 al este de Ottos,s Bar, contigui a los tanques del AyA, La Guácima. | S45: San José | T45: 3-101-091498 | U45: NA | V45: Carlos A. Méndez Navas | W45: 1-268-419 | X45: Casado | Y45: Costarricense | Z45: Ingeniero Civil | AA45: San José, Carretera a Sabanilla del Supermercado "La Cosecha" 100 Sur, 100 Este y 25 Norte, Edificio # 505, Barrio Carmiol, Montes de Oca. | AC45: Presidente | AD45: Jessica Ramirez | AE45: Carretera a Sabanilla de Montes de Oca, del Supermercado "La Cosecha" 100 Sur, 100 Este y 25 Norte, Edificio # 505, Barrio Carmiol. | AF45: 2234-1587 | AG45: San José, Carretera a Sabanilla del Supermercado "La Cosecha" 100 Sur, 100 Este y 25 Norte, Edificio # 505, Barrio Carmiol, Montes de Oca. | AH45: 2225-9551 | AI45: imnsai@racsa.co.cr | AJ45: Lunes a Viernes de 8:00 a.m. a 5:30 p.m. | AK45: IMNSA
A46: Laboratorio de Análisis y Asesoría Farmacéutica LAYAFA-UCR | B46: Universidad de Costa Rica | C46: LE | D46: A | E46: Académico | F46: LE-062 | G46: LE-069 | H46: 45147 | I46: ='17025 SAL'!$H46+$AN$1 -> 46607 | J46: 40232 | L46: Dra. Jeimy Blanco Barrantes | M46: jeimyblanco@hotmail.com; jeimy.blanco@ucr.ac.cr | N46: layafa.inifar@ucr.ac.cr | O46: 2511 -3333 | P46: 2511 3426 | Q46: Costa Rica | R46: San José, Primer piso, Facultad de Farmacia Universidad de Costa Rica, San Pedro de Montes de Oca. | S46: San José | T46: 4-000-042149 | U46: NA | V46: Carlos Araya Leandro | W46: 3-0305-0948 | X46: Casado | Y46: Costarricense | Z46: Doctor en Biología con especialidad en Genética | AA46: San José, 1. Rectoría Universidad de Costa Rica 2. Primer Piso Facultad de Farmacia LAYAFA UCR San Pedro de Montes de Oca. | AC46: Rector Universidad de Costa Rica | AD46: Jefatura administrativa del INIFAR | AE46: Licda. Mónica Herrera Francis | AF46: 2511 3660 | AG46: San José, INIFAR, Primer piso, Facultad de Farmacia Universidad de Costa Rica, San Pedro de Montes de Oca. | AH46: 2511 3426 | AI46: =HYPERLINK("mailto:monica.herrera@ucr.ac.cr;","monica.herrera@ucr.ac.cr;") -> monica.herrera@ucr.ac.cr; | AJ46: L-V de 8 am a 5 pm | AK46: UCR
A47: Instituto de Investigaciones en Salud, INISA-UCR | B47: Universidad de Costa Rica | C47: LE | D47: R | E47: Académico | F47: LE-063 | G47: LE-059 | I47: ='17025 SAL'!$H47+$AN$1 -> 1460 | J47: 39487 | L47: Erick Cordero Jara | M47: sgcinisaucr@gmail.com | N47: silvia.navarroceciliano@ucr.ac.cr | O47: 2511-2150 | P47: 2511-5130 | Q47: Costa Rica | R47: San José, de la UNED en Sabanilla 300 m este y 125 m sureste, contiguo a la Escuela de Enfermería, UCR, San Pedro de Montes de Oca | S47: San José | T47: 4-000-042149 | U47: http://www.inisa.ucr.ac.cr/ | AA47: San José, de la UNED en Sabanilla 300 este y 125 sureste, contiguo a la Escuela de Enfermería, UCR, San Pedro de Montes de Oca | AC47: Rector Universidad de Costa Rica | AD47: Jazmin Solano | AE47: FUNDEVI | AF47: 2511-3050 | AG47: San José, de la UNED en Sabanilla 300 este y 125 sureste, contiguo a la Escuela de Enfermería, UCR, San Pedro de Montes de Oca | AH47: 2511-5130 | AI47: inisa@ucr.ac.cr | AJ47: 8:00 a 12:00 y 1:00 a 5:00 | AK47: UCR | AL47: 25.10.2018 Reducción Voluntaria
A48: Laboratorio de Ensayo del Laboratorio de Eficiencia Energética - ICE | B48: Instituto Costarricense de Electricidad | C48: LE | D48: A | E48: Público | F48: LE-064 | G48: LE-055 | H48: 45453 | I48: No aplica | J48: 39735 | L48: Mónica Porras Bolaños | M48: mporrasb@ice.go.cr | N48: icelee@ice.go.cr | O48: 2000-4127 | P48: 2213-09-83 | Q48: Costa Rica | R48: San José, 200 m Oeste de DEMASA, Rincón Grande de Pavas. | S48: San José | T48: 4-000-421-39 | U48: =HYPERLINK("http://www.grupoice.com/wps/portal/elect_ahorro_LabEficEnergetica;","http://www.grupoice.com/wps/portal/elect_ahorro_LabEficEnergetica;") -> http://www.grupoice.com/wps/portal/elect_ahorro_LabEficEnergetica; | V48: Ányelo Gerald Vargas Hernández | W48: 1-1184-313 | X48: casado | Y48: costarricense | AA48: San José, 5° piso Edificio Central del ICE, Sabana Norte. | AC48: Jefe división distribución y comercialización | AD48: Geovanny Ramírez Jiménez | AE48: Instituto Costarricense de Electricidad | AF48: 2000-85-77 | AG48: San José, Sabana Norte | AH48: 2213-09-82 | AI48: =HYPERLINK("mailto:icelee@ice.go.cr","icelee@ice.go.cr") -> icelee@ice.go.cr | AJ48: 7:00 a 16:36 | AK48: ICE | AL48: 07.06.2017 reducción de alcance para el metodo de ensayo balastro tipo reactor o CWA, para la determinación de intensisdad de corriente de arranque en la entrada del balastro.
A49: Laboratorios de Sistemas de Medición de Energía Eléctrica (LASIMEE) | C49: LC | D49: A | E49: Público | F49: LC-065 | G49: LC-052 | H49: 43917 | I49: ='17025 SAL'!$H49+$AN$1 -> 45377 | J49: 39553 | L49: Jason Meza Alvarado | M49: jmeza@cnfl.go.cr mamiranda@cnfl.go.cr | N49: esegura@cnfl.go.cr lasimee@cnfl.go.cr | O49: 2295-5613 2295-5414 | P49: 2295-1550 | Q49: Costa Rica | R49: San José, CNFL, Plantel Virilla contiguo a CAPRIS, La Uruca. | S49: San José | T49: 3-101-000046 | U49: =HYPERLINK("http://www.cnfl.go.cr/","www.cnfl.go.cr") -> www.cnfl.go.cr | V49: Victor Solís Rodriguez | W49: 2-0333-0624 | X49: casado | Y49: Costarricense | Z49: Máster en Administración de Negocios | AA49: San José, CNFL, Plantel Virilla contiguo a CAPRIS, La Uruca. | AC49: Gerente General | AD49: Rodrigo Espinosa Porras | AE49: Compañía Nacional de Fuerza y Luz | AF49: 2295-1541 | AG49: San José, CNFL, Plantel Virilla contiguo a CAPRIS, La Uruca. | AH49: 2295-1550 | AI49: =HYPERLINK("mailto:respinoza@cnfl.go.cr","respinoza@cnfl.go.cr") -> respinoza@cnfl.go.cr | AJ49: 7:00am a 3:30pm | AK49: Conmpañia Nacional de Fuerza y Luz.
A50: Laboratorio Físico Químico, Tabacalera Hondureña S.A. | C50: LE | D50: R | E50: Privado | F50: LE-067 | G50: LE-057 | H50: 43528 | I50: ='17025 SAL'!$H50+$AN$1 -> 44988 | J50: 39791 | L50: Santiago Anderson | M50: santiago_anderson@bat.com | O50: (504) 2545-3437 | P50: (504) 2545-3200 | Q50: Honduras | R50: Honduras, Boulevard del Sur Zona El cacao Apartado 64, San Pedro Sula, Cortés. | S50: San Pedro Sula | T50: O5019001047518 | U50: =HYPERLINK("http://www.bat.com/","www.bat.com") -> www.bat.com | V50: Donaldo Enrique Mejía Funez | W50: 0501-1978-09358 | X50: Casado | Y50: Hondureño | Z50: Ing Mecánico Industrial | AA50: samantha_funes@bat.com | AC50: Coordinador de Calidad | AD50: Jorge Fernandez | AE50: Jorge Fernandez | AF50: (504) 2545-3226 | AG50: Honduras, Boulevard del Sur Zona El cacao Apartado 64, San Pedro Sula. | AH50: (504) 25453200 | AI50: =HYPERLINK("mailto:jorge_fernandez@bat.com","jorge_fernandez@bat.com") -> jorge_fernandez@bat.com | AJ50: 08:00- 17:00 Lunes a Viernes | AK50: Tabacalera Hondureña S.A.
A51: ROMANAS AZOCAR | B51: SERVICIOS ELECTRÓNICOS AZOCAR LTDA. | C51: LC | D51: A | E51: Privado | F51: LC-068 | G51: LC-082 | H51: 43909 | I51: ='17025 SAL'!$H51+$AN$1 -> 45369 | J51: 40519 | L51: Gabriela Obregón Valverde | M51: calidad@azocarcr.com | N51: gobregon@azocarcr.com | O51: 2222-0000 | P51: No aplica | Q51: Costa Rica | R51: San José, diagonal a la clínica Clorito Picado, Cinco esquinas de Tibás. | S51: San José | T51: 3102261620 | U51: =HYPERLINK("http://www.romanasazocar.com;/","www.romanasazocar.com;") -> www.romanasazocar.com; | V51: Carlos Cordero Monge | W51: 1-819-558 | X51: Casado | Y51: Costarricense | Z51: Ingeniero en Electrónica | AA51: San José, diagonal a la clínica Clorito Picado, Cinco esquinas de Tibás. | AB51: calidad@azocarcr.com | AC51: Gerente General | AD51: Viviana Obregón Valverde | AE51: Servicios Electrónicos Azocar Ltda. | AF51: 2222-0000 ext: 117 | AG51: San José, diagonal a la clínica Clorito Picado, Cinco esquinas de Tibás. | AH51: No aplica | AI51: =HYPERLINK("mailto:vobregon@azocarcr.com","vobregon@azocarcr.com") -> vobregon@azocarcr.com | AJ51: Viernes de 2:30pm a 4pm | AK51: Servicios Electrónicos Azocar Limitada
A52: CEMENTOS PROGRESO COSTA RICA, SOCIEDAD ANÓNIMA | B52: CEMENTOS PROGRESO COSTA RICA, SOCIEDAD ANÓNIMA | C52: LE | D52: A | E52: Privado | F52: LE-070 | G52: LE-058 | H52: 45407 | I52: ='17025 SAL'!$H52+$AN$1 -> 46867 | J52: 39791 | L52: Luis Ernesto Baltodano Segura | M52: luis.baltodano@cempro.com | N52: adrian.alvarez@cempro.com; luis.cedeno@ext.cempro.com; silvia.rodriguez@cempro.com | O52: 2201-2000, ext 11224 | P52: 2201-8200 | Q52: Costa Rica | R52: Guanacaste, 5 Km al Este del Puente La Amistad, Colorado, Las Juntas de Abangares. | S52: Guanacaste | T52: 3-101-018809 | U52: =HYPERLINK("http://www.cemexcostarica.com/","www.cemexcostarica.com") -> www.cemexcostarica.com | V52: Andres Bolaños Amerling | W52: 4-0182-0469 | X52: Casado | Y52: Costarricense | Z52: Ingeniero Industrial | AA52: San José, Plaza Roble, Edificio el Pórtico, 3°er piso, Escazú. | AC52: Director de Planeación | AD52: Jennifer Serrano Madrigal | AE52: Jennifer Serrano Madrigal | AF52: 2201-2000 | AG52: Guanacaste, Colorado de Abangares. | AH52: 2201-8202 | AI52: jennifer.serranomadrigal@ext.cemex.com; | AJ52: L-V 8-5 pm | AK52: Cemex de Costa Rica
A53: Laboratorio Aseguramiento de la Calidad Dos Pinos | B53: Cooperativa de Productores de Leche Dos Pinos R.L | C53: LE | D53: A | E53: Privado | F53: LE-071 | G53: LE-056 | H53: 44260 | I53: ='17025 SAL'!$H53+$AN$1 -> 45720 | J53: 39791 | K53: A01: 09 de diciembre del 2008 A02: 25 de mayo del 2010 A03: 27 de marzo del 2012 A04: 02 de diciembre del 2013 A05: 26 de mayo del 2015 A06: 11 de julio del 2023 | L53: Erika Vargas Salazar | M53: ervargas@dospinos.com | N53: aroda@dospinos.com; jurojasv@dospinos.com | O53: 2437-3408 / 2437-3469 | P53: 2437-3070 | Q53: Costa Rica | R53: Alajuela, 7 km oeste Aeropuerto Internacional Juan Santa María, contiguo a Zona Franca Best. El Coyol, Alajuela. | S53: Alajuela | T53: 3-004-045002 | U53: =HYPERLINK("http://www.dospinos.com/","www.dospinos.com ") -> www.dospinos.com | V53: Digna María Moya Gónzalez | W53: 2-0380-0696 | X53: Casado | Y53: Costarricense | Z53: Licenciado en Contaduría Pública | AA53: Residencia: Alajuela, residencial Hacienda los Reyes Instalaciones: Alajuela, Cooperativa de Productores de Leche Dos Pinos R.L., 7 km oeste Aeropuerto Intl Juan Santa María, contiguo a Zona Franca Best. El Coyol, Alajuela. acalderonm@dospinos.com | AC53: Gerente General Interino | AD53: Rocío Brenes Gamboa | AE53: Cooperativa de Productores de Leche Dos Pinos R.L. | AF53: 2437-3408 | AG53: Alajuela, 7 km oeste Aeropuerto Internacional Juan Santa María, contiguo a Zona Franca Best. El Coyol, Alajuela. | AH53: 2437-3070 | AI53: =HYPERLINK("mailto:rbrenes@dospinos.com;","rbrenes@dospinos.com;") -> rbrenes@dospinos.com; | AJ53: De lunes a viernes de 7:30 a 16:30 | AK53: Cooperativa de Productores de Leche Dos Pinos R.L. | AL53: 23.01.2017 reducción de alcance para el ensayo Leche en polvo íntegra, semidescremada y descremada. Suero lácteo en polvo. 05.12.2016 reducción de alcance para los ensayos Alimento balanceado para animales y materia prima, Alimento balanceado para animales y materias primas (A1) Maíz amarillo y harina de soya. (A3), Leche fluida (A2) / 05.03.2013 reducción de alcance para los ensayos de Análisis de Salmonella y Listeria en el laboratorio con sede en San Carlos
A54: Departamento de Aseguramiento de la Calidad (Productora La Florida S.A.) | C54: LE | D54: R | E54: Privado | F54: LE-072 | G54: LE-061 | I54: ='17025 SAL'!$H54+$AN$1 -> 1460 | J54: 40036 | L54: Giselle Morera | M54: =HYPERLINK("mailto:giselle.morera@Fifco.com;","giselle.morera@Fifco.com; ") -> giselle.morera@Fifco.com; | N54: =HYPERLINK("mailto:gustavo.lopez@fifco.com","gustavo.lopez@fifco.com") -> gustavo.lopez@fifco.com | O54: 2437-7140 / 2437-7216 | P54: 2431-0584 | Q54: Costa Rica | R54: 100 m este del puente sobre Río Segundo | T54: 3-101-306901 | U54: =HYPERLINK("http://www.florida.co.cr/","www.florida.co.cr") -> www.florida.co.cr | V54: Ramón De Mendiola | W54: 1-679-993 | X54: Casado | Y54: Costarricense | Z54: Ejecutivo | AA54: Apdo. 795-1000 San Jose, Costa Rica | AC54: Director General Regional de FIFCO | AD54: Rafael Adrián Guzmán | AE54: Productora La Florida S.A. | AF54: 24377179 | AG54: 100 m este del puente sobre Río Segundo | AH54: 24310584 | AI54: =HYPERLINK("mailto:ronney.lemaire@Fifco.com","ronney.lemaire@Fifco.com") -> ronney.lemaire@Fifco.com | AJ54: 7:00 a.m - 4:30p.m | AK54: Productora La Florida S.A. | AL54: 11.11.2014 Retiro de la acreditación / Suspensión voluntaria total del alcance desde el 08.10.2013 hasta el 24.06.2014, 25.09.2013 Reducción de alcance en los ensayos de Determinación de aire en producto terminado cerveza; Dióxido de carbono en producto terminado cerveza.
A55: Laboratorio de Control de Calidad MC | C55: LE | D55: R | E55: Privado | F55: LE-073 | G55: LE-071 | I55: ='17025 SAL'!$H55+$AN$1 -> 1460 | J55: 40246 | L55: Ing. Edgar Leonel Vargas Galeano | M55: e.vargas@mc-farmaceutica.com; | N55: e.vargas@mc-farmaceutica.com | O55: (504) 2225-2381 | P55: (504) 2225-2374 | Q55: Honduras | R55: Honduras, Zona Tiloarque, Boulevard FF.AA, Costado Oeste de Plaza Millennium, Tegucigalpa. | S55: Tegucigalpa | T55: 0801 9995 221448 | U55: =HYPERLINK("http://www.mcfarmaceutica.com;/","www.mcfarmaceutica.com; ") -> www.mcfarmaceutica.com; | V55: Ricardo Castillo Callejas | W55: 0801-1950-03838 | X55: Casado | Y55: Hondureña | Z55: Licenciado En Economia | AA55: Honduras, Zona Tiloarque, Boulevard FF.AA, Costado Oeste de Plaza Millennium, Tegucigalpa. | AC55: Gerente General | AD55: Sra. Amparo Hernandez | AE55: Amparo Hernandez | AF55: (504)2225-5211 | AG55: Honduras, Colonia Tiloarque, Blvd FFAA, Costado Oeste Edificio Plaza Millennium Apdo. Postal No. 4500, Comayaguela, M.D.C., Tegucigalpa. | AH55: (504)2225-2374 | AI55: =HYPERLINK("mailto:ahernandezmc@hotmail.com","ahernandezmc@hotmail.com") -> ahernandezmc@hotmail.com | AJ55: 8 h 00 min - 17 h 00 min | AK55: Laboratorio de Control de Calidad MC | AL55: Se puede verificar si hay transferncia o cheque con Isabel Hernandez
A56: Jordanlab S. de R.L. de C.V. | C56: LE | D56: R | E56: Privado | F56: LE-074 | G56: LE-062 | I56: ='17025 SAL'!$H56+$AN$1 -> 1460 | J56: 40072 | L56: Rosa Lilia Jordán Alvarenga | M56: =HYPERLINK("mailto:jordanlab@sulanet.net;","gerencia@jordanlab.com; jordanlab@sulanet.net; ") -> gerencia@jordanlab.com; jordanlab@sulanet.net; | O56: (504) 2557-5802 (504) 2557-2753 | P56: (504) 2557-5802 | Q56: Honduras | R56: Honduras, B° El Benque, 6 Ave. 5 y 6 Calle, S.O. Plaza Victoria, Local 21, San Pedro Sula, Cortés. | S56: San Pedro Sula | T56: 5019003084077 | U56: =HYPERLINK("http://www.jordanlab.com;/","www.jordanlab.com;") -> www.jordanlab.com; | V56: Rosa Lilia Jordán Alvarenga | W56: 0501-1953-02058 | X56: Soltera | Y56: Hondureña | Z56: Lic. Microbiologia y Quimica Clinica | AA56: Honduras, B° El Benque, 6 Ave. 5 y 6 Calle, S.O. Plaza Victoria, Local 21, San Pedro Sula, Departamento de Cortés. | AC56: Gerente General | AD56: Gerente General | AE56: Rosa Lilia Jordán | AF56: (504) 2557-5802 (504) 2557-2753 | AG56: Honduras, B° El Benque, 6 Ave. 5 y 6 Calle, S.O. Plaza Victoria, Local 21, San Pedro Sula, Departamento de Cortés. | AH56: (504) 2557-5803 | AI56: jordanlab@sulanet.net; jordanadm@sulanet.net | AJ56: Lunes a Jueves 08 00 h - 17 00 h Viernes 08 00 h - 16 00 h | AK56: Jordanlab S. de R.L. de C.V. | AL56: 29.08.2016 Retiro de acreditaciòn / Favor enviar copia de notificaciones al siguiente correo electronico: jordanadm@sulanet.net
A57: Laboratorio de Calibración Desarrollos Latinoamericanos de Metrología Integrada (DMI) | B57: Desarrollos Latinoamericanos de Metrología Integrada Sociedad Anónima | C57: LC | D57: A | E57: Privado | F57: LC-075 | G57: LC-081 | H57: 44182 | I57: ='17025 SAL'!$H57+$AN$1 -> 45642 | J57: 40491 | L57: Emanuel Quirós Gamboa | M57: emanuel.quiros@dmimetrologia.com | N57: calidad@dmimetrologia.com; | O57: 22-88-31-60 | P57: 2288-3159 | Q57: Costa Rica | R57: San José, 100 m al Oeste de la Agencia del Banco Nacional, Escazú. | S57: San José | T57: 3-101-403462 | U57: =HYPERLINK("http://www.dmimetrologia.com/","www.dmimetrologia.com") -> www.dmimetrologia.com | V57: Edwin Quirós Villalobos | W57: 1-0486-0945 | X57: Casado | Y57: Costarricense | Z57: Ingeniero Industrial | AA57: San José, 100 al Oeste de la Agencia del Banco Nacional, Escazú. | AC57: Gerente | AD57: Carol Duarte Guzmán | AE57: Desarrollos Latinoamericanos de Metrologia Integrada S.A. | AF57: 22-88-31-60 | AG57: San José, 100 al Oeste de la Agencia del Banco Nacional, Escazú. | AH57: 22-88-31-59 | AI57: administrativofinanciero@dmimetrologia.com | AJ57: de L a V de 8:00 am a 5 pm. | AK57: Desarrollos Latinoamericanos de Metrología Integrada | AL57: De 12:30 md a 1:30 pm cerrado por almuerzo
A58: Calibraciones de América CAMERICA S.A. | B58: Calibraciones de América CAMERICA Sociedad Anónima | C58: LC | D58: A | E58: Privado | F58: LC-076 | G58: LC-065 | H58: 43850 | I58: ='17025 SAL'!$H58+$AN$1 -> 45310 | J58: 40099 | L58: Luis Alfonso Abarca Camacho | M58: labarca@camericacr.com | N58: calidad@camericacr.com; bcampos@camericacr.com | O58: 2280-2885 | P58: n/aplica | Q58: Costa Rica | R58: San José, 300 m Oeste de la casa Presidencial, Zapote. | S58: San José | T58: 3-101-485067 | U58: www.camericacr.com | V58: Luis Alfonso Abarca Camacho | W58: 3-0319-0854 | X58: Soltero | Y58: Costarricense | Z58: Fisico | AA58: San José, 300 Oeste de la casa Presidencial, Zapote. | AC58: Gerente General Gerente Tecnico. | AD58: Milagro Vanegas Navarro | AE58: Calibraciones de América CAMERICA S.A | AF58: 2280-2885 | AG58: San José, 300 Oeste de la casa Presidencial, Zapote. | AH58: 2280-2885 | AI58: mvenegas@camericacr.com; labarca@camericacr.com; | AJ58: de L a V de 8:00 am a 5 pm. | AK58: Calibraciones de América CAMERICA S.A. | AL58: Por favor enviar copia de comunicados al
A59: Laboratorio de Análisis Industriales S. de R.L. "MQ" | C59: LE | D59: R | E59: Privado | F59: LE-077 | G59: LE-063 | I59: ='17025 SAL'!$H59+$AN$1 -> 1460 | J59: 40085 | L59: Patricia Villafranca Rossner | M59: patricia.villafranca@labmq.com;patricia.villafranca@labmq.com; Robin.garcia@labmq.com; info@labmq.com; nadezda.chang@labmq.com | O59: ( 504) 2221-0242 | P59: (504) 2221 - 0242 | Q59: Honduras | R59: Honduras, Colonia Matamoros ,con Reposteria El Hogar, Tegucigalpa. | S59: Tegucigalpa | T59: RTN 8019995332108 | U59: N.A | V59: Patricia Villafranca Rossner | W59: 501195700399 | X59: Casada | Y59: Hondureña | Z59: Microbióloga y Química Clínica | AA59: Honduras, Colonia Matamoros ,con Reposteria El Hogar, Tegucigalpa. | AC59: Gerente | AD59: Patricia Villafranca Rossner | AE59: Laboratorio de analisis industriales MQ | AF59: (504) 2221 - 0242 | AG59: Honduras, Colonia Matamoros ,con Reposteria El Hogar, Tegucigalpa. | AH59: (504) 2221 - 0242 | AI59: =HYPERLINK("mailto:patricia.villafranca@labmq.com;","patricia.villafranca@labmq.com;") -> patricia.villafranca@labmq.com; | AJ59: 8:00 am - 5:00 pm | AK59: Laboratorio de Análisis Industriales S. de R.L. "MQ" | AL59: 13.10.2015 Retiro de acreditación voluntario.
A60: Suplilab S.A. | C60: LE | D60: A | E60: Privado | F60: LE-078 | G60: LE-079 | H60: 45128 | I60: ='17025 SAL'!$H60+$AN$1 -> 46588 | J60: 40421 | L60: Dr. Mario Chaves Villalobos | M60: mario.chaves@suplilabcr.com; gestioncalidad@suplilabcr.com | N60: gestioncalidad@suplilabcr.com | O60: 2281-2000 | P60: 2281-2728 | Q60: Costa Rica | R60: San José, De la iglesia Católica de Zapote 125 m al Sur, Zapote | S60: San José | T60: 3-101-195120 | U60: NA | V60: Mario Chaves Villalobos | W60: 4-0117-0180 | Y60: Costarricense | Z60: Doctor | AA60: San José, De la iglesia Católica de Zapote 125 m al Sur, Zapote | AC60: Gerente | AD60: Karol Rivas Palma | AE60: Suplilab S.A. | AF60: 2281-2729 | AG60: San José, De la iglesia Católica de Zapote 125 m al Sur, Zapote | AH60: 2281-2728 | AI60: karol.rivas@suplilabcr.com; suplilab@racsa.co.cr; | AJ60: de L a V de 8:00 am a 5 pm. | AK60: Suplilab S.A. | AL60: De 12 md a 1:00 pm cerrado por almuerzo 24/11/25: Cambio de representante legal por salida de Doña Flory Mora Delgado
A61: INGEOTEC S.A. | B61: INGEOTEC Sociedad Anónima | C61: LE | D61: A | E61: Privado | F61: LE-079 | G61: LE-060 | H61: 43907 | I61: ='17025 SAL'!$H61+$AN$1 -> 45367 | J61: 40036 | L61: Marco Valverde Mora | M61: ingvalverde@ingeotec-cr.com | N61: ssoto@ingeotec-cr.com; gestiondecalidad@ingeotec-cr.com | O61: 2294-4026 /2294-4010 | P61: 2294-4026 | Q61: Costa Rica | R61: San José, de la estación de servicio el Trapiche, 600 m norte y 100 m oeste, Dulce Nombre de Coronado. | S61: San José | T61: 3-101-161663 | U61: =HYPERLINK("http://www.ingeotec-cr.com/","www.ingeotec-cr.com") -> www.ingeotec-cr.com | V61: Sergio Sáenz Aguilar | W61: 4-0114-0344 | X61: Casado | Y61: Costarricense | Z61: Ingeniero Civil | AA61: San José, de la estación de servicio el Trapiche, 600 norte y 100 oeste, Dulce Nombre de Coronado. | AB61: ingvalverde@ingeotec-cr.com | AC61: Presidente | AD61: Facturación y cobro | AE61: Andrea Castro Solís | AF61: 2294-4010 | AG61: San José, de la estación de servicio el Trapiche, 600 norte y 100 oeste, Dulce Nombre de Coronado. | AH61: 2294-4026 | AI61: fe@ingeotec-cr.com acastro@ingeotec-cr.com | AJ61: 8:00 a.m a 5:00 a.m | AK61: INGEOTEC S.A.
A62: Instituto de Innovación en Biotecnología e Industria (IIBI) | C62: LE | D62: A | E62: Público | F62: LE-080 | G62: LE-064 | H62: 45443 | I62: ='17025 SAL'!$H62+$AN$1 -> 46903 | J62: 40099 | L62: Elsa Nurys Villegas de la Rosa | M62: evillegas@iibi.gob.do | N62: aalvarez@iibi.gob.do | O62: (809) 566-8121 ext. 2999 | P62: ( 809 ) 227-8810 | Q62: República Dominicana | R62: República Dominicana, Calle Oloff Palme esq. Av. Nuñez de Caceres, San Gerónimo, Santo Domingo. | S62: Santo Domingo | T62: 001-0795292-1 | U62: =HYPERLINK("http://www.iibi.gov.do/","www.iibi.gov.do") -> www.iibi.gov.do | V62: Osmar Antono Olivo Sosa | Y62: Dominicana | Z62: Ingeniero agronomo | AA62: Santo Domingo, C/ Oloff Palme esq. Av. Nuñez de Caceres, San Gerónimo.Edificio verde con naranja | AC62: Director Ejecutivo | AD62: Contabilidad | AE62: Kennedy Vargas Hernandez | AF62: 809-566-8121 ext 2094 | AG62: Calle Olof Palme, esquina Núñez de Cáceres, San Gerónimo, Santo Domingo, Distrito Nacional, República Dominicana | AH62: 809-548-7760 | AI62: kvargas@iibi.gob.do | AJ62: 8:00 a.m. a 4:30 p-m Lunes a Viernes | AK62: Instituto de Innovación en Biotecnología e Industria (IIBI) | AL62: Suspensión por medida cauteral del 6/3/2024 hasta el cierre de las NC del periodo 2023
A63: Laboratorio Químico Agrícola, FHIA | C63: LE | D63: R | E63: Privado | F63: LE-082 | G63: LE-075 | I63: ='17025 SAL'!$H63+$AN$1 -> 1460 | J63: 40337 | L63: Idalia Morán | M63: laboratorio_lqa@fhia-hn.org | N63: gcalidadlqa@gmail.com; moranidalme17@gmail.com | O63: (504) 2668-2887 / (504) 2668-2470 | P63: (504) 2668-2313 | Q63: Honduras | R63: Honduras, Col. Sula, Contiguo Inst. Patria, La Lima, Cortés. | S63: Cortés | T63: RTN 05129999189738 | U63: =HYPERLINK("http://www.fhia.org.hn;/","www.fhia.org.hn;") -> www.fhia.org.hn; | V63: Adolfo Martínez | W63: C.R. 2912200503610 | X63: Casado | Y63: Estadounidense | Z63: Doctor en Economía Agrícola | AA63: Honduras, Col. Sula, Contiguo Inst. Patria, La Lima Cortes. | AC63: Honduras, Col. Sula, Contiguo Inst. Patria, La Lima Cortes. | AD63: Honduras, Col. Sula, Contiguo Inst. Patria, La Lima Cortes. | AE63: Honduras, Col. Sula, Contiguo Inst. Patria, La Lima Cortes. | AF63: Honduras, Col. Sula, Contiguo Inst. Patria, La Lima Cortes. | AG63: Honduras, Col. Sula, Contiguo Inst. Patria, La Lima Cortes. | AH63: (504) 26682313 | AI63: =HYPERLINK("mailto:Laboratorioquimicoagricola@gmail.com;","Laboratorioquimicoagricola@gmail.com;") -> Laboratorioquimicoagricola@gmail.com; | AJ63: Lunes a jueves de 7:00 a.m. a 4:00 p.m. Viernes de 7:00 a.m. a 3:00 p.m. | AK63: Laboratorio Químico Agrícola, FHIA | AL63: 11/6/2019. Retiro voluntario a la acreditación
A64: INSUMA S.A. | B64: Ingeniería Suelos y Materiales INSUMA | C64: LE | D64: A | E64: Privado | F64: LE-083 | G64: LE-068 | H64: 44041 | I64: ='17025 SAL'!$H64+$AN$1 -> 45501 | J64: 40162 | L64: José Joaquín Ocampo Salas | M64: jocampo@insuma.co.cr | N64: jrodriguez@insuma.co.cr | O64: 2234-5070 | P64: No aplica | Q64: Costa Rica | R64: San José, Costado este del parqueo de los empleados de la Casa Presidencial, Zapote | S64: San José | T64: 3101063882 | U64: =HYPERLINK("http://www.insuma.co.cr/","www.insuma.co.cr") -> www.insuma.co.cr | V64: José Antonio Rodriguez Barquero | W64: 1-469-970 | X64: Casado | Y64: Costarricense | Z64: Ingeniero Civil | AA64: San José, Costado este del parqueo de los empleados de la Casa Presidencial, Zapote | AB64: jocampo@insuma.co.cr, jrodriguez@insuma.co.cr | AC64: Gerente General | AD64: Crédito y cobro | AE64: Miriam Guzmán Calderón | AF64: 2234-5070 | AG64: San José, Costado este del parqueo de los empleados de la Casa Presidencial, Zapote | AH64: No aplica | AI64: recepcionfacturas@insuma.co.cr | AJ64: 08:00 a.m. a 2:00 p.m. | AK64: INSUMA S.A.
A65: Laboratorios Agroindustriales de Centroamérica | C65: LE | D65: R | E65: Privado | F65: LE-084 | G65: LE-067 | I65: ='17025 SAL'!$H65+$AN$1 -> 1460 | J65: 40127 | L65: José Alcerro | M65: gestiondecalidad@agroindustriales.hn; gestiondecalidad@agroindustriales.hn | O65: (504) 2508-3825/26 | P65: (504) 2552-8052 | Q65: Honduras | R65: Honduras, Colonia Prado Bajo, Avenida 10-11, calle 17,San Pedro Sula, Cortés | S65: San Pedro Sula | T65: 59 | U65: =HYPERLINK("http://www.grupoc.hn/ecolova","www.grupoc.hn/ecolova") -> www.grupoc.hn/ecolova | V65: Rony Carrillo Josch | W65: 501196807780 | X65: Casado | Y65: Hondureño | Z65: Ing. Quimico | AA65: =HYPERLINK("mailto:ronyc@tecnossuplier.com;","ronyc@tecnossuplier.com; ") -> ronyc@tecnossuplier.com; | AC65: Alta Direccion | AD65: Karina Leiva | AE65: Karina Leiva | AF65: (504)2552-8052 / (504) 2669-5145 | AG65: Honduras, Colonia Prado Bajo, Avenida 10-11, calle 17,San Pedro Sula, Cortés | AH65: 504-2552-8187 | AI65: =HYPERLINK("mailto:k.leiva-ecolova@grupoc.hn;","k.leiva-ecolova@grupoc.hn;") -> k.leiva-ecolova@grupoc.hn; | AJ65: 8am-5 pm | AK65: Ecolova S. de R. L. de C. V. | AL65: 03.02.2017 Retiro de la acreditación de manera voluntaria. Se incluye el correo de Grettel Rodriguez
A66: IHCAFE | C66: LE | D66: R | E66: Privado | F66: LE-085 | G66: LE-076 | H66: 45118 | I66: ='17025 SAL'!$H66+$AN$1 -> 46578 | J66: 40344 | L66: Marilyn J. Colindres | M66: marijassel14@gmail.com | O66: (504)2556-9100 | P66: (504)2556-5030 | Q66: Honduras | R66: Honduras, Centro Nacional de Calidad, 33 calle, 1 y 2 avenida sector El Cacao, contiguo a Toyota, San Pedro Sula, Cortés. | S66: San Pedro Sula | T66: Decreto No. 213-2000 Cédula Jurídica: 08019995355619 | U66: =HYPERLINK("http://www.ihcafe.hn/","http://www.ihcafe.hn/") -> http://www.ihcafe.hn/ | V66: Adilson Manuel Avila Casco | W66: 711196900055 poner un cero como primer número | X66: Casado | Y66: Hondureño | Z66: Licenciado en Administración de Empresas | AA66: Honduras, Colonia Luis Landa, costado norte oficinas R.N.P., edificio Asterio Reyes Hernández, Tegucigalpa | AC66: Gerente General | AD66: Orieta Pinto | AE66: IHCAFE | AF66: (504) 25569100 | AG66: Honduras, 33 Ca SO, 1-2 Avenida, Sector El Cacao, San Pedro Sula. | AH66: (504) 25565030 | AI66: =HYPERLINK("mailto:opinto@ihcafe.hn","opinto@ihcafe.hn") -> opinto@ihcafe.hn | AJ66: lunes a viernes de 8 am a 4 pm | AK66: IHCAFE | AL66: Se está en la espera de un documento apostillado con el RTN de IHCAFE. Esto se solicitó en una reunión realizada el 28/03/2023. Dijeron que durarían unas semanas en enviarse Se recibió el pasaporte del representante legal el 29/03/2023.
A67: Laboratorio de Calibración del Laboratorio Nacional de Materiales y Modelos Estructurales LANAMME-UCR. | B67: Universidad de Costa Rica | C67: LC | D67: A | E67: Académico | F67: LC-086 | G67: LC-077 | H67: 45147 | I67: ='17025 SAL'!$H67+$AN$1 -> 46607 | J67: 40372 | L67: Ing. Humberto Tioli mora | M67: direccion.lanamme@ucr.ac.cr; jose.tioli@ucr.ac.cr | N67: emmanuel.badilla@ucr.ac.cr; maria.castrosoto@ucr.ac.cr | O67: 2511-2500/ 2511-2514 | P67: 2511-4440 | Q67: Costa Rica | R67: San José, 500 m Norte de Supermercado Muñoz & Nanne, Ciudad de la Investigación, Universidad de Costa Rica, San Pedro de Montes de Oca. | S67: San José | T67: 4-000-042149 | U67: =HYPERLINK("http://www.lanamme.ucr.ac.cr/","http://www.lanamme.ucr.ac.cr/ ") -> http://www.lanamme.ucr.ac.cr/ | V67: Carlos Araya Leandro | W67: 3-0305-0948 | X67: Casado | Y67: Costarricense | Z67: Doctor en Biología con especialidad en Genética | AA67: San José, Universidad de Costa Rica, Ciudad Universitaria Rodrigo Facio, Contiguo a la Fac. de Ciencias Agroalimentarias. San Pedro de Montes de Oca. | AC67: Rector Universidad de Costa Rica | AD67: Ing. Humberto Tioli | AE67: Universidad de Costa Rica | AF67: 2511-2514 | AG67: San José, 500 Norte de Supermercado Muñoz & Nanne, Ciudad de la Investigación, Universidad de Costa Rica, San Pedro de Montes de Oca. | AH67: 2511-4440 | AI67: jose.tioli@ucr.ac.cr; maria.castrosoto@ucr.ac.cr; randall.valle@ucr.ac.cr; facturacionelectronica.lanamme@ucr.ac.cr; emmanuel.badilla@ucr.ac.cr | AJ67: 08:00 - 17:00 | AK67: UCR | AL67: Facturar a nombre de: Universidad de Costa Rica
A68: AgroBioTek Laboratorios S. de R.L. | C68: LE | D68: R | E68: Privado | F68: LE-087 | G68: LE-078 | I68: ='17025 SAL'!$H68+$AN$1 -> 1460 | J68: 40386 | L68: Gabriel Humberto Cosenza Sutton | M68: =HYPERLINK("mailto:gcosenza@agrobiotek.com;","gcosenza@agrobiotek.com;") -> gcosenza@agrobiotek.com; | O68: (504) 2238-0872 | P68: (504) 2552-7116 | Q68: Honduras | R68: San Pedro Sula Ubicado en Edificio San Remo, Bario El Benque, San Pedro Sula, Cortes. Tegucigalpa Ubicado en Edificio Santa Barbara, Barrio Concepción, Tegucigalpa, Francisco Morazan. | S68: San Pedro Sula/ Tegucigalpa | T68: RTN 08019995355582 | U68: =HYPERLINK("http://www.agrobiotek.com;/","www.agrobiotek.com;") -> www.agrobiotek.com; | V68: Gabriel Humberto Cosenza Sutton | W68: 0801-1982-18344 | X68: Casado | Y68: Hondureño | Z68: P.h.D Microbiología de Alimentos | AA68: Honduras, Edificio Santa Bárbara 3er Piso, 3 Ave 7-8 calle, Tegucigalpa. | AC68: Gerente General | AD68: Mabel Carias | AE68: Mabel Carias | AF68: 504 2238-0864 | AG68: Honduras, Edificio Santa Bárbara 3er Piso, 3 Ave 7-8 calle, Frente a La Policlínica, Tegucigalpa. | AH68: 504 2238-0864 | AI68: =HYPERLINK("mailto:mcarias@agrobiotek.com;","mcarias@agrobiotek.com;") -> mcarias@agrobiotek.com; | AJ68: 8am a 5pm | AK68: AgroBioTek Laboratorios S. de R.L. | AL68: Retiro de acreditación 16/01/2019
A69: Laboratorio Nacional de Análisis de Residuos (LANAR) | C69: LE | D69: A | E69: Privado | F69: LE-088 | G69: LE-070 | H69: 45462 | I69: ='17025 SAL'!$H69+$AN$1 -> 46922 | J69: 40232 | L69: Farida Salgado | M69: fsalgado@oirsa.org | N69: bcastellanos@oirsa.org | O69: (504) 2245-8081 | P69: (504) 2245-7361 | Q69: Honduras | R69: Honduras, Colonia San José del pedregal calle principal contiguo al Instituto Alfonso Guillen Zelaya, Tegucigalpa. | S69: Tegucigalpa | T69: 3-101556575 | U69: NA | V69: Fárida Inés Salgado | W69: 0801-1980-01714 | X69: Casada | Y69: hondureña | Z69: Química Farmacéutica | AA69: Honduras, Colonia San José del pedregal calle principal contiguo al Instituto Alfonso Guillen Zelaya, Tegucigalpa. | AC69: Gerente | AD69: Melvin Valerio | AE69: OIRSA/LANAR | AF69: (504) 2245-8081 | AG69: Honduras, Colonia San José del pedregal calle principal contiguo al Instituto Alfonso Guillen Zelaya, Tegucigalpa. | AH69: (504) 22457361 | AI69: =HYPERLINK("mailto:mvalerio@oirsa.org","mvalerio@oirsa.org") -> mvalerio@oirsa.org | AJ69: de L a J de 8:00 am a 5 pm Viernes de 8:00 am a 4 pm | AK69: Laboratorio Nacional de Análisis de Residuos (LANAR) | AL69: Se modifica el alcance de acreditación debido al levantamiento de la suspensión total del alcance de acreditación por medida cautelar. Esto fue aprobado por Comisión de Acreditación mediante acuerdo CA-007-2024-04, misma que fue notificado al OEC el 06 de marzo de 2024.
A70: Instituto de Investigaciones en Ingeniería LABCAL | C70: LC | D70: R | E70: Público | F70: LC-092 | G70: LC-090 | I70: ='17025 SAL'!$H70+$AN$1 -> 1460 | J70: 40416 | L70: Alex Núñez Mena | M70: =HYPERLINK("mailto:labcal.calidad@gmail.com","labcal.calidad@gmail.com") -> labcal.calidad@gmail.com | O70: 2511-5553 / 2511-6642 | P70: 2253-4614 | Q70: Costa Rica | R70: Diagonal a la sub-estación de la CNFL, Sabanilla, Montes de Oca | T70: 4-000-042149 | U70: =HYPERLINK("http://www.inii.ucr.ac.cr/labcal/","http://www.inii.ucr.ac.cr/labcal/") -> http://www.inii.ucr.ac.cr/labcal/ | V70: Henning Jensen Pennington | W70: 8-041-334 | X70: Casado | Y70: Costarricense | Z70: Doctor en Psicología | AA70: Sede Univesitaria Rodrigo Facio, San Pedro de Montes de Oca, Edificio Administrativo B, Segundo Piso, Oficina de Rectoría | AC70: Rector Universidad de Costa Rica | AD70: Roxana Vargas | AE70: FUNDEVI | AF70: 2511-6156 | AG70: Diagonal a la sub-estación de la CNFL, Sabanilla, Montes de Oca | AH70: 2253-4614 | AI70: =HYPERLINK("mailto:roxanalabcal@gmail.com","roxanalabcal@gmail.com; labcal.coordinacion@gmail.com") -> roxanalabcal@gmail.com; labcal.coordinacion@gmail.com | AJ70: Jueves 13 - 17 horas | AK70: UCR | AL70: Retiro de acreditación el 10.06.2014. Suspensión voluntaria total del alcance desde el 28.05.2013 hasta el 02.09.2013, prorroga de suspensión total del alcance desde el 10.09.2013 hasta el 27.05.2014
A71: Laboratorio Clínico de Pavas, COOPESALUD R.L. | C71: LE | D71: S | E71: Privado | F71: LE-093 | G71: LE-072 | H71: 45846 | I71: No aplica | J71: 40246 | L71: Karla P. Chaves Mora | M71: calidad@coopesalud.org | N71: Karla Chaves Mora, kpchaves@coopesalud.org Natalia Castillo Zeledón ncastillo@coopesalud.org Jorge Alejandro Calderón jcalderon@coopesalud.org | O71: 2231-6044 | P71: 2232-7322 | Q71: Costa Rica | R71: San José, Contiguo al Hospital Psiquiátrico, Pavas. | S71: San José | T71: 3-004-087662 | U71: =HYPERLINK("http://www.coopesalud.org;/","www.coopesalud.org;") -> www.coopesalud.org; | V71: Alberto Ferrero Aymerich | W71: 1-0701-0193 | X71: Casado en segundas nupcias | Y71: Costarricense | Z71: Médico General | AA71: San José, Contiguo al Hospital Psiquiátrico, Clínica de Pavas, Pavas | AC71: Gerente General | AD71: Marineth Vega R. | AE71: Coopesalud R.L. | AF71: 2231-6044 | AG71: San José, Contiguo al Hospital Psiquiátrico, Pavas. | AH71: 2232-7322 | AI71: =HYPERLINK("mailto:mvega@coopesalud.org","mvega@coopesalud.org") -> mvega@coopesalud.org | AJ71: 7:00 a.m. a 4:00 p.m. (L a J) 7:00 a.m. a 3:00 p.m. (V) | AK71: COOPESALUD R.L. | AL71: Se incluyen 3 representantes del OEC, es cadena de sustituciones
A72: Laboratorio de Calibración de Equipos de Medición de Bridgestone de Costa Rica | B72: Bridgestone de Costa Rica Sociedad Anónima | C72: LC | D72: A | E72: Privado | F72: LC-094 | G72: LC-083 | H72: 45272 | I72: ='17025 SAL'!$H72+$AN$1 -> 46732 | J72: 40519 | L72: Carlos Alberto Martínez Sanchez / Andrea Fonseca Fonseca | M72: martinezsanchezcarlos@la-bridgestone.com | N72: FonsecaAndrea@la-bridgestone.com, | O72: 2209-7381 2209-7300 ext: 7120/7106-4572/7105-4834 ext: 7218 | P72: 22097301 | Q72: Costa Rica | R72: Heredia, La Ribera, Kilometro 11, Autopista General Cañas, Belén. | S72: Heredia | T72: 3-101-008915 | U72: https://www.bridgestone.co.cr | V72: José Fernando Lopez Lopez. | W72: 122201367821 | Y72: Salvadoreño | AA72: Heredia, La Ribera, Kilometro 11, Autopista General Cañas, Belén. | AC72: Country Manager -Costa Rica Plant | AD72: Allan Soto Castrillo | AE72: Bridgestone de Costa Rica S.A | AF72: 22097300 | AG72: Heredia, La Ribera, Kilometro 11, Autopista General Cañas, Belén. | AH72: 22097301 | AI72: =HYPERLINK("mailto:alvarezronald@bfcr.co.cr","alvarezronald@bfcr.co.cr") -> alvarezronald@bfcr.co.cr | AJ72: de L a V de 8:00 am a 5 pm. | AK72: Bridgestone | AL72: 27.10.2016 reducción de alcance para la calibración del procedimiento IT-831-32 de magnitud Dimensional longitud/ Reducción de alcance el 10.12.2013 para la calibración de Termómetro Liquido en vidrio
A73: Laboratorio Químico de ICAFE | B73: Instituto del café de Costa Rica | C73: LE | D73: A | E73: Público | F73: LE-095 | G73: LE-084 | H73: 44008 | I73: ='17025 SAL'!$H73+$AN$1 -> 45468 | J73: 40568 | L73: Carlos Rojas Chaves | M73: crojas@icafe.cr | N73: =HYPERLINK("mailto:yalpizar@icafe.cr","yalpizar@icafe.cr") -> yalpizar@icafe.cr | O73: 2243-7874/2243-7877 | P73: 2260-1937 | Q73: Costa Rica | R73: Heredia, 400 m norte Escuela pública, San Pedro de Barva. | S73: Heredia | T73: 3-007-042037 | U73: =HYPERLINK("http://www.icafe.go.cr/","http://www.icafe.go.cr") -> http://www.icafe.go.cr | V73: Gustavo Jiménez Elizondo | W73: 1-1099-0921 | X73: Casado | Y73: costarricense | Z73: Lic. Ingeniería Electromecánico | AA73: Heredia, 400 m norte Escuela pública, San Pedro de Barva. | AC73: Director Ejecutivo A.I. | AD73: Yuly Monge loaiza | AE73: ICAFE | AF73: 2243-7869 | AG73: San José, Calle 1a, ave 18 y 20. | AH73: 2243-7852 | AI73: =HYPERLINK("mailto:ymonge@icafe.cr","ymonge@icafe.cr") -> ymonge@icafe.cr | AJ73: Lunes a viernes de 8 am a 4:30 pm | AK73: ICAFE
A74: LABCA - Laboratorio del Control de Alimentos, Agencia de Regulación Sanitaria, Dirección de Vigilancia y Fiscalización, Red de Laboratorios | C74: LE | D74: A | E74: Privado | F74: LE-096 | G74: LE-089 | I74: ='17025 SAL'!$H74+$AN$1 -> 1460 | J74: 40708 | K74: LE-089-A01: 25 de Febrero del 2014. LE-089-A02: 25 de Febrero del 2014. LE-089-A03: 10 de Marzo del 2015. LE-089-A04: 16 de Mayo del 2017. LE-089-A05: 27 de Julio del 2018. LE-089-A06: 03 de Octubre del 2018. LE-089 A07: 07 de septiembre del 2022 | L74: Zeyda Bidine Diaz Fátima Romero | M74: fatimaromero@arsa.gob.hn labca@arsa.gob.hn elisabetposadas@arsa.gob.hn | N74: Labca Arsa <labca@arsa.gob.hn; | O74: 504-2232-16-85 Ext 27 | P74: No aplica | Q74: Honduras | R74: Honduras, 3er Piso Edificio Centro de Salud Alonzo Suazo Barrio Morazán, Tegucigalpa | S74: Tegucigalpa | T74: 1707-1964-00168 | U74: NA | V74: Francis Rafael contreras Rivera | W74: 0406-1967-00218 | Y74: Hondureño | AA74: Honduras, 3er Piso Edificio Centro de Salud Alonzo Suazo Barrio Morazán, Tegucigalpa | AC74: Comisionado Presidente | AD74: No aplica | AE74: No aplica | AF74: No aplica | AG74: No aplica | AH74: No aplica | AI74: NA | AK74: Laboratorio del Control de Alimentos, Agencia de Regulación Sanitaria, Dirección de Vigilancia y Fiscalización, Red de Laboratorios
A75: MET-CAL Engineering Services S.A. | B75: MET-CAL Engineering Services Sociedad Anónima | C75: LC | D75: A | E75: Privado | F75: LC-097 | G75: LC-085 | H75: 45869 | I75: No aplica | J75: 40582 | K75: A02: 12/8/2024 | L75: Alberto José Marín Arguedas | M75: amarin@metcal.net | N75: calidad@metcal.net | O75: 2286-4286 | P75: Inhabilitado | Q75: Costa Rica | R75: San José, del Freshmarket 400 m Oeste, diagonal al Crossfit 360, Guayabos, Curridabat | S75: San José | T75: 3-101-373718 | U75: =HYPERLINK("http://www.met-cal.net/","www.met-cal.net") -> www.met-cal.net | V75: Gustavo Alonso Pérez Solano | W75: 1-0993-0538 | X75: casado | Y75: costarricense | Z75: Ingeniería Industrial, MSc. Administración de Proyectos | AA75: San José, del Freshmarket 400 m Oeste, diagonal al Crossfit 360, Guayabos, Curridabat | AC75: Miembro del Consejo Directivo y Gerente de Servicio al Cliente | AD75: Natalia Moya Estrada | AE75: Natalia Moya Estrada | AF75: 2286-4286 | AG75: San José, del Freshmarket 400 m Oeste, diagonal al Crossfit 360, Guayabos, Curridabat | AH75: Inhabilidato | AI75: =HYPERLINK("mailto:contabilidad@met-cal.net","contabilidad@met-cal.net") -> contabilidad@met-cal.net | AJ75: L a V 8 am a 4 pm | AK75: Met-Cal | AL75: Enviar notificaciones por correo electrónico a kpicado@met-cal.net . Para contactos a detallar en la página web serían info@met-cal.net y servicios@met-cal.net (estos son contactos para los clientes)
A76: Centro de Investigación en Ciencias Atómicas Nucleares y Moleculares CICANUM | B76: Universidad de Costa Rica | C76: LE | D76: A | E76: Académico | F76: LE-098 | G76: LE-087 | H76: 45147 | I76: ='17025 SAL'!$H76+$AN$1 -> 46607 | J76: 40624 | L76: Brenda Garay García | M76: calidad.cicanum@ucr.ac.cr; brenda.garay@ucr.ac.cr | O76: 2511-2427 | P76: NA | Q76: Costa Rica | R76: San José, Ciudad de la Investigación, Universidad de Costa Rica. Sabanilla, Montes de Oca. | S76: San José | T76: 4-000-042149 | U76: =HYPERLINK("http://www.cicanum.ucr.ac.cr;/","www.cicanum.ucr.ac.cr; ") -> www.cicanum.ucr.ac.cr; | V76: Carlos Araya Leandro | W76: 3-0305-0948 | X76: Casado | Y76: Costarricense | Z76: Doctor en Biología con especialidad en Genética | AA76: CICANUM Universidad de Costa Rica Apartado 11501-2060 | AC76: Rector Universidad de Costa Rica | AD76: Nancy Elizondo Control de pagos | AE76: FUNDEVI Oficina de Administración Financiera | AF76: 2511-1777 2511-4643 | AG76: San José, Ciudad de la Investigación, Universidad de Costa Rica. Sabanilla, Montes de Oca. | AH76: 2283-4640 2253-4630 | AI76: factura.electronica@fundacionucr.ac.cr Calidad.cicanum@ucr.ac.cr | AJ76: 8:00 a 16:30 8:15 a 16:30 | AK76: UCR | AL76: Antes de facturar verificar a nombre de quién debe emitirse la factura. / Bárbara Durán continua siendo Representante ante el ECA y Emmanuel Badilla es el sustituto
A77: ICE - Laboratorio de Metrología – LAMETRO | B77: Instituto Costarricense de Electricidad | C77: LC | D77: A | E77: Público | F77: LC-099 | G77: LC-092 | H77: 44022 | I77: ='17025 SAL'!$H77+$AN$1 -> 45482 | J77: 40807 | L77: Jonny Jimenez Jimenez | M77: jjimenezjim@ice.go.cr | N77: lametro@ice.go.cr | O77: 2000-0876 / 2000-6296 | P77: NA | Q77: Costa Rica | R77: Edificio N° 8, Plantel ICE Colima, Tibás, San José, Costa Rica | S77: San José | T77: 400004213902 | U77: https://grupoice.com/wps/portal/ICE/telecomunicaciones/lametro | V77: Pablo Enrique Calderón Ortiz | W77: 1-1130-0165 | X77: Casado | Y77: Costarricense | Z77: Ingeniero Eléctrico | AA77: San José, Plantel ICE Colima de Tibás, edificio Nº1, piso # 2 | AB77: Pcalderon@ice.go.cr masalas@ice.go.cr | AC77: Apoderado generalísimo con límite de suma de hasta trecientos cicuenta mil dólares | AD77: María del Pilar Ugalde Hernández | AE77: Instituto Costarricense de Electricidad | AF77: 2247-8382 | AG77: San José, Plantel ICE Colima de Tibás, contiguo al GEDI, Tibás. | AH77: 2247-8208 | AI77: dquesada@ice.go.cr , murena@ice.go.cr | AJ77: Lunes a jueves de 7 a.m. a 5 p.m. Viernes de 7 a.m. a 3 p.m. | AK77: ICE | AL77: La representación legal de Marcos Vargas Vargas se encuentra en trámite. se informa que aunque siempre se mantiene como representante legal el Ing. Marcos Vargas Vargas, por favor incluir también al Ing. Adolfo Arias Echandi. A nivel del ICE el señor Adolfo Arias es el superior jerárquico del Ing. Marcos Vargas Vargas y también es representante legal. Por lo anterior para cualquier trámite legal, como por ejemplo la firma de un compromiso de acreditación, en caso de ausencia del señor Marcos Vargas Vargas, el señor Adolfo Arias podría firmar.
A78: Laboratorio de Metrologia, PROCAME-UNA | C78: LC | D78: A | E78: Académico | F78: LC-100 | G78: LC-091 | H78: 45681 | I78: N/A | J78: 40722 | L78: Karla Vetrani | M78: procame@una.cr | N78: Karla.vetrani.chavarria@una.cr | O78: 2277-3723 | P78: 2277-3448 | Q78: Costa Rica | R78: Heredia, Campus Omar Dengo, 3 er piso Escuela de Ciencias Ambientales, Heredia. | S78: Heredia | T78: 4-000-042150-140 | U78: NA | V78: Francisco José González Alvarado | W78: 2-0451-0487 | X78: Casado | Y78: Costarricense | Z78: Máster en Educación | AA78: Heredia, Edificio Rectoría de la UNA, Calle 9 Avenida central y primera | AC78: Rector Universidad Nacional | AD78: Ligia Bermúdez Hidalgo | AE78: Universidad Nacional o FUNDAUNA según sea el caso | AF78: 2277-3448 | AG78: Heredia, Campus Omar Dengo, 3 er piso Escuela de Ciencias Ambientales, Heredia. | AH78: 2277-3448 | AI78: =HYPERLINK("mailto:procame@una.cr","procame@una.cr") -> procame@una.cr | AJ78: Lunes a Viernes de 8:00 a.m. a 5:00 p.m | AK78: UNA | AL78: En relación con la facturación se debe realizar a nombre de la Universidad Nacional en mantenimiento de la acreditación y a nombre de FUNDAUNA lo que se encuentra relacionado con auditorías
A79: Laboratorio de Ensayos Biologicos, LEBI | C79: LE | D79: R | E79: Académico | F79: LE-101 | G79: LE-088 | I79: ='17025 SAL'!$H79+$AN$1 -> 1460 | J79: 40673 | L79: Leda Gonzalez | M79: leda.gonzalez@ucr.ac.cr | N79: leda.gonzalez@ucr.ac.cr | O79: 2511-8309 | P79: 2511-3483 | Q79: Costa Rica | R79: San José, detrás de la Escuela de Medicina de la Universidad de Costa Rica, San Pedro de Montes de Oca. | S79: San José | T79: 4-000-042149 | U79: =HYPERLINK("http://www.lebi.ucr.ac.cr;/","www.lebi.ucr.ac.cr;") -> www.lebi.ucr.ac.cr; | V79: Henning Jensen Pennington | W79: 8-041-334 | X79: Casado | Y79: Costarricense | Z79: Doctor en Psicología | AA79: San José, Rectoría, Ciudad Universitaria Rodrigo Facio, San Pedro de Montes de Oca. Código Postal: 11501-2060 San José Costa Rica. | AC79: Rector Universidad de Costa Rica | AD79: Leda González Aguilera | AE79: Universidad de Costa Rica | AF79: 2511-4565 | AG79: San José, detrás de la Escuela de Medicina de la Universidad de Costa Rica, Ciudad Universitaria Rodrigo Facio, San Pedro de Montes de Oca. | AH79: 2511-3483 | AI79: =HYPERLINK("mailto:leda.gonzalez@ucr.ac.cr","leda.gonzalez@ucr.ac.cr") -> leda.gonzalez@ucr.ac.cr | AJ79: 8 a 12md y de 1 a5pm | AK79: UCR | AL79: Contactar con el LEBi. / 18.02.2019 Retiro total voluntario de la acretitación /
A80: Balanzas Ballar Costa Rica S.A. | B80: Balanzas Ballar Costa Rica S.A. | C80: LC | D80: R | E80: Privado | F80: LC-104 | G80: LC-093 | I80: ='17025 SAL'!$H80+$AN$1 -> 1460 | J80: 40813 | L80: Juan Pablo Corrales Corrales | M80: calidad@romanasballar.com | N80: ttrigueros@romanasballar.com; calidad@romanasballar.com | O80: 40001816 | P80: NA | Q80: Costa Rica | R80: Santa Rosa de Santo Domingo de Heredia, de Cosmac 50 metros sur última bodega a mano derecha. | S80: Heredia | T80: 3-101-708048 | U80: =HYPERLINK("http://www.romanasballar.com/","www.romanasballar.com") -> www.romanasballar.com | V80: Teresita Trigueros Quesada | W80: 1-0545-0906 | X80: divorciada | Y80: costarricense | Z80: comerciante | AA80: Santa Rosa de Santo Domingo de Heredia, de Cosmac 50 metros sur última bodega a mano derecha. | AC80: Gerente General | AD80: Mainor Calvo Fernández | AE80: Balanzas Ballar Costa Rica S.A. | AF80: 40001816 | AG80: Santa Rosa de Santo Domingo de Heredia, de Cosmac 50 metros sur última bodega a mano derecha. | AH80: NA | AI80: =HYPERLINK("mailto:iballar@romanasballar.com","iballar@romanasballar.com") -> iballar@romanasballar.com | AJ80: Lunes, Martes y Miercoles de 8:00 am a 4:00 pm | AK80: Balanzas Ballar Costa Rica S.A. | AL80: Copiar a todos los correos
A81: Laboratorio Bacteriológico BIOTEC | C81: LE | D81: A | E81: Privado | F81: LE-105 | G81: LE-094 | H81: 45378 | I81: ='17025 SAL'!$H81+$AN$1 -> 46838 | J81: 40890 | L81: Patricia Morera Sánchez | M81: pmorera@laboratoriobiotec.com | N81: gsoto@laboratoriobiotec.com | O81: 2440-7686 | P81: N.A | Q81: Costa Rica | R81: Alajuela, 150 m sur Parque Juan Santamaría, Calle 2, Avenida 6 y 8, Alajuela Centro. | S81: Alajuela | T81: =HYPERLINK("http://www.laboratoriobiotec.com/","3-101-317177 ") -> 3-101-317177 | U81: =HYPERLINK("http://www.laboratoriobiotec.com/","www.laboratoriobiotec.com") -> www.laboratoriobiotec.com | V81: Giovanni Soto Artavia | W81: 2-489-653 | X81: Casado | Y81: Costarricense | Z81: Microbiólogo | AA81: Alajuela, 150 m sur Parque Juan Santamaría, Calle 2, Avenida 6 y 8, Alajuela Centro. | AC81: Director Técnico | AD81: Suyin Alfaro Rojas | AE81: Laboratorio Bacteriológico Biotec | AF81: 2440-7686 | AG81: Alajuela, 150 m sur Parque Juan Santamaría, Calle 2, Avenida 6 y 8, Alajuela Centro. | AH81: N.A | AI81: =HYPERLINK("mailto:facturaciones@laboratoriobiotec.com","facturaciones@laboratoriobiotec.com") -> facturaciones@laboratoriobiotec.com | AJ81: Lunes a Viernes 8:00-12:00 y 1:00 a 5:00 | AK81: BIOTEC
A82: Laboratorio Raúl H. Melo | C82: LE | D82: R | E82: Privado | F82: LE-106 | G82: LE-086 | I82: ='17025 SAL'!$H82+$AN$1 -> 1460 | J82: 40582 | L82: Omar Peña De Coo | M82: opena@codocafe.gob.do | N82: opena.proca2@gmail.com; | O82: (809)532-9358 | P82: (809)535-3894 | Q82: República Dominicana | R82: República Dominicana, Calle Rafael Damirón, esquina Avenida Comandante Jiménez Moya, Santo Domingo | S82: Santo Domingo | T82: 4-24-00057-3 | U82: =HYPERLINK("http://www.codocafe.gov.do/","www.codocafe.gov.do") -> www.codocafe.gov.do | V82: Marino Suárez Joran | W82: 048-0010264-4 | X82: casado | Y82: Dominicano | Z82: Ingeniero Agrónomo | AA82: Santo Domingo, Calle Francisco Prats Ramírez #251, Ensanche Evaristo Morales, República Dominicana | AC82: Director Ejecutivo | AD82: Natalia Pena | AE82: Consejo Dominicano del Café | AF82: (809)532-9358 | AG82: Santo Domingo, Av. Independecia, Esq. Larimar #58, km 7 1/2 de la Sanchez | AH82: (809)535-3894 | AI82: =HYPERLINK("mailto:info@codocafe.gob.do","info@codocafe.gob.do") -> info@codocafe.gob.do | AJ82: L/V 8:00 am-4:00pm | AK82: CODOCAFE
A83: Laboratorio de Control de Calidad HOLCIM Costa Rica | B83: HOLCIM Costa Rica | C83: LE | D83: A | E83: Privado | F83: LE-107 | G83: LE-095 | H83: 43893 | I83: ='17025 SAL'!$H83+$AN$1 -> 45353 | J83: 40925 | K83: A03: 10/07/2024 | L83: Raúl Solís Steller Sergio Céspedes | M83: raul.soliss@holcim.com | N83: sergio.cespedes@holcim.com | O83: 2550-8140 8312-6707 6052-3198 | P83: 2552-8384 | Q83: Costa Rica | R83: Cartago, 3.5 km al sur de la esquina SE de los Tribunales de Justicia, Agua Caliente de Cartago | S83: Cartago | T83: 3-101-006846 | U83: =HYPERLINK("http://www.holcim.com/","www.holcim.com") -> www.holcim.com | V83: David Romero García | W83: 122201499127 | X83: Soltero | Y83: Salvadoreño | Z83: Ingeniero Químico | AA83: Cartago, 3.5 km al sur de la esquina SE de los Tribunales de Justicia, Agua Caliente de Cartago | AC83: Apoderado generalisimo sin límite de suma | AD83: Andrei Ulate | AE83: Holcim Costa Rica S.A. | AF83: 2550-8146 | AG83: Cartago, 3.5 km al sur de la esquina SE de los Tribunales de Justicia, Agua Caliente de Cartago | AH83: 2552-83-84 | AI83: andrei.ulate@holcim.com;recepcionfe-cr@lafargeholcim.com | AJ83: L-V de 7:00 a.m a 4:30 p.m | AK83: Holcim | AL83: Las facturas deben venir a nombre de la empresa y no una persona física.
A84: Referencia Laboratorio Clínico | C84: LE | D84: R | E84: Privado | F84: LE-108 | G84: LE-096 | I84: ='17025 SAL'!$H84+$AN$1 -> 1460 | J84: 40953 | L84: Lic. Amarilis Durán | M84: amarilisd@labreferencia.com | N84: amarilis7240@gmail.com | O84: (809) 221-5545 Ext. 2250 | P84: (809) 538-0081 | Q84: República Dominicana | R84: República Dominicana, Ave. Independencia No. 202, Condominio Santa Ana, Gazcue, Distrito Nacional, Santo Domingo. | S84: Santo Domingo | T84: 101128542 | U84: =HYPERLINK("http://www.labreferencia.com;/","www.labreferencia.com;") -> www.labreferencia.com; | V84: Lic. Patricia León Michel | W84: 001-1131187-4 | X84: Soltera | Y84: Dominica | Z84: Bionalista | AA84: Ave. Luperón No.3, casi esq. Mirador Sur, Zona Industrial de Herrera, Santo Domingo Oeste | AC84: Directora Ejecutiva | AD84: Lic. Marys Esteves | AE84: Gerente de Contabilidad | AF84: 221-5545 Ext. 2250 | AG84: Santo Domingo, Ave. Independencia No. 202, Condominio Santa Ana, Gazcue, Distrito Nacional. | AH84: (809)333-7545 | AI84: Mryse@labreferencia.com; | AJ84: 8 - 5 PM | AK84: Referencia Laboratorio Clínico | AL84: Fecha de retiro: 2021/01/19
A85: Proxtronics CR Ltda. | C85: LE | D85: A | E85: Privado | F85: LE-109 | G85: LE-098 | H85: 45385 | I85: ='17025 SAL'!$H85+$AN$1 -> 46845 | J85: 41037 | K85: A01: 26/06/2025 | L85: Javier Campos Segura | M85: calidad@proxcr.com | O85: (506) 2262-7332 | P85: 4034-6580 | Q85: Costa Rica | R85: Heredia, 200 m norte del Liceo Samuel Saénz Flores, Heredia | S85: Heredia | T85: 3-102-445375 | U85: =HYPERLINK("http://www.proxtronicscr.com/","www.proxtronicscr.com") -> www.proxtronicscr.com | V85: Jorge Rojas Campos | W85: 1-853-486 | X85: Casado | Y85: Costarricense | Z85: Físico | AA85: Heredia, 200 norte del Liceo Samuel Saénz Flores, Heredia | AC85: Gerente General | AD85: Cindy Pacheco | AE85: PROXTRONICS CR LTDA | AF85: 4034-6580 | AG85: Heredia, 200 norte del Liceo Samuel Saénz Flores, Heredia | AH85: NA | AI85: =HYPERLINK("mailto:servicio@proxtronicscr.com","servicio@proxtronicscr.com") -> servicio@proxtronicscr.com | AJ85: 8am - 5 pm | AK85: Proxtronics CR Ltda.
A86: Centro de Investigación en Corrosion ICE | B86: Instituto Costarricense de Electricidad | C86: LE | D86: R | E86: Público | F86: LE-112 | G86: LE-099 | I86: ='17025 SAL'!$H86+$AN$1 -> 1460 | J86: 41051 | L86: Javier Robles Cordero | M86: =HYPERLINK("mailto:jroblesco@ice.go.cr;","jroblesco@ice.go.cr; ") -> jroblesco@ice.go.cr; | N86: =HYPERLINK("mailto:jroblesco@outlook.com","jroblesco@outlook.com") -> jroblesco@outlook.com | O86: 2000-4517 | P86: 2297-4020 | Q86: Costa Rica | R86: San José, de la Metalco 500 m sur, 150 m oeste y 50 m norte, Colima de Tibás. | S86: San José | T86: =HYPERLINK("http://www.grupoice.com/wps/portal/AcercaICE_investigaCorrosion","4 0000 42139 ") -> 4 0000 42139 | U86: =HYPERLINK("http://www.grupoice.com/wps/portal/AcercaICE_investigaCorrosion","http://www.grupoice.com/wps/portal/AcercaICE_investigaCorrosion") -> http://www.grupoice.com/wps/portal/AcercaICE_investigaCorrosion | V86: Alexander Solís Barboza | W86: 1 677 013 | X86: casado una vez | Y86: Costarricense | Z86: ingeniero Civil | AA86: San José, 400 norte, Edificio UEN PySA, piso 1, Sabana Norte. | AC86: Director Negocio Ingenieria y Construcción de la Gerencia de Electricidad del ICE | AD86: NA | AE86: Carmen Rojas | AF86: 2000-5485 | AG86: San José, del Edificio Principal del ICE , 500 norte, en Sabana Norte. | AH86: 2220-8684 | AI86: =HYPERLINK("mailto:CRojasZ@ice.go.cr","CRojasZ@ice.go.cr") -> CRojasZ@ice.go.cr | AJ86: 7:00 a.m. a 4:36 p.m. | AK86: ICE
A87: Unidad de Laboratorios Químicos - ICE | B87: Instituto Costarricense de Electricidad | C87: LE | D87: A | E87: Público | F87: LE-112/118 | G87: LE-099/104 | H87: 44348 | I87: ='17025 SAL'!$H87+$AN$1 -> 45808 | J87: 41051 | K87: A01: 17/05/2023 | L87: Javier Robles Cordero | M87: jroblesco@ice.go.cr; | N87: jroblesco@outlook.com | O87: 2000-4517 | P87: 2297-4020 | Q87: Costa Rica | R87: San José, de la Metalco 500 m sur, 150 m oeste y 50 m norte, Colima de Tibás. | S87: San José | T87: 4 0000 42139 | U87: https://www.grupoice.com/wps/portal/ICE/electricidad/laboratorioss/laboratorios-metrologicosyquimicos/lab-quimicos | V87: José Joaquín Granados Ramírez | W87: 302970039 | X87: Soltero | Y87: Costarricense | Z87: Ingeniero Electromecánico | AA87: San José, Mata Redonda, Sabana Sur, Edificio ICE, Torre de Telecomunicaciones, Piso # 14 División Generación San José, Costa Rica | AB87: jogranados@ice.go.cr | AC87: Jefe División Generación | AD87: Cadena de Abastecimiento - División Generación | AE87: Sandra Hidalgo Cabrera | AF87: 2000-3087 | AG87: San José, Mata Redonda, Sabana Sur, Edificio ICE, Torre de Telecomunicaciones, Piso # 14 División Generación San José, Costa Rica | AH87: No aplica | AI87: shidalgo@ice.go.cr | AJ87: 7:00 a.m. a 4:36 p.m. | AK87: ICE
A88: Laboratorio de Investigaciones Carmen de Corporación de Desarrollo Agrícola del Monte | C88: LE | D88: R | E88: Privado | F88: LE-113 | G88: LE-100 | I88: ='17025 SAL'!$H88+$AN$1 -> 1460 | J88: 41220 | L88: Ing. Denis Morales García | M88: =HYPERLINK("mailto:DMorales1@cr.freshdelmonte.com;","DMorales1@cr.freshdelmonte.com; sanchez.kattia@cr.freshdelmonte.com") -> DMorales1@cr.freshdelmonte.com; sanchez.kattia@cr.freshdelmonte.com | N88: cjimenez3@freshdelmonte.com | O88: 2769-1415 | P88: 2769-1860 | Q88: Costa Rica | R88: Limón, frente a la Iglesia Católica, Camen 2, Siquirres. | S88: Limón | T88: 3-101-010882 | U88: NA | V88: Sr. Donald Murray Unwin | W88: 1-379-148 | X88: Casado | Y88: Costarricense | Z88: Biólogo | AA88: =HYPERLINK("mailto:DMorales1@cr.freshdelmonte.com;","DMorales1@cr.freshdelmonte.com; sanchez.kattia@cr.freshdelmonte.com") -> DMorales1@cr.freshdelmonte.com; sanchez.kattia@cr.freshdelmonte.com | AC88: Sustituto del coordinador Sistema Gestión del Laboratorio | AD88: Jefe del laboratorio | AE88: Kattya Sánchez Chan | AF88: 2769-1415 ext 4310 | AG88: Limón, frente a la Iglesia Católica, Camen 2, Siquirres. | AH88: 2769-1860 | AI88: =HYPERLINK("mailto:sanchez.kattia@cr.freshdelmonte.com","sanchez.kattia@cr.freshdelmonte.com") -> sanchez.kattia@cr.freshdelmonte.com | AJ88: 7am-12pm 1pm-5,30 pm | AK88: Corporación de Desarrollo Agrícola del Monte | AL88: 28.01.2016 Retiro de acreditación voluntaria
A89: Centro Tecnológico de Concreto (CETEC) Holcim Costa Rica | B89: HOLCIM Costa Rica | C89: LE | D89: R | E89: Privado | F89: LE-114 | G89: LE-101 | I89: ='17025 SAL'!$H89+$AN$1 -> 1460 | J89: 41338 | L89: Dilan Masis | M89: dilan.masis@lafargeholcim.com; | N89: delsa.alfaror@lafargeholcim.com | O89: 2205-2986 / 2205-2984 / 8703-2980/8326-4533 | P89: 2205-2700 | Q89: Costa Rica | R89: Cartago, 3.5 km al sur de la esquina SE de los Tribunales de Justicia, Agua Caliente de Cartago | S89: Cartago | T89: 3-101-006846 | U89: =HYPERLINK("http://www.holcim.com/","www.holcim.com") -> www.holcim.com | V89: David Romero García | W89: 122201499127 | X89: Soltero | Y89: Salvadoreño | Z89: Ingeniero Químico | AA89: Cartago, 3.5 km al sur de la esquina SE de los Tribunales de Justicia, Agua Caliente de Cartago | AC89: Apoderado generalísimo sin límite de suma | AD89: Cartago, Agua Caliente. | AE89: Cartago, Agua Caliente. | AF89: Cartago, Agua Caliente. | AG89: Cartago, Agua Caliente. | AH89: 2205-2700 | AI89: francesco.rossi@holcim.com;recepcionfe-cr@lafargeholcim.com | AJ89: L-V de 7:00 a.m a 4:30 p.m | AK89: Holcim Costa Rica | AL89: Retiro voluntario mediante acuerdo CA-017-2023-08 Las facturas deben venir a nombre de la empresa y no una persona física. 28.01.2014 Suspensión voluntaria total del alcance por un periodo de 6 messes, del 14.01.2014 al 28.06.2014
A90: Central de Ingenios S.A. | C90: LE | D90: R | E90: Privado | F90: LE-115 | G90: LE-103 | I90: ='17025 SAL'!$H90+$AN$1 -> 1460 | J90: 41408 | L90: Fabiola Alvarez | M90: falvarez@cisahn.com | O90: (504) 2509-7700 | P90: (504) 2559-1964 | Q90: Honduras | R90: Honduras, Boulevard del Este , 200 m de la entrada desvío Colonia Rivera Hernández, San Pedro Sula, Cortés. | S90: San Pedro Sula | T90: 5019995104574 | U90: =HYPERLINK("http://www.cisahn.com;/","www.cisahn.com; ") -> www.cisahn.com; | V90: Claudio Ferrera | W90: 0501-1948-00856 | X90: Casado | Y90: Hondurena | Z90: Lic. Admon de Empresas | AA90: Honduras, Boulevard del Este , 200 de la entrada desvío Colonia Rivera Hernández, San Pedro Sula. | AC90: Director Ejecutivo | AD90: Rafael Calix | AE90: Rafael Calix | AF90: (504) 2550-0110 | AG90: Honduras, Boulevard del Este , 200 de la entrada desvío Colonia Rivera Hernández, San Pedro Sula. | AH90: (504) 2550-1964 | AI90: =HYPERLINK("mailto:rcalix@cisahn.com;","rcalix@cisahn.com;") -> rcalix@cisahn.com; | AJ90: 8.00 a 5.00 pm | AK90: Central de Ingenios S.A. | AL90: CA-005-2023-06 Aceptar la solicitud de retiro voluntario de la acreditación del laboratorio de ensayos, Central de Ingenios S.A., cédula jurídica 5019995104574, con expediente LE-115. De acuerdo con el punto 2 del ECA-MC-P34, el OEC debe cumplir los siguientes lineamientos: − Cesar inmediatamente el uso del símbolo de acreditación, en todo documento o publicidad que contenga cualquier referencia a su condición de acreditado. − Comunicar a todos sus clientes sobre el retiro de la acreditación. − Informar en un plazo de 10 días hábiles a partir de la notificación del acuerdo, al correo gc@eca.or.cr, la evidencia del cumplimiento del plan de acciones requerido para el proceso de retiro de acreditación, donde se incluya al menos lo siguiente: Cómo el OEC realizará el cese inmediato el uso del símbolo de acreditación, en todo documento o publicidad que contenga cualquier referencia a su condición de acreditado. La comunicación a todos sus clientes sobre el retiro de la acreditación. Las modificaciones o afectaciones en el sistema del sistema de gestión; otras actividades que se consideren necesarias; los tiempos de implementación de estas actividades.
A91: Laboratorio de Microbiología de Aguas UCR | B91: Universidad de Costa Rica | C91: LE | D91: A | E91: Académico | F91: LE-117 | G91: LE-102 | H91: 45147 | I91: ='17025 SAL'!$H91+$AN$1 -> 46607 | J91: 41387 | L91: María Laura Arias EchandI | M91: maria.ariasechandi@ucr.ac.cr | N91: caro1798@gmail.com | O91: 2511 -8643 | P91: 2511 -4270 | Q91: Costa Rica | R91: San José, Segundo piso de la Facultad de Microbiología, Universidad de Costa Rica, San Pedro de Montes de Oca. | S91: San José | T91: 4-000-042149 | U91: =HYPERLINK("http://www.ucr.ac.cr/","www.ucr.ac.cr") -> www.ucr.ac.cr | V91: Carlos Araya Leandro | W91: 3-0305-0948 | X91: Casado | Y91: Costarricense | Z91: Doctor en Biología con especialidad en Genética | AA91: San José, Sede Univesitaria Rodrigo Facio, Edificio Administrativo B, Segundo Piso, Oficina de Rectoría, San Pedro de Montes de Oca. | AC91: Rector Universidad de Costa Rica | AD91: Fundevi | AE91: Fundevi | AF91: 2511 1777 | AG91: San José, 100 este y 200 norte de la Fuente de la Hispanidad, San Pedro de Montes de Oca | AH91: 2225 3876 | AI91: fundevi.ucr.ac.cr; | AJ91: 7:30 am a 4:00 pm | AK91: UCR
A92: Laboratorio Químico de Aceites y Combustibles, Negocio de Generación, ICE | B92: Instituto Costarricense de Electricidad | C92: LE | D92: R | E92: Público | F92: LE-118 | G92: LE-104 | I92: ='17025 SAL'!$H92+$AN$1 -> 1460 | J92: 41478 | L92: Javier Robles Cordero | M92: JRoblesCo@ice.go.cr | O92: 2501-1081 | P92: 2220-6665 | Q92: Costa Rica | R92: San José, Instituto Costarricense de Electricidad, Plantel de Colima de Tibás, puesto 2, Colima de Tibás | S92: San José | T92: 4-000-042139 | U92: =HYPERLINK("http://www.grupoice.com;/","www.grupoice.com;") -> www.grupoice.com; | V92: Alberto Ramírez Quíros | W92: 3-0201-0779 | X92: casado | Y92: Costarricense | Z92: Ing. En Mantenimiento Industrial | AA92: San José, Edificio Central del ICE UEN-PE Piso 8, Mata redonda, Sabana Norte. | AC92: Jefatura inmediata de la RAD | AD92: Alejandro Calderón Segura | AE92: Apoyo administrativo CSTRC | AF92: 2520-8812 | AG92: San José, Instituto Costarricense de Electricidad, Plantel de Colima de Tibás, puesto 2, Colima de Tibás | AH92: 2240-6107 | AI92: =HYPERLINK("mailto:LcalderonS@ice.go.cr","LcalderonS@ice.go.cr") -> LcalderonS@ice.go.cr | AJ92: lunes a jueves 7:00 a 17:00 y viernes de 7:00 a 15:00 | AK92: ICE | AL92: N/A
A93: Laboratorio de Aseguramiento de Calidad de Planta Cristal, Florida Bebidas, División Refrescos y Lácteos | C93: LE | D93: R | E93: Privado | F93: LE-119 | G93: LE-107 | I93: ='17025 SAL'!$H93+$AN$1 -> 1460 | J93: 41604 | L93: Vanessa López Mesén | M93: =HYPERLINK("mailto:vanessa.lopez@fifco.com","vanessa.lopez@fifco.com") -> vanessa.lopez@fifco.com | O93: 2437-6309 | P93: 2437-6402 | Q93: Costa Rica | R93: Heredia, Planta Cristal | S93: Heredia | T93: 3-101-306901 | U93: =HYPERLINK("http://www.florida.co.cr/;","http://www.florida.co.cr/;") -> http://www.florida.co.cr/; | V93: Ramón De Mendiola Sánchez | W93: 1-679-993 | X93: Casado | Y93: Costarricense | Z93: Empresario | AA93: Heredia, Edificio Corporativo | AC93: Director General | AD93: Productora La Florida S.A | AE93: Rebeca Acuña Acuña | AF93: 2437-6300 | AG93: Heredia, Edificio Corporativo | AH93: 2437-6402 | AI93: =HYPERLINK("mailto:rebeca.acuna@fifco.com","rebeca.acuna@fifco.com") -> rebeca.acuna@fifco.com | AJ93: 8 a 5 | AK93: Florida Bebidas, División Refrescos y Lácteos | AL93: 26.08.2014 Retiro de acreditación
A94: Laboratorio de Calibración de Planta Cristal, Florida Bebidas, División Refrescos | C94: LC | D94: R | E94: Privado | F94: LC-120 | G94: LC-108 | I94: ='17025 SAL'!$H94+$AN$1 -> 1460 | J94: 41604 | L94: Roberto Cubero López | M94: =HYPERLINK("mailto:roberto.cubero@fifco.com","roberto.cubero@fifco.com") -> roberto.cubero@fifco.com | O94: 2437-6317 | P94: 2437-6402 | Q94: Costa Rica | R94: Heredia, Planta Cristal | S94: Heredia | T94: 3-101-306901 | U94: =HYPERLINK("http://www.florida.co.cr/;","http://www.florida.co.cr/;") -> http://www.florida.co.cr/; | V94: Ramón De Mendiola Sánchez | W94: 1-679-993 | X94: Casado | Y94: Costarricense | Z94: Empresario | AA94: Heredia, Edificio Corporativo | AC94: Director General | AD94: Productora La Florida S.A | AE94: Rebeca Acuña Acuña | AF94: 2437-6300 | AG94: Heredia, Edificio Corporativo | AH94: 2437-6402 | AI94: =HYPERLINK("mailto:rebeca.acuna@fifco.com","rebeca.acuna@fifco.com") -> rebeca.acuna@fifco.com | AJ94: 8 a 5 | AK94: Florida | AL94: 26.08.2014 Retiro de acreditación
A95: Laboratorio de Ingeniería de Materiales y Pavimentos S.A. LIMPSA | C95: LE | D95: A | E95: Privado | F95: LE-121 | G95: LE-105 | H95: 45462 | I95: ='17025 SAL'!$H95+$AN$1 -> 46922 | J95: 41506 | K95: LE-105-A01: 10 de Febrero de 2015 LE-105-A02: 08 de Diciembre del 2016 LE-105-A03: 15 de Diciembre del 2016 LE-105-A04: 16 de Marzo del 2017 LE-105-A05: 16 de Enero del 2018 LE-105-A06: 5 agosto 2020 LE-105-A07 28 marzo 2023 | L95: Adriana Mahecha Chicué | M95: gerenciageneral@limpsacr.com | N95: gestorcalidad@limpsacr.com | O95: 2772-6463 | P95: 2772-6463 | Q95: Costa Rica | R95: San José, 800 m noreste de la Escuela Los Chiles, carretera a General Viejo, Daniel Flores, Pérez Zeledón. | S95: San José | T95: 3-101-636961 | U95: NA | V95: Adriana Mahecha Chicué | W95: 117000110916 | X95: Soltera | Y95: Colombiana | Z95: Lic. Administración | AA95: San José, 800 noreste de la Escuela Los Chiles, carretera a General Viejo, Daniel Flores, Pérez Zeledón. | AC95: Gerente General | AD95: Ivannia Arias López | AE95: LABOTARORIO DE INGENIERIA DE MATERIALES Y PAVIMENTOS S.A. | AF95: 27726463 | AG95: San José, 800 noreste de la Escuela Los Chiles, carretera a General Viejo, Daniel Flores, Pérez Zeledón. | AH95: 27726463 | AI95: facturaselectronicas@limpsacr.com | AJ95: 7:00 A.M. - 5:00 P.M. LUNES A VIERNES | AK95: Laboratorio de Ingeniería de Materiales y Pavimentos S.A. | AL95: A07 28/2/23 A06 5/8/20
A96: Area de Inspección y Verificación de la Calidad, de la Dirección de Calidad e Inocuidad del Consejo Nacional de Producción | C96: LE | D96: R | E96: Público | F96: LE-122 | G96: LE-109 | I96: ='17025 SAL'!$H96+$AN$1 -> 1460 | J96: 41618 | L96: David Adolfo Araya Amador | M96: hroddriguez@cnp.go.cr | N96: hroddriguez@cnp.go.cr | O96: 2265-3337 | Q96: Costa Rica | R96: Heredia, Planta la China, San Joaquín de Flores. | S96: Heredia | T96: 4-000-042146 | U96: =HYPERLINK("http://web.cnp.go.cr;/","http://web.cnp.go.cr;") -> http://web.cnp.go.cr; | V96: Edgar Isaac Vargas González | W96: 900650431 | AC96: Gerente General | AD96: Hansel Rodríguez Jiménez, | AE96: Consejo Nacional de Produccion | AF96: 2265-3338 | AG96: San José, del almacén Yamuni en Sabana este, 100 al sur, Avenida 10, calle 36. | AH96: 2257-9355 | AI96: hrodriguez@cnp.go.cr; hanselrodriguezj@gmail.com | AJ96: Lunea a Viernes de 7:30am a 3:45pm | AK96: Consejo Nacional de la Producción (CNP)
A97: INDOCAL | B97: Instituto Dominicano para la Calidad (INDOCAL) | C97: LC | D97: A | E97: Privado | F97: LC-123 | G97: LC-113 | H97: 45545 | I97: 47006 | J97: 41737 | K97: A02: 16/12/2024 | L97: Carlos Acosta | M97: INDOCAL@indocal.gob.do | N97: cacosta@indocal.gob.do | O97: (809) 686-2205 | P97: NA | Q97: República Dominicana | R97: República Dominicana, Santo Domingo, Distrito Nacional, Gazcue, Paseo Presidente Vicini Burgos #60. | S97: Santo Domingo | T97: 430-128-317 | U97: www.indocal.gob.do | V97: Lorenzo David Ramírez Uribe | W97: 001-1289215-3 | X97: Casado | Y97: Dominicano | Z97: Ingeniero Industrial | AA97: República Dominicana, Santo Domingo de Guzman, Distrito Nacional, Sector San Gerónimo. | AB97: INDOCAL@indocal.gob.do cacosta@indocal.gob.do | AC97: Director General del INDOCAL | AD97: Sección de facturación y cobros | AE97: INDOCAL | AF97: (809) 686-2205 ext. 311 y 292 | AG97: República Dominicana, Santo Domingo, Distrito Nacional, San Gerónimo, C/Olof Palme, Esq. Nunez de Caceres. | AH97: NA | AI97: ccolon@indocal.gob.do | AJ97: de 8:00 am - 4:00 pm de lunes a viernes (hora dominicana) | AK97: INDOCAL
A98: WATERLAB | C98: LE | D98: R | E98: Privado | F98: LE-124 | G98: LE-106 | I98: ='17025 SAL'!$H98+$AN$1 -> 1460 | J98: 41527 | L98: Bartholomeus Cornelus Marcus Van Stekelenburg | M98: =HYPERLINK("mailto:info@waterlab.com","info@waterlab.com") -> info@waterlab.com | O98: 2282-0780 | P98: 2282-1309 | Q98: Costa Rica | R98: San José, 200 m este de Plaza Obelisco, calle Juturna, Santa Ana. | S98: San José | T98: 3-101-636420 | U98: =HYPERLINK("http://www.juturnawater.com/","www.juturnawater.com ") -> www.juturnawater.com | V98: Bartholomeus Cornelus Marcus Van Stekelenburg | W98: 46415513 | X98: Soltero | Y98: Estadounidense | Z98: Empresario | AA98: San José, 200 este de Plaza Obelisco, calle Juturna, Santa Ana. | AC98: Representante legal | AD98: Ericka Martínez Esquivel | AE98: WATERLAB | AF98: 22820780 | AG98: San José, 200 este de Plaza Obelisco, calle Juturna, Santa Ana. | AH98: 2282-1309 | AI98: =HYPERLINK("mailto:emartinez@waterlab.com","emartinez@waterlab.com") -> emartinez@waterlab.com | AJ98: L-V: 8:00 a.m. - 5:00 p.m. | AK98: WATERLAB | AL98: Retiro voluntario de acreditación 10.10.2017
A99: Laboratorio de Microbiología de Empacadora de Productos Acuáticos San Lorenzo S.A. de C.V. | B99: Laboratorio de Microbiología de Empacadora de Productos Acuáticos San Lorenzo SA de CV | C99: LE | D99: A | E99: Privado | F99: LE-125 | G99: LE-114 | H99: 44120 | I99: ='17025 SAL'!$H99+$AN$1 -> 45580 | J99: 41772 | K99: A01:20/01/2025 | L99: Alejandra Morales | M99: amorales@granjasmarinas.com | N99: laboratorio_esl@granjasmarinas.com | O99: (504) 3352 3846 (504) 2781-2028 Ext 328/344 | P99: No aplica | Q99: Honduras | R99: Honduras, Barrio Puerto Viejo frente a Plaza Marina, San Lorenzo. | S99: Valle | T99: ´06029995442848 | U99: NA | V99: Juan Carlos Javier Medina | W99: 801197012626 | X99: Casado | Y99: Hondureño | Z99: Ingeniero Industrial | AA99: Honduras, Choluteca, El Cortijo, calle principal, Contiguo a perruquería | AB99: jjavier@granjasmarinas.com | AC99: Gerente General | AD99: Departamento de compras | AE99: Yesica Hernández | AF99: (504) 9864 6438 | AG99: Honduras, Oficinas corporativas, Grupo Granjas Marinas, Barrio El Cortijo, calle El Aterrizaje Choluteca, Choluteca. | AH99: N/A | AI99: yhernandez@granjasmarinas.com | AJ99: 8:00 am - 5:00 pm | AK99: Empacadora de Productos Acuáticos San Lorenzo S.A. de C.V.
A100: TecnoControl Laboratorio S.A. | C100: LE | D100: R | E100: Privado | F100: LE-126 | G100: LE-110 | H100: 44040 | I100: ='17025 SAL'!$H100+$AN$1 -> 45500 | J100: 41618 | L100: Roger Esquivel / Emilia Esquivel | M100: roesqui@tecnocontrolcr.net | N100: e.esquivel@tecnocontrolcr.net | O100: 2440-3419 / 8467-3000 | Q100: Costa Rica | R100: Alajuela, Oficentro Terrum, edificio #27, Río Segundo de Alajuela. | S100: Alajuela | T100: 3-101-585172 | U100: =HYPERLINK("http://www.tecnocontrolcr.net;/","www.tecnocontrolcr.net;") -> www.tecnocontrolcr.net; | V100: Roger Esquivel Benavides | W100: 4-0102-0144 | X100: Casado | Y100: Costarricense | Z100: Ingeniero Civil | AA100: Alajuela, Oficentro Terrum, edificio #27, Río Segundo de Alajuela. | AC100: Gerente General (Propietario) | AD100: Lic. Yorleny Carvajal | AE100: Tecnocontrol Laboratorio S.A. | AF100: 2440-2978 | AG100: Alajuela, Centro de Negocios Terrum, oficina #27. | AH100: 2440-3419 | AI100: =HYPERLINK("mailto:info@tecnocontrolcr.net","info@tecnocontrolcr.net") -> info@tecnocontrolcr.net | AJ100: L-V 7am/5pm | AK100: TecnoControl Laboratorio S.A. | AL100: Suspensión a partir del 2022.05.25 hasta que se verifique que se encuentra al día con sus obligaciones en la CCSS
...

Sheet 17020 SAI
B1: Norma de Referencia: INTE ISO/IEC 17020:2012 Evaluación de la conformidad. Requisitos para el funcionamiento de diferentes tipos de organismos que realizan la inspección.
A2: Nombre del OEC | B2: Nombre Razón social | C2: Tipo OEC | D2: Estatus | E2: Sector | F2: # Expediente | G2: # Acreditación | H2: Fecha firma de contrato | I2: Renovación de contrato | J2: Fecha de Otorgamiento | K2: Resumen fecha ampliaciones | L2: Nombre Representante ante ECA | M2: Email para notificaciones (oficial) | N2: Email alternativos (copias de comunicación) | O2: Teléfono | P2: Fax | Q2: País | R2: Dirección | S2: Provincia | T2: Cédula Jurídica | U2: Sitio Web | V2: NombreRepresentante Legal | W2: # Identificación | X2: Estado Civil | Y2: Nacionalidad | Z2: Profesión | AA2: Dirección para recibir notificaciones | AB2: Correo electrónico | AC2: Cargo dentro del OEC: | AD2: Contacto Dpto. de Facturación/ Cobro | AE2: Nombre | AF2: Teléfono2 | AG2: Dirección3 | AH2: Fax4 | AI2: Email | AJ2: Horario de atención | AK2: Empresa | AL2: Observaciones
A3: Saybolt de Costa Rica S.A. | C3: OI | D3: R | E3: Privado | G3: OI-001 | I3: ='17020 SAI'!$H3+'17025 SAL'!$AN$1 -> 1460 | J3: 38054 | K3: N.A | M3: saybolt.cr.ops@corelab.com; eduardo.aguero@corelab.com | O3: 2290-4439 / 8880-7395 | P3: 2290-4680 | Q3: Costa Rica | R3: 50m Sur UCIMED, Sabana Oeste. San José (contiguo al Restaurante Órale) | AK3: Saybolt de Costa Rica S.A.
A4: Saybolt de Costa Rica S.A. | C4: OI | D4: N-P | E4: Privado | F4: OI-002 | I4: ='17020 SAI'!$H4+'17025 SAL'!$AN$1 -> 1460 | K4: N.A | L4: Eduardo Agüero | M4: eduardo.aguero@corelab.com; saybolt.cr.ops@corelab.com | O4: 2290-4439 / 8880-7395 | P4: 2290-4680 | Q4: Costa Rica | R4: 50m Sur UCIMED, Sabana Oeste. San José (contiguo al Restaurante Órale) | AK4: Saybolt de Costa Rica S.A.
A5: Intertek Testing Services Costa Rica, S.A | C5: OI | D5: R | E5: Privado | F5: OI-004 | G5: OI-002 | I5: ='17020 SAI'!$H5+'17025 SAL'!$AN$1 -> 1460 | J5: 38551 | K5: N.A | L5: Alexis Ayala Jurado | M5: alexis.ayala@intertek.com | O5: (507) 2329100 | P5: (507) 22325002 | Q5: Costa Rica | R5: Zona Procesadora de Exportacion Albrrok, Edificio No 6 | T5: 3-101-255234 | U5: www.intertek.com | V5: Alexis Ayala Jurado | W5: Pasaporte No 1768706 | X5: Casado | Y5: Panameño | Z5: Quimico | AA5: De la Estacion de Bomberos Barrio Lujan 100 Oeste, 15 Sur Edificio Jimenez Barletta, 3er Piso | AC5: Gerente General | AD5: Yamilette Camacho Cantillo | AE5: Intertek Testing Services Costa Rica S.A. | AF5: (506) 22564663 | AG5: De la Estacion de Bomberos Barrio Lujan 100 Oeste, 15 Sur Edificio Jimenez Barletta, 3er Piso | AH5: (506) 22564663 | AI5: yamilette.camacho@intertek.com | AJ5: Lunea a Viernes de 8:00 a 5:00 | AK5: Intertek Testing Services Costa Rica, S.A | AL5: Retiro de acreditación a partir del 08.04.2014, suspensión voluntaria total del alcance por 6 meses del 26.11.2013 al 13.08.2014
A6: AMSPEC Costa Rica S. A | B6: AMSPEC Costa Rica S. A | C6: OI | D6: A | E6: Privado | F6: OI-006 | G6: OI-004 | H6: 43991 | I6: ='17020 SAI'!$H6+'17025 SAL'!$AN$1 -> 45451 | J6: 39125 | K6: OI-004-A01 | L6: Patricia Montenegro Ortega | M6: patricia.montenegro@amspecgroup.com | N6: enrique.wong@amspecgroup.com | O6: 2225-2609 | P6: NA | Q6: Costa Rica | R6: San José, Avenida 10 y 12, calle 37, Urbanización Los Yoses, San Pedro de Montes de Oca, de la tercera entrada de los Yoses trescientos metros al sur, cien metros al Oeste y cincuenta metros al Norte./Limón, 200 metros norte del Hotel Cocori, Playa Bonita. | S6: San José | T6: 3-101-378451 | U6: www.amspecgroup.com | V6: Enrique Wong Ching | W6: 1-953-987 | X6: Casado | Y6: Costarricense | Z6: Ing. Industrial | AA6: San José, Avenida 10 y 12, calle 37, Urbanización Los Yoses, San Pedro de Montes de Oca, de la tercera entrada de los Yoses trescientos metros al sur, cien metros al Oeste y cincuenta metros al Norte./Limón, 200 metros norte del Hotel Cocori, Playa Bonita. | AB6: enrique.wong@amspecgroup.com | AC6: Gerente General | AD6: Alice Cerdas | AE6: OIL TEST INTERNATIONAL (OTI COSTA RICA) S.A. | AF6: 22252609 | AG6: San José, Avenida 10 y 12, calle 37, Urbanización Los Yoses, San Pedro de Montes de Oca, de la tercera entrada de los Yoses trescientos metros al sur, cien metros al Oeste y cincuenta metros al Norte./Limón, 200 metros norte del Hotel Cocori, Playa Bonita. | AH6: NA | AI6: alice.cerdas@amspecgroup.com | AJ6: 8:00am - 5:00pm | AK6: AmSpec Group | AL6: OTI Costa Rica ha sido adquirido por AmSpec Group La transición de OTI a AmSpec se realizará en varias fases por lo que su primera fase es el cambio de correos electrónicos los cuales tendrán terminación @amspecgroup.com , y de forma paulatina el resto de los cambios se irán realizando, sin afectar ningún servicio ni comunicación con todos nuestros clientes.
A7: Organismo de Inspección Compañía Asesora de Construcción e Ingeniería, CACISA | B7: Compañía Asesora de Construcción e Ingeniería CACISA S.A | C7: OI | D7: A | E7: Privado | F7: OI-007 | G7: OI-005 | H7: 45099 | I7: ='17020 SAI'!$H7+'17025 SAL'!$AN$1 -> 46559 | J7: 39791 | K7: A01, A02, A04: 23/07/2024 | L7: Ing. Elda Patricia Daniels Chang | M7: pdaniels@cacisa.cr | O7: 2244-0548 | P7: 2244-1385 | Q7: Costa Rica | R7: Heredia, de la iglesia de Santa Rosa, 200 metros oeste y 750 metros norte, Santo Domingo. | S7: Heredia | T7: 3-101-036290 | U7: www.cacisa.cr | V7: Rodolfo De León rdeleon@cacisa.cr | W7: 900460935 | X7: Casado | Y7: Costarricense | Z7: Ingeniero Civil | AA7: Heredia, de la iglesia de Santa Rosa, 200 oeste y 750 norte, Sto. Domingo. | AC7: Director General | AD7: psalas@cacisa.cr | AE7: Paula Salas cuentas por pagar | AF7: 2244-0548 | AG7: Heredia, de la iglesia de Santa Rosa, 200 oeste y 750 norte, Santo Domingo. | AH7: 2244-1385 | AI7: psalas@cacisa.cr | AJ7: L-V de 7:30 a.m. a 5:30 p.m. | AK7: CACISA | AL7: Reducción del alcance el 10.12.2013 para las inspecciones de Movimientos de Tierra en un Proyecto de Supervisión específicamente las siguientes actividades: E5. Excavación con explosivos, E8. Conformación del Subrasante, E10. Conformación de caminos existentes, II-5.4-19 Barreras de hormigón y guardacaminos, II-5.4-21 Señales verticales de tránsito y postes de kilometraje.
A8: Riteve SyC, S.A | B8: Riteve SyC, S.A | C8: OI | D8: R | E8: Privado | F8: OI-009 | G8: OI-006 | H8: 44151 | I8: ='17020 SAI'!$H8+'17025 SAL'!$AN$1 -> 45611 | J8: 40162 | K8: OI-009-A01 | L8: Viviana Delgado Soto | M8: vdelgado@rtv.co.cr | N8: gjimenez@rtv.co.cr | O8: 2209-2034/8840-3970 | P8: 2209-2001 | Q8: Costa Rica | R8: Heredia, 100 metros Este de Bomba Texaco, Lagunilla. | S8: Heredia | T8: 3-101-286493 | U8: =HYPERLINK("http://www.rtv.co.cr/","www.rtv.co.cr") -> www.rtv.co.cr | V8: Pualo Valverde Tristán | W8: 1-0723-0645 | X8: Casado | Y8: Costarricense | Z8: Ingeniero industrial | AA8: Heredia, 100 Este de Bomba Texaco, Lagunilla. | AC8: Gerente General | AD8: Tesorería | AE8: Wendy Rojas | AF8: 2209-2020 | AG8: Heredia, 100 Este de Bomba Texaco, Lagunilla. | AH8: 2209-2001 | AI8: =HYPERLINK("mailto:tesoreria@rtv.co.cr","tesoreria@rtv.co.cr") -> tesoreria@rtv.co.cr | AJ8: 8:00 a.m. a 5:30 p,m. | AK8: Riteve SyC, S.A | AL8: Retiro de la acreditación mediante acuerdo ECA-CA-2023-234 notificado el 16/10/23
A9: Ileana Aguilar Ingeniería y Administración S.A, IAA | B9: Ileana Aguilar Ingeniería y Administración Sociedad Anónima | C9: OI | D9: A | E9: Privado | F9: OI-010 | G9: OI-007 | H9: 45425 | I9: ='17020 SAI'!$H9+'17025 SAL'!$AN$1 -> 46885 | J9: 40162 | K9: A01: 27/09/2011 A02: 25/09/2013 A03: 27/10/2015 A04: 15/11/2017 A05: 20/12/2017 A06: 30/05/2018 A07: 07/04/2025 | L9: Ing. Luis Arturo Chavarría Blanco | M9: calidad@iaacr.com | N9: iaguilar@iaacr.com | O9: 2460-0217 | P9: NA | Q9: Costa Rica | R9: Barrio San Antonio, 250 metros Norte y 200 metros Oeste del Hogar de Ancianos, Ciudad Quesada, San Carlos. | S9: Alajuela | T9: 3-101-543051 | U9: www.iaacr.com | V9: lleana Aguilar Aguilar | W9: 1-0880-0756 | X9: Soltera | Y9: Costarricense | Z9: Ingeniera Civil | AA9: Alajuela, 300 suroeste de la plaza de deportes, Florencia de San Carlos. | AC9: Ingeniero de Proyecto, Gerente General, Responsable del Sistema de Gestión de Calidad | AD9: Tatiana Zúñiga Rojas | AE9: lleana Aguilar Aguilar | AF9: 2460-8661 | AG9: Alajuela, 400 norte de la esquina noroeste del mercado municipal de Ciudad Quesada, diagonal a Coopenae, en los altos de la Agencia de Viajes San Carlos. | AH9: 2460-8420 | AI9: tzuniga@iaacr.com | AJ9: 8:00 am a 5:00 pm de lunes a viernes | AK9: Ileana Aguilar Ingeniería y Administración S.A, IAA | AL9: Todos los correos se deben enviar con copia Jefrey López
A10: M.S.D Consultores y Constructores, S. A | B10: M.S.D Consultores y Constructores Sociedad Anónima | C10: OI | D10: A | E10: Privado | F10: OI-011 | G10: OI-008 | H10: 43893 | I10: ='17020 SAI'!$H10+'17025 SAL'!$AN$1 -> 45353 | J10: 40162 | K10: OI-008-A01 / OI-008-A02 / OI-008-A03 / OI-008-A04/ OI-008-A05 | L10: Brenda Mondragón Lagos | M10: gc@msdcyc.com; msoto@msdcyc.com | N10: msoto@msdcyc.com /msd.soto@yahoo.com | O10: 4080-6056 | P10: 21028308 | Q10: Costa Rica | R10: San José, Urbanización El Prado, Lote 14, del Archivo Nacional 200 metros este, casa de dos plantas color amarillo, frente a Ruta Nacional n° 11807 | S10: San José | T10: 3-101-549128 | U10: www.msdcyc.com | V10: Margarita Soto Durán | W10: 2-456-795 | X10: Soltera | Y10: Costarricense | Z10: Ingeniera Civil | AA10: San José, Urbanización El Prado, Lote 14, del Archivo Nacional 200 metros este, casa de dos plantas color amarillo, frente a Ruta Nacional n° 11807 | AC10: Gerente e Ingeniera de Proyecto | AE10: Brenda Mondragón Lagos | AF10: 4080-6056 | AG10: San José, Curridabat, Residencial El Prado, 200 metros este del Archivo Nacional. | AH10: 2286-5983 | AI10: contabilidad@msdcyc.com | AJ10: De 7:00 a.m. a 5:00 p.m. | AK10: M.S.D Consultores y Constructores, S. A
A11: Consultora y Ejecutora SALASA S.A | B11: Consultora y Ejecutora Salasa S.A. | C11: OI | D11: A | E11: Privado | F11: OI-012 | G11: OI-009 | H11: 45203 | I11: ='17020 SAI'!$H11+'17025 SAL'!$AN$1 -> 46663 | J11: 40211 | K11: OI-009-A01 / OI-009-A02 / OI-009-A03/ OI-009-A04/ OI-009-A05, OI-009-A06, OI-009-A07 | L11: Jorge Salazar Gonzalez | M11: Gestion.Calidad@salasa.co.cr; jsalazar@salasa.co.cr | O11: 4052-2850 | P11: 2296-1156 | Q11: Costa Rica | R11: Residencial Torres del Este Casa N° C-22, en San Juan de la Unión, Cartago (Entrando por Pasoca, y la entrada al Residencial está contiguo a la Escuela Villas de Ayarco) | S11: San José | T11: 3-101-489684 | U11: =HYPERLINK("http://www.consultorasalasa.com;/","www.consultorasalasa.com;") -> www.consultorasalasa.com; | V11: Jorge Salazar Gonzalez | W11: 2-439-943 | X11: Divorciado | Y11: Costarricense | Z11: Ingeniero Civil | AA11: San José, de la Iglesia Católica de San Diego 100 metros oeste, Edificio de tres Pisos, San Diego de Tres Ríos | AC11: Director General | AD11: Jorge Salazar Gonzalez | AE11: Consultora y Ejecutora SALASA S.A. | AF11: 4052-2850 | AG11: San José, de la Iglesia Católica de San Diego 100 metros oeste, Edificio de tres Pisos, San Diego de Tres Ríos | AH11: 2553-5286 | AI11: salasa.factura@gmail.com; con copia a: kmena@salasa.co.cr; gestión.calidad@salasa.co.cr | AJ11: 8:00 am a 5:00 pm | AK11: Consultora y Ejecutora SALASA S.A
A12: Grupo Roading Consulters S.A | C12: OI | D12: N-P | E12: Privado | F12: OI-013 | I12: ='17020 SAI'!$H12+'17025 SAL'!$AN$1 -> 1460 | J12: . | K12: N.A | L12: Licda. Lucía Chaverri Morales | M12: lchaverri@gruporoading.com; jnunez@gruporoading.com | O12: 2430-0245/8705-8265 | P12: 2430-0245 | Q12: Costa Rica | R12: Plaza Colonial, San Rafael de Escazú local 1-11b | T12: 3-101-449436 | AK12: Grupo Roading Consulters S.A
A13: Construcciones Gutiérrez COGUSA S.A | B13: Construcciones Gutiérrez COGUSA Sociedad Anónima | C13: OI | D13: A | E13: Privado | F13: OI-014 | G13: OI-010 | H13: 45190 | I13: ='17020 SAI'!$H13+'17025 SAL'!$AN$1 -> 46650 | J13: 40260 | K13: A01: 27/05/2024 A02: 28/02/2018 A03: 13/09/2022 A04: 20/10/2023 A05: 15/10/2024 A06: 14/07/2025 | L13: Victor Manuel Gutiérrez Bustos/Marjorie Acuña Vargas | M13: sistema-calidad@cogusa-cr.net | N13: Usar este para el usuario en sitio web: info@cogusa-cr.net | O13: 2551-1403 / 2551-0562 | Q13: Costa Rica | R13: Cartago Centro, 20m Sur del Museo Municipal de Cartago 200m Norte de las Ruinas de Cartago. | S13: Cartago | T13: 3-101-343608 | U13: =HYPERLINK("http://www.construccionesgutierrez.com;/","www.construccionesgutierrez.com;") -> www.construccionesgutierrez.com; | V13: Víctor Manuel Gutiérrez Bustos | W13: 1-0701-0765 | X13: Casado | Y13: Costarricense | Z13: Ingeniero Civil | AA13: Cartago Centro, 20m Sur del Museo Municipal de Cartago 200m Norte de las Ruinas de Cartago. | AC13: Gerente general | AD13: NA | AE13: Marjorie Acuña Vargas | AF13: 2795-0615/ 8718-7950 | AG13: Cartago Centro, 20m Sur del Museo Municipal de Cartago 200m Norte de las Ruinas de Cartago. | AH13: 2795-0568 | AI13: sistema-calidad@cogusacr.com; info@cogusacr.com | AJ13: De Lunes a Viernes de 8:00:am a 5:00:pm | AK13: Construcciones Gutiérrez COGUSA S.A
A14: Inversiones Rivera Segura S.A, IRSSA | B14: Inversiones Rivera Segura Sociedad Anónima | C14: OI | D14: A | E14: Privado | F14: OI-015 | G14: OI-012 | H14: 45384 | I14: ='17020 SAI'!$H14+'17025 SAL'!$AN$1 -> 46844 | J14: 40263 | K14: OI-012-A01 / OI-012-A02 / OI-012-A03 / OI-012-A04 / OI-012-A05 | L14: Yacare Montero, Carlos Rivera | M14: yacare.montero@irssa-cr.com; carlos.rivera@irssa-cr.com | N14: servicio.cliente@irssa-cr.com; | O14: 27113201 | P14: 27107491 | Q14: Costa Rica | R14: Limón, Centro Comercial Nuevo Guápiles, local No. 5, Guápiles de Pococí | S14: Limón | T14: 3-101-464758 | U14: NA | V14: Carlos Rivera Umaña | W14: 107310046 | X14: Casado | Y14: Costarricense | Z14: Ingeniero Civil | AA14: Limón, Centro Comercial Nuevo Guápiles, local No. 5, Guápiles de Pococí | AC14: Gerente | AE14: Tatiana Enríquez Martínez | AF14: 27113201 | AG14: Limón, Centro Comercial Nuevo Guápiles, local No. 5, Guápiles de Pococí | AH14: 27107491 | AI14: servicio.cliente@irssa-cr.com; tatiana.enriquez@irssa-cr.com; | AJ14: L-V de 8:00 am a 5:00 pm | AK14: Inversiones Rivera Segura S.A, IRSSA
A15: Leitón Salas Consultores y Asociados S.A | C15: OI | D15: R | E15: Privado | F15: OI-016 | G15: OI-015 | I15: ='17020 SAI'!$H15+'17025 SAL'!$AN$1 -> 1460 | J15: 40297 | K15: N.A | L15: IGNACIO LEITON SALAS | M15: brenargentina@hotmail.com; leitonignacio@gmail.com; bmondragon@ilsconsultores.com | O15: 8313-8719/6051-5061 | P15: 2214-6250 | Q15: Costa Rica | R15: Piedades de Santa Ana, Residencial La Caraña, casa NO. 3 | T15: 3-101-523499 | U15: www.ilsconsultores.com | V15: IGNACIO LEITON SALAS | W15: 1-739-523 | X15: CASADO | Y15: COSTARRICENSE | Z15: LIC. EN ING. CIVIL | AA15: Piedades de Santa Ana, Residencial La Caraña, casa NO. 3 | AC15: GERENTE GENERAL | AD15: IGNACIO LEITON SALAS | AE15: LEITON SALAS CONSULTORES Y ASOCIADOS S.A. | AF15: 8313-8719/6051-5061 | AG15: Piedades de Santa Ana, Residencial La Caraña, casa NO. 3 | AH15: 2214-6250 | AI15: brenargentina@hotmail.com; leitonignacio@gmail.com; bmondragon@ilsconsultores.com | AJ15: De L a V de 8:00 a.m. a 12:00 m.d. y de 1:00 a 5:00 p.m. | AK15: Leitón Salas Consultores y Asociados S.A | AL15: Retiro de acreditación a partir del 08.04.2014. Con suspensión voluntaria. / Prorroga de suspensión voluntaria del 29.09.2013 al 27.12.2013
A16: Grupo Dedal, S.A. | B16: Grupo Dedal, Sociedad Anónima | C16: OI | D16: A | E16: Privado | F16: OI-017 | G16: OI-013 | H16: 45258 | I16: ='17020 SAI'!$H16+'17025 SAL'!$AN$1 -> 46718 | J16: 40281 | K16: OI-013-A01 / OI-013-A02 / OI-013-A03 / OI-013-A04 / OI-013-A05 | L16: Ing. Daniel Solís Carmona Cala Roversie Carmona | M16: grupodedal@gmail.com | N16: grupodedal@gmail.com ; kala16.rover@gmail.com; kala0616@hotmail.com | O16: 2241-0390 | Q16: Costa Rica | R16: Princesa Marina en Moravia 100 Sur, Apartamentos Las Torres #2 . | S16: San José | T16: 3-101-556575 | U16: NA | V16: Daniel Solís Carmona | W16: 1-0753-0114 | X16: Casado | Y16: Costarricense | Z16: Ing. Civil | AA16: San José, del Rest. La Princesa Marina 100 S 100 O y 100 S casa #55, Moravia. | AC16: Gerente | AD16: Alejandra Roversie Carmona | AE16: Grupo Dedal, S.A. | AF16: 2240-0390 | AG16: San José, del Rest. La Princesa Marina 100 S 100 O y 100 S casa #55, Moravia. | AH16: 2240-0390 | AI16: kala0616@hotmail.com; grupodedal@gmail.com; | AJ16: de L a V de 8:00 am a 5 pm. | AK16: Grupo Dedal, S.A. | AL16: 20.08.2013 Cambio de Tipo de A a C, De 12 md a 1:30 pm cerrado por almuerzo El OEC indica que el correo para notificaciones es kala0616@hotmail.com, mientras que el usuario al sitio web el OEC solicitó que se utilice el grupodedal@gmail.com
A17: Consultoría y Construcción en obras civiles Moreira S.A; CCOCIMO S.A. | B17: CCOCIMO Sociedad Anónima | C17: OI | D17: A | E17: Privado | F17: OI-018 | G17: OI-014 | H17: 43979 | I17: ='17020 SAI'!$H17+'17025 SAL'!$AN$1 -> 45439 | J17: 40281 | K17: OI-014-A01 / OI-014-A02 | L17: Lesmes Miranda Alvarado | M17: lmiranda@ccocimo.com | O17: 2487-8724 | P17: 2441-9386 | Q17: Costa Rica | R17: Alajuela, 225 metros este de la Fiesta del Maíz, La Garita | S17: Alajuela | T17: 3-101-551701 | U17: NA | V17: Greivin Moreira Palma | W17: 2 – 467 - 953 | X17: Soltero | Y17: Costarricense | Z17: Ingeniero Civil | AA17: Alajuela, 225 m este de la Fiesta del Maíz, La Garita | AC17: Gerente General / Ing de Proyecto Titular | AD17: Marcella Alvarado Calderón | AE17: CCOCIMO S.A | AF17: 2487-8724 | AG17: Alajuela, 225 m este de la Fiesta del Maíz, La Garita | AH17: 2487-8724 | AI17: facturas@ccocimo.com /malvarado@ccocimo.com | AJ17: 8:00am / 5:00pm | AK17: Consultoría y Construcción en obras civiles Moreira S.A; CCOCIMO S.A. | AL17: 22.04.2014, cambio de tipo de "A" a "C"
A18: M.C.S Mauca Interamericana S.A. | B18: M.C.S Mauca Interamericana Sociedad Anónima | C18: OI | D18: A | E18: Privado | F18: OI-019 | G18: OI-017 | H18: 45876 | I18: No aplica | J18: 40297 | K18: OI-017-A01 / OI-017-A02 / OI-017-A03 | L18: Mauricio Calvo Salazar/Alejandra Vargas | M18: maucalvo_cr@yahoo.com; maucalvo@maucacr.com; calidadmauca@gmail.com | O18: 2665-3419 | P18: 2666-9360 | Q18: Costa Rica | R18: Guanacaste, 100 metros sur del Scotiabank, Urbanización Malinche, Liberia | S18: Guanacaste | T18: 3-101-556987 | U18: =HYPERLINK("http://www.maucacr.com;/","www.maucacr.com;") -> www.maucacr.com; | V18: Mauricio Calvo Salazar | W18: 1-884-254 | X18: Casado | Y18: Costarricense | Z18: Ingeniero Civil | AA18: Guanacaste, 100 sur del Scotiabank, Urbanización Malinche, Liberia | AC18: Gerencia Técnica | AD18: Mauricio Calvo Salazar | AE18: M.C.S. Mauca Interamericana S. A. | AF18: 2665-3419 | AG18: Guanacaste, 100 sur del Scotiabank, Urbanización Malinche, Liberia | AH18: 2666-9360 | AI18: maucalvo_cr@yahoo.com; maucalvo@mauca cr.com; | AJ18: 8 a.m. a 5 p.m. | AK18: M.C.S Mauca Interamericana S.A.
A19: Poligonal S.A. | B19: Poligonal Sociedad Anónima | C19: OI | D19: A | E19: Privado | F19: OI-020 | G19: OI-018 | H19: 45869 | I19: No aplica | J19: 40297 | K19: OI-018-A01 / OI-018-A02 / OI-018-A03 | L19: Carlo Molina Rivera/Alejandra Vargas | M19: carlomolinarivera@gmail.com; poligonalsa@gmail.com | O19: 8385-6550 | P19: NA | Q19: Costa Rica | R19: Guanacaste, Nicoya, Barrio la Virginia, 25 mts oeste de la empresa de buses Traroc. | S19: Guanacaste | T19: 3-101-187188 | U19: NA | V19: Carlo Molina Rivera | W19: 1-747-290 | X19: Divorciado | Y19: Costarricense | Z19: Ingeniero Civil | AA19: Guanacaste, Nicoya, Barrio la Virginia, 25 mts oeste de la empresa de buses Traroc. | AC19: Apoderado Generalísimo | AD19: Carlo Molina Rivera | AE19: POLIGONAL S.A. | AF19: 8385-6550 | AG19: Guanacaste, 100 sur del Scotiabank, Urbanización Malinche, Liberia | AH19: 2666-9360 | AI19: cmolinae@racsa.co.cr | AJ19: Lunes - Viernes 8:00 a.m. a 5:00 p.m. | AK19: Poligonal S.A.
A20: Diseño, Inspección y Consultoría en Carreteras y Obras Civiles DICCOC S.R.L. | B20: Diseño, Inspección y Consultoría en Carreteras y Obras Civiles DICCOC Sociedad de Responsabilidad Limitada | C20: OI | D20: A | E20: Privado | F20: OI-021 | G20: OI-016 | H20: 45869 | I20: No aplica | J20: 40297 | K20: OI-016-A01 / OI-016-A02 / OI-016-A03 / OI-016-A04 / OI-016-A05 | L20: Alister Cervantes Morales | M20: alistercm@diccoc.com, gestiondecalidad@diccoc.com | O20: 2261-7570 | P20: 2261-8443 | Q20: Costa Rica | R20: Heredia, de la esquina noreste de la Iglesia Católica, 400 metros al este, casa de dos plantas, color gris, San Rafael. | S20: Heredia | T20: 3-102-518005 | U20: www.diccoc.com | V20: Mónica Bolaños Sánchez | W20: 1-0802-0326 | X20: Casada | Y20: Costarricense | Z20: Ingeniera Civl | AA20: Heredia, de la esquina noreste de la Iglesia Católica, 400 metros al este, casa de dos plantas, color gris, San Rafael. | AC20: Gerente General | AD20: Angelly Paniagua Sánchez | AE20: Diseño, Inspección y Consultoría en Carreteras y Obras Civiles, S.R.L. | AF20: 2261-7570 | AG20: Heredia, de la esquina noreste de la Iglesia Católica, 400 metros al este, casa de dos plantas, color gris, San Rafael. | AH20: 2261-8443 | AI20: angelly.paniagua@diccoc.com | AJ20: Lunes a Viernes de 8:00 a.m. a 4:00 p.m. | AK20: Diseño, Inspección y Consultoría en Carreteras y Obras Civiles DICCOC R.L.
A21: Empresarial FAMCOVA de Costa Rica, S.A. | B21: Empresarial FAMCOVA de Costa Rica, S.A. | C21: OI | D21: A | E21: Privado | F21: OI-022 | G21: OI-019 | H21: 43979 | I21: ='17020 SAI'!$H21+'17025 SAL'!$AN$1 -> 45439 | J21: 40297 | K21: OI-019-A01 /OI-019-A02 | L21: Lesmes Miranda Alvarado | M21: lmiranda@famcova.net | N21: malvarado@famcova.net | O21: 2487-8724 | P21: 2487-8724 | Q21: Costa Rica | R21: Alajuela, 225 metros este de la Fiesta del Maíz, La Garita | S21: Alajuela | T21: 3-101-500445 | U21: www.famcova.net | V21: Luis Carlos Corrales Xatruch | W21: 2 0465 0245 | X21: Casado | Y21: Costarricense | Z21: Ingeniero Civil | AA21: Alajuela, 225 m este de la Fiesta del Maíz, La Garita | AC21: Gerencia/Ingeniero de proyecto titular | AD21: Lesmes Miranda Alvarado | AE21: Empresarial FAMCOVA de Costa Rica, S.A. | AF21: 2487-8724 | AG21: Alajuela, 225 m este de la Fiesta del Maíz, La Garita | AH21: 2487-8724 | AI21: lmiranda@famcova.net | AJ21: 8:00 a 5:00 jornada continua | AK21: Empresarial FAMCOVA de Costa Rica, S.A. | AL21: 22.04.2014, cambio de tipo de "A" a "C"
A22: Grupo Lauher, S.A. | B22: Grupo Lauher Sociedad Anónima | C22: OI | D22: A | E22: Privado | F22: OI-023 | G22: OI-020 | H22: 45194 | I22: ='17020 SAI'!$H22+'17025 SAL'!$AN$1 -> 46654 | J22: 40297 | K22: OI-020-A01 / OI-020-A02 / OI-020-A03 / OI-020-A04 | L22: Bernal Hernández Soto Maricela Arrieta | M22: bhernandez@grupolauher.com; behernandez@cfia.or.cr; | N22: marrieta@grupolauher.com | O22: 8318-5299/ 2475-6446 | P22: 2475-6590 | Q22: Costa Rica | R22: Alajuela, 30 metros suroeste de la plaza de deportes, entreda a Pénjamo casa esquinera, Florencia de San Carlos. | S22: Alajuela | T22: 3-101-535666 | U22: www.grupolauher.com | V22: Bernal Hernández Soto | W22: 2-467-192 | X22: Casado | Y22: Costarricense | Z22: Licenciado en Ingeniería civil / Maestría en Administración de proyectos | AA22: Alajuela, 30 suroeste de la plaza de deportes, entrada a Pénjamo casa esquinera, Florencia de San Carlos. | AC22: Gerente general / Ingeniero Titular | AD22: Cindy Rodríguez Cruz- crodriguez@grupolauher.com | AE22: Bernal Hernández Soto | AF22: 2475-6446 | AG22: Alajuela, 30 suroeste de la plaza de deportes, entreda a Pénjamo casa esquinera, Florencia de San Carlos. | AH22: 2475-6446 | AI22: bhernandez@grupolauher.com | AJ22: 7:30 am a 5:00pm | AK22: Grupo Lauher, S.A.
A23: INCOSESA - Inspección y Consultoría Sánchez Elizondo S.A. | B23: Inspección y Consultoría Sánchez Elizondo Sociedad Anónima | C23: OI | D23: A | E23: Privado | F23: OI-024 | G23: OI-021 | H23: 45391 | I23: ='17020 SAI'!$H23+'17025 SAL'!$AN$1 -> 46851 | J23: 40323 | K23: A01: 25/06/2019 A02: 27/01/2025 | L23: Erik Aguilar Sánchez | M23: erikaguilarsanchez@yahoo.com | N23: infoincosesacr@gmail.com | O23: 8723-8851 | P23: 2450-1528 | Q23: Costa Rica | R23: Alajuela, 150 m Sur de la iglesia Católica, contiguo al Pani, Centro de Orotina | S23: Alajuela | T23: 3-101-530157 | U23: NA | V23: Erik Aguilar Sánchez | W23: 1-712-745 | X23: Casado | Y23: Costarricense | Z23: Ingeniero Civil | AA23: Alajuela, 150 m Sur de la iglesia Católica, contiguo al Pani, Centro de Orotina | AC23: Gerente, Ingeniero Titular, RSGC, Asistente e Inspector | AD23: Erik Aguilar Sánchez | AE23: Erik Aguilar Sánchez | AF23: 2451-0809 | AG23: Alajuela, 150 m Sur de la iglesia Católica, contiguo al Pani, Centro de Orotina | AH23: 8723-881 | AI23: containcosesa@gmail.com | AJ23: Lunes a Viernes 8:00 am a 5:00 pm | AK23: Inspección y Consultoría Sánchez Elizondo S.A. | AL23: Tal y como se ha comunicado oportunamente, nuestro OEC opera sin un contrato de inspección activo
A24: Consorcio Estratega V & CH S.A. | B24: Consorcio Estratega V & CH Sociedad Anónima | C24: OI | D24: A | E24: Privado | F24: OI-025 | G24: OI-022 | H24: 45534 | I24: No aplica | J24: 40344 | K24: A01: 22/04/2014 A02: 17/08/2017 A03: 29/01/2024 A04: 5/11/2024 | L24: Adalid Villanea Calvo | M24: cevchsa@gmail.com | N24: chaconlawyer@gmail.com | O24: 2271-5314/8814-61-75/24587-8724 | P24: 2272-52-72 | Q24: Costa Rica | R24: San José, 25 m este del Banco Nacional, comercial La Rosa, local 2, Curridabat/Alajuela, 100 metros este de la casa de la fiesta del maíz, La Garita | S24: Alajuela | T24: 3-101-256151 | U24: NA | V24: ADALID VILLANEA CALVO | W24: 1-0510-0784 | X24: casado | Y24: costarricense | Z24: Ing.Civil | AA24: San José, 25 m este del Banco Nacional, comercial La Rosa, local 2, Curridabat/Alajuela, 100 m este de la casa de la fiesta del maíz, La Garita | AC24: Gerente Ing. Titular | AD24: Licda Ana M. Chacón Novoa | AE24: Licda Ana M. Chacón Novoa | AF24: 8328-06-75 | AG24: San José, 25 m este del Banco Nacional, comercial La Rosa, local 2, Curridabat/Alajuela, 100 m este de la casa de la fiesta del maíz, La Garita | AH24: 2272-52-72 | AI24: =HYPERLINK("mailto:chaconlawyer@gmail.com","chaconlawyer@gmail.com") -> chaconlawyer@gmail.com | AJ24: 8:00 am a 5 pm | AK24: Consorcio Estratega V & CH S.A. | AL24: 22.04.2014, cambio de tipo de "A" a "C"
A25: Organismo de Inspección Plataforma de Almenar S.A. | B25: Plataforma de Almenar Sociedad Anónima | C25: OI | D25: R | E25: Privado | F25: OI-026 | G25: OI-023 | H25: 43544 | I25: ='17020 SAI'!$H25+'17025 SAL'!$AN$1 -> 45004 | J25: 40344 | K25: OI-023-A01/ OI-023-A02 | L25: Juan José Mesén Espinoza | M25: plataformadealmenar@gmail.com | N25: jjmesene@hotmail.com | O25: 8346-0433/8503-2484 | P25: 4030-2000. | Q25: Costa Rica | R25: Cartago, Quebradilla, 300 m oeste de la entrada a Bermejo | S25: Cartago | T25: 3-101-540228 | U25: NA | V25: JUAN JOSE MESEN ESPINOZA | W25: 5-230-652 | X25: CASADO | Y25: COSTARRICENSE | Z25: LIC. EN ING. CIVIL | AA25: Puntarenas, de la oficina del Registro Civil 30 sur y 50 oeste, Buenos Aires. | AC25: GERENTE GENERAL | AD25: JUAN JOSE MESEN ESPINOZA | AE25: PLATAFORMA DE ALMENAR S.A. | AF25: 2772-1013/8313-88719 | AG25: Puntarenes, de la oficina del Registro Civil 30 sur y 50 oeste, Buenos Aires. | AH25: 2772-1013 | AI25: brenargentina@hotmail.com; jjmesene@hotmail.com | AJ25: De L a V de 8:00 a.m. a 12:00 m.d. y de 1:00 a 5:00 p.m. | AK25: Organismo de Inspección Plataforma de AlmenarS.A. | AL25: 13.01.2015, cambio de tipo de "A" a "C" Acuerdo CA-031-2022-05 Retiro del OEC
A26: Inversiones Bamba M.D. S.A. | C26: OI | D26: N-P | E26: Privado | F26: OI-027 | I26: ='17020 SAI'!$H26+'17025 SAL'!$AN$1 -> 1460 | K26: N.A | L26: Ing. Wasser Alberto Matarrita Díaz | M26: inversionesbamba@hotmail.com; Wassermd@hotmail.com; jpezcoco@hotmail.com; wassermd@bambamd.org | O26: 2494-1163 | P26: 2494-1163 | Q26: Costa Rica | R26: De la entrada principal de Plaza Pinos, (Pinturas Decor Protecto), 200 m Sur. Edificio esquinero color mostaza en los altos del Salón Guadalupe, Grecia, Alajuela. | T26: 3-101-296728 | AK26: Inversiones Bamba M.D. S.A.
A27: Vieto y Asociados Sociedad Anónima | B27: Vieto y Asociados Sociedad Anónima | C27: OI | D27: A | E27: Privado | F27: OI-028 | G27: OI-028 | H27: 45378 | I27: ='17020 SAI'!$H27+'17025 SAL'!$AN$1 -> 46838 | J27: 40911 | K27: OI-028-A01 / OI-028-A02 | L27: Susy Vieto de la Fuente | M27: susy.vieto@vieto.com | N27: calidad@vieto.com | O27: 2268-8297 ext: 225 | P27: 2268-9457 | Q27: Costa Rica | R27: Heredia, del rancho de Doña Lela 3.5km sobre la autopista Braulio Carrillo, después del segundo puente peatonal 400 metros norte primer entrada de lastre a mano derecha, San Luis de Santo Domingo. | S27: Heredia | T27: 3-101-029579-15 | U27: www.vieto.com | V27: Susy Vieto de la Fuente | W27: 1-0753-0214 | X27: Casada | Y27: Costarricense | Z27: Administradora de empresas | AA27: susy.vieto@vieto.com calidad@vieto.com | AC27: Gerente de Calidad | AD27: Vanessa Loaiza | AE27: Vieto & Asociados S.A. | AF27: 2268-8297 | AG27: Heredia, del rancho de Doña Lela 3.5km sobre la autopista Braulio Carrillo, después del segundo puente peatonal 400 norte primer entrada de lastre a mano derecha, San Luis de Santo Domingo. | AH27: 2268-9457 | AI27: contabilidad@vieto.com | AJ27: Lunes a viernes de 7:00am a 5:00pm Sábados 7:00am a 12:00md | AK27: Vieto y Asociados Sociedad Anónima | AL27: De lunes a viernes cerrado de 12:00md a 1:00pm
A28: Laboratorio Químico Lambda S.A. | C28: OI | D28: N-P | E28: Privado | F28: OI-029 | I28: ='17020 SAI'!$H28+'17025 SAL'!$AN$1 -> 1460 | K28: N.A | L28: Rafael Amón Pérez | M28: lambda@racsa.co.cr; lambda@racsa.co.cr | O28: 2226-4462 | P28: 2286-1168 | Q28: Costa Rica | R28: San Francisco de 2 Ríos, Barrio Los Álamos, de la Iglesia 100 m oeste, 75 m norte y 75m oeste. | T28: 3-101-07-4595-15 | AK28: Lambda
A29: DIPOA-SENASA | C29: OI | D29: N-P | E29: Privado | F29: OI-030 | I29: ='17020 SAI'!$H29+'17025 SAL'!$AN$1 -> 1460 | K29: N.A | L29: Dra. Mónica Sandi Lizano | M29: msandi@senasa.go.cr; gsuarez@senasa.go.cr | O29: 2260-8648 | P29: 2260-8648 | Q29: Costa Rica | R29: Lagunilla de Heredia, 1.5 km este de Jardines del Recuerdo y 300 m norte del Campus Universitario Benjamín Núñez | T29: 3-007475726 | AK29: MAG
A30: Organismo de Inspección CASTRO & DE LA TORRE S.A | B30: CASTRO & DE LA TORRE S.A | C30: OI | D30: A | E30: Privado | F30: OI-031 | G30: OI-025 | H30: 45203 | I30: ='17020 SAI'!$H30+'17025 SAL'!$AN$1 -> 46663 | J30: 40582 | K30: OI-025-A01 / OI-025-A02 / OI-025-A03 / OI-025-A04 / OI-025-A05 | L30: Ing. Oscar Picado Acuña | M30: opicado@cyt.cr | N30: info@cyt.cr | O30: 4010-2273 | P30: 2296-0076 | Q30: Costa Rica | R30: 500 m Oeste de la Fabrica Jack’s, Zona Industrial de Pavas, San José. | S30: San José | T30: 3-101-007884 | U30: www.cyt.cr | V30: Orlando De la Torre Castro | W30: 107400155 | X30: Casado | Y30: Costarricense | Z30: Ingeniero Industrial | AA30: San José, 500 m oeste de la Fabrica Jack’s, frente al Ministerio de Salud, Pavas. | AC30: Sub-Gerente | AD30: Alexis Mata | AE30: Castro & De la Torre S.A. | AF30: 2232-2273 | AG30: San José, 500 m oeste de la Fabrica Jack’s, frente al Ministerio de Salud, Pavas. | AH30: 2296-0076 | AI30: amata@cyt.cr | AJ30: Lunes a Viernes de 8:00 am a 5:00 pm | AK30: CASTRO & DE LA TORRE
A31: IMNSA Ingenieros Consultores S.A., Organismo de Inspección | B31: IMNSA Ingenieros Consultores Sociedad Anónima | C31: OI | D31: R | E31: Privado | F31: OI-032 | G31: OI-030 | H31: 43539 | I31: ='17020 SAI'!$H31+'17025 SAL'!$AN$1 -> 44999 | J31: 41296 | K31: N.A | L31: Brenda Mondragón Lagos | M31: calidadimnsa@gmail.com | N31: asistentecalidadimnsa@gmail.com | O31: 2234-1587 | P31: 2225-9551 | Q31: Costa Rica | R31: San José, Carretera a Sabanilla, del Supermercado "La Cosecha" 100 metros Sur, 100 metros Este y 25 metros Norte, Edificio # 505, Barrio Carmiol, Montes de Oca. | S31: San José | T31: 3-101-091498 | U31: NA | V31: Carlos A. Méndez Navas | W31: 1-268-419 | X31: Casado | Y31: Costarricense | Z31: Ingeniero Civil | AA31: San José, Carretera a Sabanilla, del Supermercado "La Cosecha" 100 Sur, 100 Este y 25 Norte, Edificio # 505, Barrio Carmiol, Montes de Oca. | AC31: Presidente | AE31: Verónica Arnuero | AF31: 2234-1587 | AG31: San José, Carretera a Sabanilla, del Supermercado "La Cosecha" 100 Sur, 100 Este y 25 Norte, Edificio # 505, Barrio Carmiol, Montes de Oca. | AH31: 2225-9551 | AI31: imnsai@racsa.co.cr | AJ31: Lunes a Viernes de 8:00 a.m. a 5:30 p.m. | AK31: IMNSA Ingenieros Consultores S.A | AL31: CA-003-2024 Retirar la acreditación de IMNSA Ingenieros Consultores Sociedad Anónima, cédula jurídica 3-101-091498, específicamente al Organismo de Inspección tipo C, IMNSA Ingenieros Consultores S.A., Organismo de Inspección, con expediente número OI-032, por no cumplir con lo indicado en el acuerdo CA-035-2023-05 y en concordancia al procedimiento ECA-MC-P34. De acuerdo con el punto 2 del ECA-MC-P34, el OEC debe cumplir los siguientes lineamientos: − Cesar inmediatamente el uso del símbolo de acreditación, en todo documento o publicidad que contenga cualquier referencia a su condición de acreditado. − Comunicar a todos sus clientes sobre el retiro de la acreditación. − Informar en un plazo de 10 días hábiles a partir de la notificación del acuerdo, al correo gc@eca.or.cr, la evidencia del cumplimiento del plan de acciones requerido para el proceso de retiro de acreditación, donde se incluya al menos lo siguiente: Cómo el OEC realizará el cese inmediato el uso del símbolo de acreditación, en todo documento o publicidad que contenga cualquier referencia a su condición de acreditado. La comunicación a todos sus clientes sobre el retiro de la acreditación. Las modificaciones o afectaciones en el sistema del sistema de gestión; otras actividades que se consideren necesarias y los tiempos de implementación de estas actividades. El presente acuerdo rige a partir del 01 de febrero del 2024.
A32: Organismo de Inspección SCM Metrología y Laboratorios S.A. | B32: SCM Metrología y Laboratorios Sociedad Anónima | C32: OI | D32: A | E32: Privado | F32: OI-033 | G32: OI-026 | H32: 45869 | I32: No aplica | J32: 40807 | K32: N.A | L32: Jose Marvin Rodríguez Vásquez | M32: carlos.alvarado@scmmetrologia.com | N32: jose.rodriguez@scmmetrologia.com | O32: (+506) 4020-1201 / (+506) 7206-1540 / (+506) 7206-1566 | P32: 4020-1203 | Q32: Costa Rica | R32: Alajuela, 2 kilometros este del Aeropuerto Internacional Juan Santamaría, Río Segundo de Alajuela | S32: Alajuela | T32: 3-101-271623 | U32: http://www.scmmetrologia.com/Newsite/ | V32: Edgar Sánchez Molina | W32: 2-0459-0214 | X32: Casado | Y32: Costarricense | Z32: Químico | AA32: vecino de San Pablo de Heredia, Residencial Doña Nina, casa 19. | AC32: Director | AD32: Laura Molina Salazar | AE32: SCM Metrología y Laboratorio S.A. | AF32: 2431-5252 ext. 102 | AG32: Alajuela, 2 km este del Aeropuerto Internacional Juan Santamaría, Río Segundo de Alajuela | AH32: 2432-4180 | AI32: laura.molina@scmmetrologia.com; mauricio.montero@scmmetrologia.com | AJ32: 7:00 am a 4:30 pm | AK32: SCM
A33: Organismo de Inspección del Centro de Electroquímica y Energía Química CELEQ | B33: Universidad de Costa Rica | C33: OI | D33: A | E33: Académico | F33: OI-034 | G33: OI-027 | H33: 45147 | I33: ='17020 SAI'!$H33+'17025 SAL'!$AN$1 -> 46607 | J33: 40876 | K33: OI-027-A01 / OI-027-A02 / OI-027-A03 / OI-027-A04 / | L33: Mariann Guillén Osorno Dr. Jean Sanabria Chinchilla | M33: calidad.celeq@ucr.ac.cr direccion.celeq@ucr.ac.cr | N33: jean.sanabria@ucr.ac.cr | O33: 2511-2487 | P33: 2511-2484 | Q33: Costa Rica | R33: San José, Ciudad de la Investigación de la UCR, San Pedro de Montes de Oca | S33: San José | T33: 4-000-042 149 | U33: =HYPERLINK("http://celeq.ucr.ac.cr;/","http://celeq.ucr.ac.cr;/") -> http://celeq.ucr.ac.cr;/ | V33: Carlos Araya Leandro | W33: 3-0305-0948 | X33: Casado | Y33: Costarricense | Z33: Doctor en Economía, Gestión y Control de Entidades y Políticas Públicas. | AA33: San José, Sede Univesitaria Rodrigo Facio, Edificio Administrativo B, Segundo Piso, Oficina de Rectoría, San Pedro de Montes de Oca | AC33: Rector de la U.C.R. | AD33: Licda. Marjorie Badilla | AE33: Fundevi | AF33: 2511-3217 | AG33: San José, Ciudad de la Investigación de la UCR, San Pedro de Montes de Oca | AH33: 2511-3211 | AI33: mbadillad@hotmail.com | AJ33: 8 a.m. a 4 p.m. | AK33: UCR | AL33: 2. Director del Organismo de Inspección: Ing. Eduardo HernándezQuesada
A34: Empresa Equipsa Tica S.A. | C34: OI | D34: N-P | E34: Privado | F34: OI-035 | I34: ='17020 SAI'!$H34+'17025 SAL'!$AN$1 -> 1460 | K34: N.A | L34: Roycers Urbina Cerna | M34: roycers@racsa.co.cr; equipsatica@racsa.co.cr | O34: 2235-5607/ 8919-4852 | P34: 2297-5181 | Q34: Costa Rica | R34: Tibas, 400 norte del cruce de Colima, costado este de la plaza de deportes | AK34: Empresa Equipsa Tica S.A.
A35: DISTRIBUIDORA CHERSOL SOLUCIONES | C35: OI | D35: N-P | E35: Privado | F35: OI-036 | I35: ='17020 SAI'!$H35+'17025 SAL'!$AN$1 -> 1460 | K35: N.A | L35: Ing. Randall Gonzalez Uribe | M35: rginspecciones@gmail.com | O35: 2268-3835 | P35: 2659-8155 | Q35: Costa Rica | R35: San Isidro de Heredia | AK35: DISTRIBUIDORA CHERSOL SOLUCIONES
A36: Equigas de Costa Rica S.A. | C36: OI | D36: N-P | E36: Privado | F36: OI-037 | I36: ='17020 SAI'!$H36+'17025 SAL'!$AN$1 -> 1460 | K36: N.A | L36: Darin Serrano Bolaños | M36: dserrano@equigascr.com; info@equigascr.com; dvarela@equigascr.com | O36: 2258-3774/ 2256-0948 | P36: 2233-3438 | Q36: Costa Rica | R36: Calle 2, avenida 16 y 18 | AK36: Equigas de Costa Rica S.A.
A37: FOMMOR S.A. | C37: OI | D37: N-P | E37: Privado | F37: OI-038 | I37: ='17020 SAI'!$H37+'17025 SAL'!$AN$1 -> 1460 | K37: N.A | L37: José Gabriel Fonseca Mora | M37: jgfonseca86@gmail.com; fommor@gmail.com; | O37: 2443-3787 | P37: 2441-3891 | Q37: Costa Rica | R37: Desamparados de Alajuela, 250 mts oeste del Colegio de Licenciados y Profesores | T37: 3-101-115827 | AK37: FOMMOR S.A.
A38: Instituto Dominicano del Café, INDOCAFE | C38: OI | D38: R | E38: Privado | F38: OI-039 | G38: OI-029 | I38: ='17020 SAI'!$H38+'17025 SAL'!$AN$1 -> 1460 | J38: 41079 | K38: N.A | L38: Omar Peña De Coo | M38: opena@codocafe.gob.do | N38: opena.proca2@gmail.com; | O38: (001 809) 532-9358, 532-9413 | P38: (001 809) 535-3894 | Q38: República Dominicana | R38: República Dominicana, Calle Rafael Damirón, esquina Avenida Comandante Jiménez Moya, Santo Domingo | S38: Santo Domingo | T38: 4-24-00057-3 | U38: www.codocafe.gov.do | V38: Marino Suarez Joran | W38: 048-0010264-4 | X38: casado | Y38: Dominicano | Z38: Ingeniero Agrónomo | AA38: Santo Domingo, Calle Francisco Prats Ramírez #251, Ensanche Evaristo Morales, República Dominicana | AC38: Director Ejecutivo | AD38: Natalia Pena | AE38: Consejo Dominicano del Café | AF38: (001 809)532-9358 | AG38: Santo Domingo, Av. Independencia, Esq. Larimar #58, km 7 1/2 de la Sanchez | AH38: (809)535-3894 | AI38: =HYPERLINK("mailto:info@codocafe.gob.do","info@codocafe.gob.do") -> info@codocafe.gob.do | AJ38: L/V 8:00 am-4:00pm | AK38: CODOCAFE | AL38: Todos los correos se deben enviar con copia a todos los destinatarios
A39: Total Quality Services S.A con razón comercial Total Quality Inspections. | C39: OI | D39: R | E39: Privado | F39: OI-040 | G39: OI-031 | I39: ='17020 SAI'!$H39+'17025 SAL'!$AN$1 -> 1460 | J39: 41590 | K39: N.A | L39: Ing. Francisco de la Barrera | M39: =HYPERLINK("mailto:inspecciones@tqspanama.com","inspecciones@tqspanama.com; fdelabarrera@tqspanama.com;") -> inspecciones@tqspanama.com; fdelabarrera@tqspanama.com; | O39: (507) 6671-1766 | P39: (507) 2792-866 | Q39: Panamá | R39: Centro Comercial Plaza Aventura, Oficina 425, Bethania Panamá | T39: 1615902-1-669292 DV 80 | U39: NA | V39: Erick Reinaldo Aparicio Cerrud | W39: 7-46-315 | X39: Casado | Y39: Panameño | Z39: Lienciado en Contabilidad | AA39: Corregimiento de Bethania – Centro Comercial Plaza Aventura – Oficina 425 | AC39: Presidente de la organización | AD39: Kirenia Arjona P. | AE39: TOTAL QUALITY SERVICES, S.A. | AF39: (507) 2792865 | AG39: Centro Comercial Plaza Aventura, Oficina 425, Bethania, Panamá. | AH39: (507) 2792865 | AI39: =HYPERLINK("mailto:karjona@tqspanama.com;","karjona@tqspanama.com;") -> karjona@tqspanama.com; | AJ39: Lunes a viernes de 8:00 a 5:00 y sábados de 8:00 a12:00 | AK39: Total Quality Services S.A con razón comercial Total Quality Inspections. | AL39: 27.01.2015, retiro voluntario de acreditación Todas las comunicaciones deben darse con el nombre tal y como aparece en el Directorio OEC.
A40: Camacho y Mora | C40: OI | D40: N-P | E40: Privado | F40: OI-041 | I40: ='17020 SAI'!$H40+'17025 SAL'!$AN$1 -> 1460 | L40: Ing. José Manuel Camacho Castro | M40: =HYPERLINK("mailto:jcamacho@camachoymora.com","jcamacho@camachoymora.com; cym@camachoymora.com") -> jcamacho@camachoymora.com; cym@camachoymora.com | O40: 2253-0552 | P40: 2280-5587 | Q40: Costa Rica | R40: Los Yoses Sur, de la Boutique Arenas 600m sur | T40: 3- 101-080419 | U40: =HYPERLINK("http://www.camachoymora.com/","www.camachoymora.com") -> www.camachoymora.com | V40: José Manuel Camacho Castro | W40: 1-0707-0194 | Y40: Costarricense | Z40: Ingeniero Civil | AC40: Representatante Legal | AE40: Camacho y Mora S.A. | AF40: 2253-0552 | AG40: Los Yoses Sur, de Boutique Arenas 600 m al sur | AH40: 2280-7785 | AK40: Camacho y Mora
A41: Organismo de Inspección Desarrollos Latinoamericanos de Metrología Integrada | B41: Desarrollos Latinoamericanos de Metrología Integrada Sociedad Anónima | C41: OI | D41: A | E41: Privado | F41: OI-042 | G41: OI-032 | H41: 44237 | I41: ='17020 SAI'!$H41+'17025 SAL'!$AN$1 -> 45697 | J41: 42122 | K41: N.A | L41: Emanuel Quirós Gamboa | M41: emanuel.quiros@dmimetrologia.com | N41: equiros@dmimetrologia.com | O41: 2288-3160 | P41: 2288-3159 | Q41: Costa Rica | R41: San José, del AyA 100 metros Sur, en la intersección de calle 138 con avenida 32, Escazú centro. | S41: San José | T41: 3-101-403462 | U41: =HYPERLINK("http://www.dmimetrologia.com/","www.dmimetrologia.com") -> www.dmimetrologia.com | V41: Edwin Manuel Quirós Villalobos | W41: 1-0486-0945 | Y41: Costarricense | Z41: Ingeniero Industrial | AC41: Gerente | AD41: Carol Duarte Guzmán | AE41: Desarrollos Latinoamericanos de Metrologia Integrada S.A. | AF41: 22-88-31-60 | AG41: San José, 100 al Oeste de la Agencia del Banco Nacional, Escazú. | AH41: 22-88-31-59 | AI41: administrativofinanciero@dmimetrologia.com | AJ41: de L a V de 8:00 am a 5 pm. | AL41: 16.11.2018 Levantamiento de suspención total del alacance / 07.07.2015 levantamiento de fecha condicionante de acreditación inicial. 28.04.2015 Acreditación inicial condicionada por un período no prorrogable de tres meses, vigencia de la acreditación a partir del 28 de abril de 2015 y hasta el 28 de julio de 2015
A42: Área de Inspección del Laboratorio Nacional de Aguas AyA. | B42: Instituto Costarricense de Acueductos y alcantarillados | C42: OI | D42: A | E42: Público | F42: OI-043 | G42: OI-033 | H42: 44159 | I42: ='17020 SAI'!$H42+'17025 SAL'!$AN$1 -> 45619 | J42: 42381 | L42: Ilena Vega Guzmán | M42: ivega@aya.go.cr | N42: nalfaro@aya.go.cr | O42: 2242-5000, ext. 6538 | P42: 2279-5973 | Q42: Costa Rica | R42: Cartago, 400 metros Norte de la Municipalidad de Tres Ríos, La Unión . | S42: Cartago | T42: 4000-042138-04 | U42: =HYPERLINK("http://www.aya.go.cr/","http://www.aya.go.cr/") -> http://www.aya.go.cr/ | V42: José Alberto Moya Segura | W42: 1-0538-0956 | X42: Casado | Y42: Costarricense | Z42: Ingeniero Industrial | AA42: Cartago, 400 Norte de la Municipalidad de Tres Ríos, La Unión | AC42: Gerente General. | AE42: Laboratorio Nacional de Aguas, AyA | AG42: Cartago, 400 Norte de la Municipalidad de Tres Ríos, La Unión . | AH42: 22795118 | AK42: Instituto Costarricense de Acueductos y Alcantarillados
A43: Area de Inspección y Verificación de la Calidad, de la Dirección de Calidad e Inocuidad del Consejo Nacional de Producción (CNP) | B43: Consejo Nacional de Producción | C43: OI | D43: A | E43: Público | F43: OI-044 | G43: OI-034 | H43: 45882 | I43: No aplica | J43: 42458 | L43: Hanzel Rodríguez Jiménez | M43: hrodriguez@cnp.go.cr | N43: acordoba@cnp.go.cr; mgonzaleza@cnp.go.cr, hanselrodriguezj@gmail.com | O43: 2265 3338 2265 3337 | Q43: Costa Rica | R43: Heredia, Planta la China, San Joaquín de Flores. | S43: Heredia | T43: 4-000-042146 | U43: http://web.cnp.go.cr; | V43: José Claudio Fallas Cortés | W43: 109970582 | X43: Viudo | Y43: Costarricense | Z43: Licenciado en Administración de empresas | AA43: Edificio Caycur, calle 88 Boulevar Ernesto Rohrmoser, Pavas, San José | AB43: gerencia@cnp.go.cr jfallasc@cnp.go.cr | AC43: Gerente General | AD43: Hansel Rodríguez Jiménez, | AE43: Consejo Nacional de Produccion | AF43: 2265-3338 | AG43: San José, 100 Sur del almacén Yamuni, Sabana este. | AH43: 2257-9355 | AI43: hrodriguez@cnp.go.cr; hanselrodriguezj@gmail.com | AJ43: Lunea a Viernes de 7:30am a 3:45pm | AK43: Consejo Nacional de Produccion
A44: Dirección de Medicamentos Veterinarios (SENASA) | B44: Servicio Nacional de Salud Animal | C44: OI | D44: R | E44: Público | F44: OI-045 | G44: OI-036 | I44: ='17020 SAI'!$H44+'17025 SAL'!$AN$1 -> 1460 | J44: 43040 | L44: Tatiana Leal Barrantes | M44: tleal@senasa.go.cr | N44: tatilealbtes@gmail.com | O44: 2587-1728/2587-1726 | P44: 2262-0221 | Q44: Costa Rica | R44: Heredia, de Jardínes del Recuerdo, 1kilometro oeste y 400 metros norte, Campus Benjamín Nuñez, Barreal | S44: Heredia | T44: 3-007-475726 | U44: =HYPERLINK("http://www.senasa.go.cr/","www.senasa.go.cr") -> www.senasa.go.cr | V44: Federico Chaverri Suárez | W44: 1-0806-0534 | Y44: Costarricense | Z44: Médico veterinario | AA44: Heredia, de Jardínes del Recuerdo, 1km oeste y 400 m norte, Campus Benjamín Nuñez, Barreal | AC44: Director General | AD44: NA | AE44: NA | AF44: NA | AG44: NA | AH44: NA | AI44: NA | AJ44: NA | AK44: SENASA
A45: Soluciones de Evaluación de Conformidad y Competitividad Limitada (SECC) | C45: OI | D45: R | E45: Privado | F45: OI-046 | I45: ='17020 SAI'!$H45+'17025 SAL'!$AN$1 -> 1460 | J45: 42908 | L45: Sergio Coto Hernández | M45: servicioalcliente@secc.co.cr | N45: coto.sergio@gmail.com; scoto@secc.co.cr; lmora@secc.co.cr | O45: 8844-5667 | P45: NA | Q45: Costa Rica | R45: Cartago, 300 m Sur de la plaza de deportes del barrio La Pitahaya, Agua Caliente, San Francisco | S45: Cartago | T45: 3-101-723747 | U45: www.sec.co.cr | V45: Sergio Coto Hernández | W45: 3-0371-0477 | X45: Casado | Y45: Costarricense | Z45: Ingeniero en producción industrial | AA45: Cartago, 300 m Sur de la plaza de deportes del barrio La Pitahaya, Agua Caliente, San Francisco | AC45: Gerente | AD45: Sergio Coto Hernández/Laura Mora Mora | AE45: Soluciones de Evaluación de Conformidad Limitada | AF45: 8844-5667 | AG45: Cartago, 300 m Sur de la plaza de deportes del barrio La Pitahaya, Agua Caliente, San Francisco | AH45: NA | AI45: servicioalcliente@secc.co.cr; coto.sergio@gmail.com | AK45: Soluciones de Evaluación de Conformidad Limitada | AL45: 09.07.2018 Retiro de la acreditación de manera voluntaria
A46: Soluciones de Evaluación de Conformidad y Competitividad Limitada (SECC) | C46: OI | D46: R | E46: Privado | I46: ='17020 SAI'!$H46+'17025 SAL'!$AN$1 -> 1460 | V46: Laura Mora Mora | W46: 1-1408-0201 | X46: Soltera | Y46: Costarricense | Z46: Ingeniera industrial | AC46: Gerente
A47: Centro de Investigación en Vivienda y Construcción-CIVCO | B47: Instituto Tecnológico de Costa Rica | C47: OI | D47: A | E47: Público | F47: OI-047 | G47: OI-037 | H47: 45385 | I47: ='17020 SAI'!$H47+'17025 SAL'!$AN$1 -> 46845 | J47: 43040 | K47: LE-037-A01 | L47: Giannina Ortiz Quesada | M47: civco@tec.ac.cr | N47: gortiz@tec.ac.cr; avillalobos@itcr.ac.cr | O47: 2550-2309 | P47: NA | Q47: Costa Rica | R47: Cartago, 400 m este, Estadio Fello Meza, (Sede Central I.T.C.R.) | S47: Cartago | T47: 4-000-042145 | U47: www.tec.ac.cr | V47: Luis Paulino Méndez Badilla | W47: 1-0499-0080 | X47: casado | Y47: costarricense | Z47: Ingeniero en Electrónica | AA47: Cartago, 400 este, Estadio Fello Meza, (Sede Central I.T.C.R.) | AC47: Rector | AE47: Fundación Tecnológica FUNDATEC | AK47: Instituto Tecnológico de Costa Rica
A48: Grupo Roading Consulters S.A. | B48: Grupo Roading Consulters Sociedad Anónima | C48: OI | D48: R | E48: Privado | F48: OI-048 | G48: OI-038 | I48: ='17020 SAI'!$H48+'17025 SAL'!$AN$1 -> 1460 | J48: 43054 | L48: Lucía Chaverrí Morales | M48: chaverrilucia@gmail.com | N48: jnunez@gruporoading.com | O48: 4030-3753/8705-8265 | P48: NA | Q48: Costa Rica | R48: San José, Condominio Parques del Sol 138, Santa Ana | S48: San José | T48: 3-101-449436 | U48: NA | V48: Lucia Chaverri Morales | W48: 1-1162-0366 | X48: Casada una vez | Y48: Costarricense | Z48: Administradora de empresas | AA48: San José, Condominio Parques del Sol 138, Santa Ana | AC48: Directora | AE48: Grupo Roading Consulters S.A. | AF48: 4030-3753/8702-8311 | AG48: San José, Condominio Paques del Sol, casa No. 138, Santa Ana | AH48: NA | AK48: Grupo Roading Consulters S.A. | AL48: Retiro de acreditación 2021.02.16
A49: Balanzas Ballar Costa Rica S.A. | B49: Balanzas Ballar Costa Rica S.A. | C49: OI | D49: R | E49: Privado | F49: OI-049 | G49: OI-039 | I49: ='17020 SAI'!$H49+'17025 SAL'!$AN$1 -> 1460 | J49: 43350 | L49: Paula Hernández | M49: rballar@ice.co.cr | N49: phernandez@romanasballar.com; | O49: 2297-4000 | P49: 2235-7348 | Q49: Costa Rica | R49: San José, de ferretería EPA 175 m Oeste, Colima de Tibás | S49: San José | T49: 3-101-708048 | U49: www.balanzasballar.com | V49: Jorge Eduardo Ballar González | W49: 9-048-991 | X49: Casado | Y49: Costarricense | Z49: Comerciante | AA49: San José, 175 m Oestede ferretería EPA, Colima de Tibás | AC49: Gerente General | AE49: Balanzas Ballar Costa Rica S.A | AF49: 2297-4000 | AG49: San José, 175 m Oestede ferretería EPA, Colima de Tibás | AH49: 2235-7348 | AJ49: Lunes, Martes y Miercoles de 8:00 am a 4:00 pm | AL49: Retiro de la acreditación 2021.04.12
A50: Chaso del Valle S.A. | B50: Chaso del Valle Sociedad Anónima | C50: OI | D50: A | E50: Privado | F50: OI-050 | G50: OI-040 | H50: 45394 | I50: ='17020 SAI'!$H50+'17025 SAL'!$AN$1 -> 46854 | J50: 43403 | L50: Adriana Fonseca | M50: servicioalcliente@chaso.com | N50: afonseca@chaso.com | O50: 4001-5915 | P50: 4001-6460 | Q50: Costa Rica | R50: 125 m norte del San José Palacios, contiguo a Meco. | S50: San José | T50: 3-101-151258 | U50: www.chaso.com | V50: Francisco José Soto Sagot | W50: 1-0783-0445 | X50: Casado | Y50: Costarricense | Z50: Comerciante | AA50: San José, 200 norte, 150 oeste de Torre Mercedes, contiguo a Funeraria Magisterio, Barrio Pitahaya | AC50: Representante legal
A51: ITP - Organismo de Inspección | B51: Ingeniería Técnica de Proyectos ITP S.A | C51: OI | D51: A-S | E51: Privado | F51: OI-056 | G51: OI-043 | H51: 43938 | I51: ='17020 SAI'!$H51+'17025 SAL'!$AN$1 -> 45398 | J51: 43734 | L51: Ing. Shirleny Salas Picado | M51: shirleny.salas@itp.cr | O51: 2220-1400 Ext. 2009 / 2010 | P51: 2290-9295 | Q51: Costa Rica | R51: Frente al ampm de la Uruca, contiguo a Repretel canal 6, edificio gris con naranja | S51: San José | T51: 3-101-362220 | U51: www.itp.cr | V51: Ing. Oscar Martínez Martínez | W51: 3-0276-0787 | X51: Casado | Y51: Costarricense | Z51: Ing. Civil | AA51: Frente al ampm de la Uruca, contiguo a Repretel canal 6, edificio gris con naranja | AC51: Gerente General | AE51: ITP - Ingeniería de Proyectos ITP S.A | AF51: 2220-1400 Ext. 2013 | AG51: La Uruca, San José, Costa Rica, transversal 72, diagonal a supermercado ampm | AI51: facturacioncxp@itp.cr ; | AK51: ITP - Ingeniería Técnica de Proyectos ITP S.A
A52: Escuela de Ingeniería Química - UCR | B52: Universidad de Costa Rica | C52: OI | D52: R | E52: Académico | F52: OI-051 | G52: OI-042 | I52: ='17020 SAI'!$H52+'17025 SAL'!$AN$1 -> 1460 | J52: 43647 | L52: Esteban Durán Herrera | M52: esteban.duranherrera@ucr.ac.cr | N52: paula.solano@ucr.ac.cr | O52: 2511-6640 | P52: 2225-2622 | Q52: Costa Rica | R52: San José, Ciudad Universitaria Rodrigo Facio, Facultad de Ingeniería, Edificio de la torre, 5to piso, San Pedro | S52: San José | T52: 4-000-042149 | U52: eiq@ucr.ac.cr | V52: Gustavo Gutiérrez Espeleta | W52: 1-660-352 | X52: Divorciado | Y52: costarricense | Z52: Doctor en Biología con especialidad en Genética | AA52: San José, Sede Univesitaria Rodrigo Facio, Edificio Administrativo B, Segundo Piso, Oficina de Rectoría, San Pedro de Montes de Oca | AC52: Rector de la U.C.R. | AE52: Fundación de la Universidad de Costa Rica | AF52: 2511-1777 | AG52: San José, Ciudad Universitaria Rodrigo Facio, San Pedro de Montes de Oca, | AL52: Retiro voluntario de la acreditación 2021.05.25
A53: Asociación Cámara Nacional de Productores y Exportadores de Piña - CANAPEP-OI | B53: Asociación Cámara Nacional de Productores y Exportadores de Piña - CANAPEP-OI | C53: OI | D53: A | E53: Privada | F53: OI-052 | G53: OI-044 | H53: 45394 | I53: ='17020 SAI'!$H53+'17025 SAL'!$AN$1 -> 46854 | J53: 43914 | L53: Stephanie Rodríguez Hidalgo | M53: srodriguez@canapep.com | N53: amunoz@canapep.com | O53: 22915237 | P53: 22915229 | Q53: Costa Rica | R53: San José, del Scotiabank 100 m Norte y 50 m Oeste, Sabana Norte | S53: San José | T53: 3-002-355854 | U53: www.canapep.com | V53: Abel Chaves Trigueros | W53: 202590468 | X53: Casado | Y53: Costarricense | Z53: Licenciado en ciencias económicas | AA53: San José, del Scotiabank 100 m Norte y 50 m Oeste, Sabana Norte | AC53: Presidente | AD53: Rebeca Sequeira/Antonella Bonanni | AE53: Cámara Nacional de Productores y Exportadores de Piña | AF53: 22915237 | AG53: San José, del Scotiabank 100 m Norte y 50 m Oeste, Sabana Norte | AH53: 22915229 | AI53: info@canapep.com | AJ53: Lunes a viernes de 8am a 5pm | AK53: Cámara Nacional de Productores y Exportadores de Piña
A54: BSS S.R.L. | B54: BSS Ingeniería Consultoría e Inspecciones SRL | C54: OI | D54: A | E54: Privada | F54: OI-053 | G54: OI-041 | H54: 45482 | I54: N/A | J54: 43620 | K54: OI-041-A01 | L54: Marcela Fernández Mora Michel González Yendry Elizondo Quirós | M54: mfernandez@bss.cr | N54: mgonzalez@bss.cr; yendry@bss.cr; info@bss.cr | O54: 4001-6261 / 83851598 | P54: No aplica | Q54: Costa Rica | R54: PROVINCIA 01 SAN JOSÉ, CANTÓN 02 ESCAZÚ, SAN RAFAEL, BELLO HORIZONTE, RESIDENCIAL LOS ELISEOS, CASA NÚMERO CUARENTA | S54: San José | T54: 3-102-498029 | U54: https://bss.cr/ | V54: Marcela de los Ángeles Fernández Mora | W54: 1-1350-0129 | X54: Divorciada | Y54: Costarricense | Z54: Ingeniera en producción industrial | AA54: San José, Montes de Oca, San Pedro, Residencial Lugano, Timbre 17 | AB54: mfernandez@bss.cr | AC54: Gerente | AD54: Gestión Financiera | AE54: Marcela de los Ángeles Fernández Mora | AF54: 4001-6261 | AG54: San José, Montes de Oca, San Pedro, Urbanización Lugano | AH54: No aplica | AI54: info@bss.cr; mfernandez@bss.cr | AJ54: 8:00 am - 5:00 pm | AK54: Blue Sky Services SRL
A55: Organismo de Inspección del Laboratorio Nacional de Materiales y Modelos Estructurales - UCR | B55: Universidad de Costa Rica | C55: OI | D55: A | E55: Publica | F55: OI-054 | G55: OI-045 | H55: 45147 | I55: ='17020 SAI'!$H55+'17025 SAL'!$AN$1 -> 46607 | J55: 43927 | K55: A01: 13/01/2025 | L55: Alejandro Navas Carro Humberto Tioli Mora | M55: Direccion.lanamme@ucr.ac.cr; Jose.tioli@ucr.ac.cr | N55: emmanuel.badilla@ucr.ac.cr; maria.castrosoto@ucr.ac.cr | O55: 2511-2500/2511-2531 | Q55: Costa Rica | R55: San José, 500 m Norte de Supermercado Muñoz & Nanne, Ciudad de la Investigación, Universidad de Costa Rica, San Pedro de Montes de Oca. | S55: San José | T55: 4-000-042149 | U55: http://www.lanamme.ucr.ac.cr/ | V55: Carlos Araya Leandro | W55: 3-0305-0948 | X55: Casado | Y55: Costarricense | Z55: Doctor en Economía, Gestión y Control de Entidades y Políticas Públicas. | AA55: San José, Universidad de Costa Rica, Sede Rodrigo Facio, contiguo a la Fac. de Ciencias Agroalimentarias, San Pedro de Montes de Oca. | AC55: Rector Universidad de Costa Rica | AD55: Ing. Humberto Tioli | AE55: Universidad de Costa Rica | AF55: 2511-2500/2511-2531 | AG55: San José, Universidad de Costa Rica, Sede Rodrigo Facio, contiguo a la Fac. de Ciencias Agroalimentarias, San Pedro de Montes de Oca. | AI55: jose.tioli@ucr.ac.cr; maria.castrosoto@ucr.ac.cr; randall.valle@ucr.ac.cr; facturacionelectronica.lanamme@ucr.ac.cr; emmanuel.badilla@ucr.ac.cr | AJ55: 8:00 a.m a 5:00 p.m. | AK55: Universidad de Costa Rica
A56: Proeléctrica de Centroamérica S.A. | B56: PROELÉCTRICA DE CENTROAMÉRICA S.A. | C56: OI | D56: A | E56: Privada | F56: OI-055 | G56: OI-061 | H56: 44322 | I56: ='17020 SAI'!$H56+'17025 SAL'!$AN$1 -> 45782 | J56: 44670 | L56: Seidy Ortega, Denic Murillo Murillo | M56: seidy@proelectrica.net, dmurillo@proelectrica.net | N56: info@proelectrica.net | O56: 2460-2901/8366-6151 | P56: 2460-2109 | Q56: Costa Rica | R56: San Carlos, Quesada, Hogar de Ancianos, detrás de las oficinas del ICT, 2da planta edificio color blanco. | S56: Alajuela | T56: 3-101-399003 | U56: www.proelectrica.net | V56: Denic Danay Murillo Murillo | W56: 205490010 | Y56: Costarricense | Z56: Ingeniero Electricista | AA56: Alajuela, detrás de la oficina del ICT, Ciudad Quesada, San Carlos. | AC56: Gerente | AE56: Proeléctrica de Centroamérica S.A. | AF56: 2460-2109 | AG56: Alajuela, detrás de la oficina del ICT, Ciudad Quesada, San Carlos. | AH56: 2460-2109 | AI56: dann@proelectrica.net; dmurillo@proelectrica.net | AK56: Proeléctrica de Centroamérica S.A.
A57: LGC Ingeniería de Pavimentos S.A. | B57: LGC Ingeniería en Pavimentos, Sociedad Anónima | C57: OI | D57: A | E57: Privado | F57: OI-057 | G57: OI-057 | H57: 45142 | I57: ='17020 SAI'!$H57+'17025 SAL'!$AN$1 -> 46602 | J57: 44265 | K57: NA | L57: José Luis Loría Álvarez | M57: jloria@lgcingenieria.net | N57: Ing. Amed Aldi Bolaños amedaldi@lgcingenieria.net | O57: 2270-55-54 / 2270-55-55 | P57: 2219-8035 | Q57: Costa Rica | R57: Dirección: Desamparados, San Miguel, San José, Costa Rica, de la entrada de Casa Cuba 400 metros este edificio a mano derecha color terracota. | S57: San José | T57: 3-101-303726 | U57: N/A | V57: LUIS GUILLERMO CHAVARRIA BRAVO | W57: 1-680-947 | X57: Casado | Y57: Costarricense | Z57: Lic.Ing. Civil | AA57: Dirección: Desamparados, San Miguel, San José, Costa Rica, de la entrada de Casa Cuba 400 metros este edificio a mano derecha color terracota. | AC57: Gerente General | AD57: Carlos Montero Godinez | AE57: LGC INGENIERIA DE PAVIMENTOS .A. | AF57: 2270-0555/2270-0331/ 2270-0538 | AG57: Dirección: Desamparados, San Miguel, San José, Costa Rica, de la entrada de Casa Cuba 400 metros este edificio a mano derecha color terracota. | AH57: 2219-8035 | AI57: =HYPERLINK("mailto:lgcingenieriadepavimentos@gmail.com","calidadlgc@gmail.com; lgcingenieriadepavimentos@gmail.com") -> calidadlgc@gmail.com; lgcingenieriadepavimentos@gmail.com | AJ57: De L a V de 730 a.m. a 5:00 p.m./sabados de 7:30 a.m. a 11:00 a.m. | AK57: LGC Ingeniería de Pavimentos S.A.
A58: Laboratorio de Inspección RECOPE | B58: Refinadora Costarricense de Petroleo | C58: OI | D58: A | E58: Público | F58: OI-058 | G58: OI-058 | H58: 45378 | I58: ='17020 SAI'!$H58+'17025 SAL'!$AN$1 -> 46838 | J58: 44355 | K58: A01: 17/01/2023 A02: 25/11/2024 | L58: Roberto Coto Rojas / Lorena Acosta Solís. | M58: sg.metrologia@recope.go.cr | N58: labmetrologia@recope.go.cr | O58: 2550-3750 | P58: N.A. | Q58: Costa Rica | R58: Departamento de Metrología, Palntel El Alto de Ochomogo, kilometro 12, Ruta 2, Ochomogo San Nicolas, Cartago. | S58: Cartago | T58: 3-101-007749 | U58: www.recope.go.cr | V58: Max Umaña Hidalgo | W58: 107450632 | X58: Casado | Y58: Costarricense | Z58: Ingeniero Civil | AA58: San José, Goicochea, San Francisco, Tournón, calle 108, Ruta 32, km 0, Edificio Hernán Garrón, contiguo al Puesto de Bolsa del Banco Nacional | AC58: Apoderado | AD58: José Abilio Serrano | AE58: RECOPE | AF58: 2284-2700 ext.: 4516 | AG58: San José, Goicochea, San Francisco, Tournón, calle 108, Ruta 32, km 0, Edificio Hernán Garrón, contiguo al Puesto de Bolsa del Banco Nacional | AH58: NA | AI58: joseabilio.serrano@recope.go.cr | AJ58: De L a V de 07:00 a.m. a 03:00 p.m. | AK58: Refinadora Costarricense de Petroleo
A59: Organismo de Inspección de la Cámara de Empresarios del Combustible | B59: Cámara de Empresarios del Combustible | C59: OI | D59: A | E59: Privado | F59: OI-059 | G59: OI-059 | H59: 44210 | I59: ='17020 SAI'!$H59+'17025 SAL'!$AN$1 -> 45670 | J59: 44995 | K59: A01: 07/04/2025 | L59: Pablo Guzmán Trejos | M59: pguzman@empresariosdelcombustible.com | N59: info@empresariosdelcombustible.com | O59: 2232-4575 | P59: 2220-4391 | Q59: Costa Rica | R59: San Jose, Mata Redonda, Rancho Luna, calle 70, Sabana Oeste, del restaurante Princesa Marina, 200 m oeste, casa esquinera portón negro. | S59: San José | T59: 3-002-056477 | U59: www.empresariosdelcombustible.com | V59: Alberto Geradro Mesen Madrigal | W59: 1-0395-0803 | X59: Casado | Y59: Costarricense | Z59: Empresario | AA59: San Jose, Mata Redonda, Rqancho Luna, calle 70, Sabana Oeste, del restaurante Princesa Marina, 200 m oeste, casa esquinera portón negro. | AC59: Presidente | AD59: Departamento Contable | AE59: Emilia Chaverri Saborío | AF59: 2231-4575 ext.: 2 | AG59: San Jose, Mata Redonda, Rqancho Luna, calle 70, Sabana Oeste, del restaurante Princesa Marina, 200 m oeste, casa esquinera portón negro. | AH59: 2220-4391 | AI59: echaverri@aceccr.com / facturas@aceccr.com | AJ59: De 8:00 am a 5:00 pm | AK59: Cámara de Empresarios del Combustible
A60: Organismo de Inspección de Programa de Estudios en Calidad, Ambiente y Metrología PROCAME | B60: Universidad Nacional | C60: OI | D60: N-P | E60: Publico | F60: OI-060 | I60: ='17020 SAI'!$H60+'17025 SAL'!$AN$1 -> 1460 | L60: Karla Vetrani Chavarría | M60: procame@una.cr | N60: Karla.vetrani.chavarria@una.cr | O60: 22777-3448 | P60: N.A. | Q60: Costa Rica | R60: Heredia, Universidad Nacional, Campus Omar Dengo, 3 er piso Escuela de Ciencias Ambientales, Heredia. | S60: Heredia | T60: 4-000-042150-14 | U60: www.procame.una.ac.cr | V60: Francisco González Alvarado | W60: 204510487 | X60: casado | Y60: Costarricense | Z60: Historiador y educador | AA60: Heredia, Universidad Nacional, Edificio Rectoria | AC60: Rector | AE60: Karla Vetrani Chavarría | AF60: 2277-3448 | AG60: Heredia, Universidad Nacional, Campus Omar Dengo, 3 er piso Escuela de Ciencias Ambientales, Heredia. | AH60: N.A. | AI60: procame@una.cr | AJ60: Lunes a viernes, 8:00 a.m. a 12 m.d 1:00 pm. a 5:00 pm. | AK60: Procame
A61: Proeléctrica de Centroamérica S.A. | B61: Proeléctrica de Centroamérica S.A. | C61: OI | D61: N-P | E61: Privado | F61: OI-061 | H61: 43852 | I61: ='17020 SAI'!$H61+'17025 SAL'!$AN$1 -> 45312 | L61: Seidy Patricia Ortega Pérez | M61: dmurillo@proelectrica.net seidy@proelectrica.net | N61: info@proelectrica.net | O61: 2460-2109 | P61: 2460-2109 | Q61: Costa Rica | R61: Alajuela, San Carlos, Quesada, Hogar de Ancianos, detrás de las oficinas del ICT, 2da planta edificio color blanco | S61: Alajuela | T61: 3-101-399003 | U61: www.proelectrica.net | V61: Denic Danay Murillo Murillo | W61: 2-0549-0010 | X61: soltero | Y61: Costarricense | Z61: Ingeniero Electricista | AA61: Alajuela, San Carlos, Quesada, Hogar de Ancianos, detrás de las oficinas del ICT, 2da planta edificio color blanco | AC61: Gerente | AD61: Administrativo / Seidy Ortega Perez | AI61: fe@proelectrica.net | AJ61: De L-V de 8:00 am a 5:pm | AK61: Proeléctrica de Centroamérica S.A.
A62: Seléctrica | B62: Solís Eléctrica Sociedad Responsabilidad Limitada | C62: OI | D62: A | E62: Privado | F62: OI-062 | G62: OI-062 | H62: 44515 | I62: ='17020 SAI'!$H62+'17025 SAL'!$AN$1 -> 45975 | J62: 44915 | L62: Marianela Tenorio Wong | M62: marianela@selectrica.net | N62: info@selectrica.net | O62: 27104787 | P62: 27104875 | Q62: Costa Rica | R62: Costa Rica, Limón, Pococí, Guápiles, Guápiles, sobre Ruta 32, frente a la Terminal de Buses del Caribe, sobre ruta 32. | S62: Limón | T62: 3-102-176592 | U62: www.selectrica.net | V62: Luis Mariano Solís Vargas | W62: 2-0375-0053 | X62: casado | Y62: Costarricense | Z62: Ingeniero Electromecánico | AA62: Costa Rica, Limón, Pococí, Guápiles, Guápiles, sobre Ruta 32, frente a la Terminal de Buses del Caribe, sobre ruta 32 | AC62: Gerente | AD62: Crédito y Cobro / Dana Arias Montero | AI62: dana@selectrica.net | AJ62: De Lunes a Viernes de 7:00 A.M a 5:00 P.M | AK62: Selectrica | AL62: Otorgar la acreditación a Solís Eléctrica Sociedad Responsabilidad Limitada, cédula jurídica 3-102-176592, específicamente al Organismo de Inspección tipo C, Seléctrica, con expediente OI-062, según recomendación de la Secretaría de Acreditación SAI-021-2022 para las actividades de evaluación de la conformidad descritas en el siguiente cuadro y que fueron evaluadas según se indica en el informe de evaluación in situ o remota, por cumplir con los requisitos de la norma INTE-ISO/IEC 17020:2012 y los criterios de acreditación.
